Workbook

Sheet Forward EPS
A1: 표 1. ISC 실적 추이 및 전망
A3: ISC (095340) | 리서치 기준일 2026-02-04 | 단위는 각 표에 표시 | 하나증권 4Q25 Earnings Review 기준 (삼성증권·IM증권 자료는 참고)
A4: 입력/추정 가정: 연노랑 배경 + 파란 글씨 | 공시 자동 수집: 연청회색 배경 | 계산식: 검은 글씨 | 다른 시트 연결: 초록 글씨 | 미확보: 진한 회색
A5: 항목 | B5: 1Q25 | C5: 2Q25 | D5: 3Q25 | E5: 4Q25 | F5: 1Q26E | G5: 2Q26E | H5: 3Q26E | I5: 4Q26E | J5: 2025 | K5: 2026E | L5: 2027E
A6: 매출액 | B6: 31.68 | C6: 51.66 | D6: 64.52 | E6: 72.33 | F6: =SUM($F$7:$F$13) -> 66.4 | G6: =SUM($G$7:$G$13) -> 71 | H6: =SUM($H$7:$H$13) -> 77.2 | I6: =SUM($I$7:$I$13) -> 88.3 | J6: =SUM($B6:$E6) -> 220.19 | K6: =SUM($F6:$I6) -> 302.9 | L6: =SUM($L$7:$L$13) -> 373.1
A7: 데이터센터 | B7: 16.9 | C7: 33.1 | D7: 44 | E7: 54.4 | F7: 47.3 | G7: 50.6 | H7: 57.2 | I7: 62.9 | J7: =SUM($B7:$E7) -> 148.4 | K7: =SUM($F7:$I7) -> 218 | L7: 268.52
A8: 스마트폰 | B8: 9.5 | C8: 14 | D8: 13.5 | E8: 12 | F8: 9.6 | G8: 10.6 | H8: 10.6 | I8: 10 | J8: =SUM($B8:$E8) -> 49 | K8: =SUM($F8:$I8) -> 40.8 | L8: 50.26
A9: PC/Laptop | B9: 3.2 | C9: 3 | D9: 4.5 | E9: 3 | F9: 3.4 | G9: 3.5 | H9: 3.6 | I9: 3.4 | J9: =SUM($B9:$E9) -> 13.7 | K9: =SUM($F9:$I9) -> 13.9 | L9: 17.12
A10: 오토모티브 | B10: 1 | C10: 0.7 | D10: 1.5 | E10: 1.9 | F10: 3.3 | G10: 2.8 | H10: 3.4 | I10: 4.8 | J10: =SUM($B10:$E10) -> 5.1 | K10: =SUM($F10:$I10) -> 14.3 | L10: 17.61
A11: 웨어러블 | B11: 0.7 | C11: 0.7 | D11: 0.8 | E11: 1 | F11: 0.8 | G11: 0.8 | H11: 0.9 | I11: 0.9 | J11: =SUM($B11:$E11) -> 3.2 | K11: =SUM($F11:$I11) -> 3.4 | L11: 4.19
A12: LSI | B12: 0 | C12: 0 | D12: 0 | E12: 0 | F12: 0 | G12: 0 | H12: 0 | I12: 0 | J12: =SUM($B12:$E12) -> 0 | K12: =SUM($F12:$I12) -> 0 | L12: 0
A13: 기타 | B13: 0.4 | C13: 0.2 | D13: 0.2 | E13: 0 | F13: 2 | G13: 2.7 | H13: 1.5 | I13: 6.3 | J13: =SUM($B13:$E13) -> 0.8 | K13: =SUM($F13:$I13) -> 12.5 | L13: 15.4
A14: 매출액 YoY | B14: =($B$6/$B$31-1)*100 -> -9.6663815 | C14: =($C$6/$C$31-1)*100 -> 3.818328 | D14: =($D$6/$D$31-1)*100 -> 28.041278 | E14: =($E$6/$E$31-1)*100 -> 84.233316 | F14: =($F$6/$B$6-1)*100 -> 109.59596 | G14: =($G$6/$C$6-1)*100 -> 37.437089 | H14: =($H$6/$D$6-1)*100 -> 19.652821 | I14: =($I$6/$E$6-1)*100 -> 22.079358 | J14: =($J$6/$G$31-1)*100 -> 26.197845 | K14: =($K$6/$J$6-1)*100 -> 37.563014 | L14: =($L$6/$K$6-1)*100 -> 23.175966
A15: 매출액 QoQ | B15: =($B$6/$E$31-1)*100 -> -19.307183 | C15: =($C$6/$B$6-1)*100 -> 63.068182 | D15: =($D$6/$C$6-1)*100 -> 24.893535 | E15: =($E$6/$D$6-1)*100 -> 12.104774 | F15: =($F$6/$E$6-1)*100 -> -8.1985345 | G15: =($G$6/$F$6-1)*100 -> 6.9277108 | H15: =($H$6/$G$6-1)*100 -> 8.7323944 | I15: =($I$6/$H$6-1)*100 -> 14.378238
A16: 매출원가 | B16: 17.44 | C16: 29.11 | D16: 36.92 | E16: 38.98 | F16: 35.14 | G16: 37.57 | H16: 40.86 | I16: 46.73 | J16: =SUM($B16:$E16) -> 122.45 | K16: =SUM($F16:$I16) -> 160.3 | L16: 195.6
A17: 매출총이익 | B17: =$B$6-$B$16 -> 14.24 | C17: =$C$6-$C$16 -> 22.55 | D17: =$D$6-$D$16 -> 27.6 | E17: =$E$6-$E$16 -> 33.35 | F17: =$F$6-$F$16 -> 31.26 | G17: =$G$6-$G$16 -> 33.43 | H17: =$H$6-$H$16 -> 36.34 | I17: =$I$6-$I$16 -> 41.57 | J17: =$J$6-$J$16 -> 97.74 | K17: =$K$6-$K$16 -> 142.6 | L17: =$L$6-$L$16 -> 177.5
A18: 매출총이익률 | B18: =$B$17/$B$6*100 -> 44.949495 | C18: =$C$17/$C$6*100 -> 43.650794 | D18: =$D$17/$D$6*100 -> 42.777433 | E18: =$E$17/$E$6*100 -> 46.108116 | F18: =$F$17/$F$6*100 -> 47.078313 | G18: =$G$17/$G$6*100 -> 47.084507 | H18: =$H$17/$H$6*100 -> 47.072539 | I18: =$I$17/$I$6*100 -> 47.078143 | J18: =$J$17/$J$6*100 -> 44.388937 | K18: =$K$17/$K$6*100 -> 47.078244 | L18: =$L$17/$L$6*100 -> 47.574377
A19: 판매 및 일반관리비 | B19: =$B$17-$B$20 -> 7.25 | C19: =$C$17-$C$20 -> 8.84 | D19: =$D$17-$D$20 -> 10.18 | E19: =$E$17-$E$20 -> 11.42 | F19: =$F$17-$F$20 -> 10.66 | G19: =$G$17-$G$20 -> 11.93 | H19: =$H$17-$H$20 -> 13.64 | I19: =$I$17-$I$20 -> 12.67 | J19: =$J$17-$J$20 -> 37.69 | K19: =$K$17-$K$20 -> 48.9 | L19: =$L$17-$L$20 -> 52.4
A20: 영업이익 | B20: 6.99 | C20: 13.71 | D20: 17.42 | E20: 21.93 | F20: 20.6 | G20: 21.5 | H20: 22.7 | I20: 28.9 | J20: =SUM($B20:$E20) -> 60.05 | K20: =SUM($F20:$I20) -> 93.7 | L20: 125.1
A21: 영업이익률 | B21: =$B$20/$B$6*100 -> 22.064394 | C21: =$C$20/$C$6*100 -> 26.538908 | D21: =$D$20/$D$6*100 -> 26.99938 | E21: =$E$20/$E$6*100 -> 30.31937 | F21: =$F$20/$F$6*100 -> 31.024096 | G21: =$G$20/$G$6*100 -> 30.28169 | H21: =$H$20/$H$6*100 -> 29.404145 | I21: =$I$20/$I$6*100 -> 32.729332 | J21: =$J$20/$J$6*100 -> 27.271902 | K21: =$K$20/$K$6*100 -> 30.934302 | L21: =$L$20/$L$6*100 -> 33.529885
A22: 세전이익 | B22: 9.3 | C22: 13.51 | D22: 19.77 | E22: 24.01 | F22: 22.07 | G22: 23.04 | H22: 24.32 | I22: 30.97 | J22: =SUM($B22:$E22) -> 66.59 | K22: =SUM($F22:$I22) -> 100.4 | L22: 137.9
A23: 지배주주순이익 | B23: 6.83 | C23: 11.5 | D23: 16.07 | E23: 21.72 | F23: 17.94 | G23: 18.72 | H23: 19.77 | I23: 25.17 | J23: =SUM($B23:$E23) -> 56.12 | K23: =SUM($F23:$I23) -> 81.6 | L23: 112
A24: 지배주주순이익률 | B24: =$B$23/$B$6*100 -> 21.559343 | C24: =$C$23/$C$6*100 -> 22.260937 | D24: =$D$23/$D$6*100 -> 24.907006 | E24: =$E$23/$E$6*100 -> 30.029034 | F24: =$F$23/$F$6*100 -> 27.018072 | G24: =$G$23/$G$6*100 -> 26.366197 | H24: =$H$23/$H$6*100 -> 25.608808 | I24: =$I$23/$I$6*100 -> 28.505096 | J24: =$J$23/$J$6*100 -> 25.487079 | K24: =$K$23/$K$6*100 -> 26.939584 | L24: =$L$23/$L$6*100 -> 30.018762
A25: EPS (원) | B25: =$B$23*1000000/21197.1 -> 322.21389 | C25: =$C$23*1000000/21197.1 -> 542.52704 | D25: =$D$23*1000000/21197.1 -> 758.12257 | E25: =$E$23*1000000/21197.1 -> 1024.6685 | F25: =$F$23*1000000/21197.1 -> 846.34219 | G25: =$G$23*1000000/21197.1 -> 883.13967 | H25: =$H$23*1000000/21197.1 -> 932.67475 | I25: =$I$23*1000000/21197.1 -> 1187.4266 | J25: =$J$23*1000000/21197.1 -> 2647.532 | K25: =$K$23*1000000/21197.1 -> 3849.5832 | L25: =$L$23*1000000/21197.1 -> 5283.7416
A26: EPS YoY | B26: =($B$25/$B$32-1)*100 -> -56.744775 | C26: =($C$25/$C$32-1)*100 -> -27.989981 | D26: =($D$25/$D$32-1)*100 -> 44.384546 | E26: =($E$25/$E$32-1)*100 -> 84.380306 | F26: =($F$25/$B$25-1)*100 -> 162.66471 | G26: =($G$25/$C$25-1)*100 -> 62.782609 | H26: =($H$25/$D$25-1)*100 -> 23.024269 | I26: =($I$25/$E$25-1)*100 -> 15.883978 | J26: =($J$25/$G$32-1)*100 -> 2.6710574 | K26: =($K$25/$J$25-1)*100 -> 45.402708 | L26: =($L$25/$K$25-1)*100 -> 37.254902
A27: EPS QoQ | B27: =($B$25/$E$32-1)*100 -> -42.020374 | C27: =($C$25/$B$25-1)*100 -> 68.374817 | D27: =($D$25/$C$25-1)*100 -> 39.73913 | E27: =($E$25/$D$25-1)*100 -> 35.158681 | F27: =($F$25/$E$25-1)*100 -> -17.403315 | G27: =($G$25/$F$25-1)*100 -> 4.3478261 | H27: =($H$25/$G$25-1)*100 -> 5.6089744 | I27: =($I$25/$H$25-1)*100 -> 27.314112
A28: 밸류에이션 적용 EPS (원) | K28: 4025
A30: 전년 동기 비교 기준 — 2024년 분기·연간 확정치 (DART 연결 손익계산서)
A31: 매출액 (2024) | B31: 35.07 | C31: 49.76 | D31: 50.39 | E31: 39.26 | G31: 174.48
A32: EPS (2024, 원) | B32: =$B$33*1000000/21197.1 -> 744.91322 | C32: =$C$33*1000000/21197.1 -> 753.40495 | D32: =$D$33*1000000/21197.1 -> 525.07183 | E32: =$E$33*1000000/21197.1 -> 555.7364 | G32: =$G$33*1000000/21197.1 -> 2578.6546
A33: 지배주주순이익 (2024) | B33: 15.79 | C33: 15.97 | D33: 11.13 | E33: 11.78 | G33: 54.66
A35: 자료: ISC, 하나증권 4Q25 Earnings Review (2026.02.04), DART 정기보고서 | 금액 단위: 십억원, 비율 단위: %, EPS: 원
A36: 주) 시점 가정은 2025년 4분기 실적 리뷰를 쓰는 시점(2026.02.04)입니다. 따라서 2025년까지는 전부 확정치이고 2026년 네 개 분기와 2027년은 전부 애널리스트 추정 입력(연노랑)입니다.
A37: 주) 이 시트가 추정치의 유일한 입력 원천입니다. 다른 시트를 참조하지 않으며, 반대로 M1_실적추정_모델 · 15_p5_손익계산서의 2025F~2027F 열 · Target PER 이 이 시트의 값을 받아갑니다.
A38: 주) 2025년 확정치는 1Q25 분기보고서·반기보고서·3분기보고서·사업보고서의 연결 손익계산서에서 가져왔습니다 (4Q25 = 연간 − 3분기 누적). 분기 합계가 2025년 연간 확정치와 소수점까지 일치합니다.
A39: 주) 2026년 입력 기본값은 하나증권 도표 4 의 1Q26F~4Q26F 추정치 그대로입니다. 어플리케이션별 매출을 더한 연간 합계가 302.9십억원, 영업이익 합계가 93.7십억원으로 리포트 원문 추정 재무제표와 정확히 일치합니다. 매출원가·세전이익·지배주주순이익의 분기 배분은 연간 원문값(160.3 / 100.4 / 81.6)을 매출·영업이익 비중으로 나눈 값입니다.
A40: 주) 매출액은 어플리케이션 7개 항목의 합입니다. 2025년 확정 구간만 공시 매출을 직접 넣었습니다 (하나증권 도표 4 의 어플리케이션 반올림 합과 0.1 이내 차이).
A41: 주) 판매 및 일반관리비는 「매출총이익 − 영업이익」 수식입니다. 2025년 확정 구간에서 이 값이 공시 판관비(7.25 / 8.84 / 10.18 / 11.42십억원)와 정확히 일치합니다.
A42: 주) 리포트 발간 이후 실제로 발표된 1Q26 실적은 매출 68.27 · 영업이익 23.62 · 지배주주순이익 20.47십억원입니다 (잠정실적 공시 2026.04.27 및 1Q26 분기보고서). 리뷰 작성 시점 가정을 지키려고 이 시트에는 반영하지 않았고, 11_도표7_영업이익_시가총액 시트에서 확정치로 확인할 수 있습니다.
A43: 주) 밸류에이션 적용 EPS 4,025원은 하나증권 도표 1 기준값이며 Target PER 시트가 이 칸을 받아갑니다. 모델이 산출한 2026E EPS(3,850원)와 다른 것은 리포트가 12개월 선행 기준을 쓰기 때문입니다.
A44: 주) 참조 모델과 같이 비율은 % 기호 없는 숫자(예: 44.9 = 44.9%)로 저장했습니다.

Sheet Target PER
A1: Target PER 선정 및 목표주가 모델
A3: ISC (095340) | 리서치 기준일 2026-02-04 | 단위는 각 표에 표시 | 하나증권 4Q25 Earnings Review 기준 (삼성증권·IM증권 자료는 참고)
A4: 입력/추정 가정: 연노랑 배경 + 파란 글씨 | 공시 자동 수집: 연청회색 배경 | 계산식: 검은 글씨 | 다른 시트 연결: 초록 글씨 | 미확보: 진한 회색
A5: Target PER 선택 로직
A6: 선정 방식 | B6: 특정 피어 조정 | D6: 드롭다운에서 선택하세요 — 특정 피어 조정 / 피어 평균 / 피어 중앙값 / 직접 입력. 현재: WinWay 62.6배에서 30% 할인 → Target P/E 43.82배 (하나증권 도표 1과 동일)
A7: Forward EPS | B7: ='Forward EPS'!$K$28 -> 4025 | D7: Forward EPS 시트의 「밸류에이션 적용 EPS」 칸을 그대로 받아옵니다 (기본 4,025원).
A8: 선택 피어 | B8: WinWay | D8: 드롭다운에서 아래 피어 표의 기업 중 선택. 선정 방식이 '특정 피어 조정'일 때만 쓰입니다.
A9: 선택 피어 P/E | B9: =INDEX($C$22:$C$26,MATCH($B$8,$A$22:$A$26,0)) -> 62.6 | D9: WinWay 26년 예상 PER 62.6배 (하나증권 기준일 2026.02.04)
A10: 할인/프리미엄 | B10: -0.3 | D10: 하나증권: 최근 주가 급등 및 사업 포트폴리오 차이를 감안해 30% 할인
A11: 피어 평균 P/E | B11: =AVERAGE($F$22:$F$26) -> 26.44 | D11: Include = Y 인 피어만 평균 (국내 피어 4개)
A12: 피어 중앙값 P/E | B12: =MEDIAN($F$22:$F$26) -> 25.385
A13: 직접 입력 P/E | B13: 43.82 | D13: 선정 방식을 '직접 입력'으로 바꿀 때 쓰는 값
A14: 도출 Target P/E | B14: =IF($B$6="특정 피어 조정",$B$9*(1+$B$10),IF($B$6="피어 평균",$B$11,IF($B$6="피어 중앙값",$B$12,$B$13))) -> 43.82 | D14: 선정 방식에 따라 자동 분기
A15: 목표주가 (원) | B15: =ROUND($B$7*$B$14,-4) -> 180000 | D15: 하나증권과 동일하게 1만원 단위 반올림 → 180,000원
A16: 현재주가 (원) | B16: 143100 | D16: 2026.02.04 종가 — 시장 데이터에서 자동 수집
A17: 상승여력 | B17: =$B$15/$B$16-1 -> 0.25786164 | D17: 목표주가 ÷ 현재주가 − 1
A20: 피어 정보 및 참고 멀티플
A21: 기업명 | B21: 시장 | C21: 기준 P/E | D21: Include | E21: 조정률 | F21: 적용 P/E
A22: WinWay | B22: TWSE | C22: 62.6 | D22: N | E22: 0 | F22: =IF($D$22="Y",$C$22*(1+$E$22),"") | G22: 하나증권 도표 1의 Winway 26년 예상 PER
A23: 리노공업 | B23: KOSDAQ | C23: 28.3 | D23: Y | E23: 0 | F23: =IF($D$23="Y",$C$23*(1+$E$23),"") -> 28.3 | G23: 삼성증권 2026.04.28 리포트 참고값 (기준일 상이)
A24: 티에스이 | B24: KOSDAQ | C24: 22.47 | D24: Y | E24: 0 | F24: =IF($D$24="Y",$C$24*(1+$E$24),"") -> 22.47 | G24: 삼성증권 2026.04.28 리포트 참고값
A25: 테크윙 | B25: KOSDAQ | C25: 15.68 | D25: Y | E25: 0 | F25: =IF($D$25="Y",$C$25*(1+$E$25),"") -> 15.68 | G25: 삼성증권 2026.04.28 리포트 참고값
A26: 두산테스나 | B26: KOSDAQ | C26: 39.31 | D26: Y | E26: 0 | F26: =IF($D$26="Y",$C$26*(1+$E$26),"") -> 39.31 | G26: 삼성증권 2026.04.28 리포트 참고값
A28: 피어 평균 P/E | F28: =AVERAGE($F$22:$F$26) -> 26.44
A29: 피어 중앙값 P/E | F29: =MEDIAN($F$22:$F$26) -> 25.385
A31: 정합성 체크 — 하나증권 원문 대조
A32: 항목 | B32: 모델 산출 | C32: 원문값 | D32: 차이
A33: Target P/E | B33: =$B$14 -> 43.82 | C33: 43.82 | D33: =$B$33-$C$33 -> 0
A34: 목표주가 (원) | B34: =$B$15 -> 180000 | C34: 180000 | D34: =$B$34-$C$34 -> 0
A35: 상승여력 | B35: =$B$17 -> 0.25786164 | C35: 0.26 | D35: =$B$35-$C$35 -> -0.0021383648
A37: 자료: ISC, 하나증권 4Q25 Earnings Review (2026.02.04) | 국내 피어 P/E 는 삼성증권 2026.04.28 리포트 참고값
A38: 주) 선정 방식·선택 피어·Include 는 드롭다운으로 고르게 해 두었습니다. 방식을 '피어 평균' 또는 '피어 중앙값'으로 바꾸면 아래 피어 표에서 Include = Y 인 기업들의 적용 P/E 평균·중앙값이 그대로 Target P/E 가 됩니다. 하나증권 리포트는 WinWay 단일 피어에 30% 할인을 적용하는 방식입니다. 기본 설정을 그대로 두면 원문 목표주가 180,000원과 상승여력 26%(반올림)가 재현됩니다.
A39: 주) 국내 피어 4개는 하나증권 리포트에 없어 삼성증권 2026.04.28 리포트의 값을 참고로 넣었습니다. 기준일이 달라 하나증권 기준일(2026.02.04) 수치와 직접 비교되지 않으므로, 선정 방식을 '피어 평균/중앙값'으로 바꿀 때는 P/E를 같은 기준일로 갱신해 주세요.
A40: 주) WinWay 는 Include = N 으로 두어 피어 평균·중앙값 계산에서 제외했습니다 (대만 상장사이며 밸류에이션 수준이 국내 피어와 크게 다름).

Sheet 00_사용안내
B1: ISC (095340) Valuation Workbook
B2: 원자료: 하나증권 「ISC (095340) — 이유 없는 증설은 없다」 4Q25 Earnings Review, 2026.02.04, Analyst 김민경
A4: 1. 서식 규칙 (Formatting convention)
B5: 구분 | C5: 서식 | D5: 설명
B6: 애널리스트 입력 칸 | C6: 연노랑 바탕 + 파란 글씨 | D6: 서비스가 사용자에게 입력받을 칸입니다. 다음 분기·연도 추정치와 밸류에이션 가정(비교 P/E·할인율·타겟 멀티플·가중치)만 여기에 들어갑니다. 여기만 고치면 실적 추정·목표주가·상승여력·민감도가 전부 다시 계산됩니다. (01·02·08번 시트)
B7: 공시·시장 자동 수집값 | C7: 연청회색 바탕 + 파란 글씨 | D7: 과거 확정 실적, 발행주식수, 현재주가처럼 서비스가 공시·시장 데이터에서 알아서 끌어오는 값입니다. 형식상 하드코딩이지만 사용자 입력 대상이 아니므로 노란 칸과 구분해 두었습니다.
B8: 보고서 원문 전사값 | C8: 파란 글씨 (바탕 없음) | D8: 하나증권 보고서에 인쇄된 숫자를 그대로 옮긴 값입니다. 원문 대조용 참조 시트(04번 이후)에 쓰였습니다.
B9: 수식 계산값 | C9: 검정 글씨 | D9: 같은 시트 안의 값으로 계산된 결과입니다.
B10: 다른 시트 참조값 | C10: 초록 글씨 | D10: 다른 시트를 참조해 계산된 결과입니다.
B11: 확보하지 못한 구간 | C11: 진한 회색 바탕 | D11: 어느 공개 자료에서도 값을 찾지 못한 칸입니다. 임의로 추정해 넣지 않았습니다.
A13: 2. 시트 구성
B14: 시트 | C14: 원문 위치 | D14: 내용
B15: Forward EPS | C15: (서비스 화면) | D15: 실적 추정 및 EPS 계산. 분기별로 구분되어 있고 2Q26E~4Q26E 세 열만 사용자 입력을 받습니다
B16: Target PER | C16: (서비스 화면) | D16: 멀티플 설정 및 목표주가. 선정 방식·피어·할인율을 수정받아 Target P/E → 목표주가 → 상승여력 산출
B17: M1_실적추정_모델 | C17: (분석용 파생) | D17: 어플리케이션별 매출·분기 영업이익 → 연간 손익 → EPS·BPS·EBITDA 상세 모델
B18: M2_목표주가_타겟멀티플 | C18: (분석용 파생) | D18: PER·PBR·EV/EBITDA 세 방식 목표주가와 가중평균, 투자의견 자동 판정
B19: M3_민감도분석 | C19: (분석용 파생) | D19: 할인율 × 비교 P/E 조합별 목표주가·상승여력 민감도
B20: 01_p1_투자의견_KeyData | C20: p.1 표지 | D20: 투자의견·목표주가·Key Data (원문 행 순서 그대로, 52주 최고/최저도 원문처럼 한 행)
B21: 02_p1_Consensus | C21: p.1 Consensus Data | D21: 시장 컨센서스 (2025·2026)
B22: 03_p1_주가추이 | C22: p.1 Stock Price | D22: 표지 주가 차트 대체. 분기말 종가·시가총액 (1Q22~2Q26)
B23: 04_p1_FinancialData | C23: p.1 Financial Data | D23: 요약 투자지표 (2023~2026F)
B24: 05_도표1_Valuation | C24: 도표 1 | D24: 밸류에이션. EPS·비교 P/E·할인율 → Target P/E·목표주가
B25: 06_도표2_PER_Band | C25: 도표 2 | D25: 12MF P/E Band 배수
... B43: Z_출처_공시_리서치 | C43: (부록) | D43: 외부에서 끌어온 수치의 출처, 미확보 구간, ISC의 DART 공시 정보
A45: 3. 읽을 때 유의사항
B46: • | C46: 보고서 본문의 줄글(텍스트)은 요청에 따라 제외했고, 표에 인쇄된 수치만 시트로 옮겼습니다.
B47: • | C47: 탭 색으로 성격을 구분했습니다. 노랑 = 서비스 화면(입력받는 시트), 주황 = 분석용 파생 모델, 청록 = 리포트 원문 표·그래프, 보라 = 원문에 없는 파생 표, 회색 = 안내·부록입니다.
B48: • | C48: 리포트에 실린 표·그래프는 하나당 시트 하나씩 들어가 있고, 표 형태도 원문에 최대한 맞췄습니다. 원문 대조용 「정합성 체크」는 각 시트 맨 아래에 구분해서 붙였습니다.
B49: • | C49: 시트 순서는 리포트에 나오는 순서를 따랐습니다. 앞의 01~03번만 예외로, 실제로 값을 넣어 쓰는 모델이라 맨 앞에 뒀습니다. 01에서 실적을 추정하면 그 EPS·BPS·EBITDA가 02로 넘어가 목표주가가 나옵니다 (04번 이후 원문 시트와 내용이 일부 중복됩니다).
B50: • | C50: 도표 7~10은 각각 한 시트씩 독립되어 있고, 리포트 표에 없는 수치는 공시·리서치 자료에서 확보해 파란 글씨로 채웠습니다. 각 시트 하단에 셀 단위 출처 블록이 있고, 24번 시트에 전체 출처와 미확보 구간을 정리했습니다.
B51: • | C51: 각 표 시트 하단에는 「정합성 체크」 블록이 있습니다. 원문 숫자를 수식으로 다시 계산해 원문과 대조하며, 차이는 보고서 자체의 반올림 표기 차이입니다 (예: 도표4의 2025년 매출 220.1 vs 분기 합 220.2).
B52: • | C52: 밸류에이션에 쓰인 26년 예상 EPS 4,025원은 추정재무제표의 2026F EPS 3,850원과 다릅니다. 원문 도표1의 값을 그대로 사용했으며, 05_도표1_Valuation 시트에서 두 값을 나란히 비교해 두었습니다.
B53: • | C53: 백분율은 모두 소수(0.26 = 26%)로 저장하고 표시 형식만 %로 지정했습니다. 수식에 바로 쓸 수 있습니다.
B54: • | C54: 음수는 회계 관례에 따라 괄호로, 0은 「-」로 표시됩니다.
B55: • | C55: 입력 칸(연노랑 FFF2CC + 파란 글씨 0000FF)은 기존 모델링 파일과 같은 색상을 씁니다. 연청회색 칸은 서비스가 공시·시장 데이터에서 자동으로 채울 과거 확정치이므로 사용자 입력 대상이 아닙니다.
B56: • | C56: 도표 2·3은 주가 시계열이 인쇄되지 않아 밴드 배수만 09번 시트에 기록했습니다. 회색으로 칠한 칸은 어느 공개 자료에서도 확보하지 못한 구간이라는 뜻이며, 임의로 추정해 넣지 않았습니다.
B57: • | C57: 본 파일은 하나증권 리서치 자료를 정리한 학습·분석용 자료이며 투자 권유가 아닙니다.

Sheet M1_실적추정_모델
A1: 실적 추정 모델 (Earnings Estimate)
A2: 연노랑 칸만 애널리스트가 입력하는 다음 분기·연도 추정치입니다. 연청회색 칸은 공시·시장 데이터에서 자동으로 채워지는 과거 확정치라 손댈 필요가 없습니다. 노랑 칸을 바꾸면 연간 손익 → EPS·BPS·EBITDA까지 다시 계산되고 M2_목표주가_타겟멀티플 시트에 반영됩니다.
A4: ⓞ 공통 가정
A5: 항목 | B5: 입력값 | C5: 단위 | D5: 비고
A6: 발행주식수 | B6: 21197.1 | C6: 천주 | D6: 공시 자동 수집값 (사용자 입력 대상 아님). 01_p1_투자의견_KeyData 시트의 발행주식수, 2026.02.04 기준. 주당지표 계산의 분모입니다.
A8: ① 분기 실적 (Forward EPS 시트 연동 — 2025년 확정 / 2026년 추정 입력 모두 Forward EPS 에서 받습니다)
A9: 구분 | B9: 1Q25 | C9: 2Q25 | D9: 3Q25 | E9: 4Q25 | F9: 1Q26F | G9: 2Q26F | H9: 3Q26F | I9: 4Q26F | J9: 2025F | K9: 2026F | L9: 단위
A10: 데이터센터 | B10: ='Forward EPS'!$B$7 -> 16.9 | C10: ='Forward EPS'!$C$7 -> 33.1 | D10: ='Forward EPS'!$D$7 -> 44 | E10: ='Forward EPS'!$E$7 -> 54.4 | F10: ='Forward EPS'!$F$7 -> 47.3 | G10: ='Forward EPS'!$G$7 -> 50.6 | H10: ='Forward EPS'!$H$7 -> 57.2 | I10: ='Forward EPS'!$I$7 -> 62.9 | J10: =SUM($B10:$E10) -> 148.4 | K10: =SUM($F10:$I10) -> 218 | L10: 십억원
A11: 스마트폰 | B11: ='Forward EPS'!$B$8 -> 9.5 | C11: ='Forward EPS'!$C$8 -> 14 | D11: ='Forward EPS'!$D$8 -> 13.5 | E11: ='Forward EPS'!$E$8 -> 12 | F11: ='Forward EPS'!$F$8 -> 9.6 | G11: ='Forward EPS'!$G$8 -> 10.6 | H11: ='Forward EPS'!$H$8 -> 10.6 | I11: ='Forward EPS'!$I$8 -> 10 | J11: =SUM($B11:$E11) -> 49 | K11: =SUM($F11:$I11) -> 40.8 | L11: 십억원
A12: PC/Laptop | B12: ='Forward EPS'!$B$9 -> 3.2 | C12: ='Forward EPS'!$C$9 -> 3 | D12: ='Forward EPS'!$D$9 -> 4.5 | E12: ='Forward EPS'!$E$9 -> 3 | F12: ='Forward EPS'!$F$9 -> 3.4 | G12: ='Forward EPS'!$G$9 -> 3.5 | H12: ='Forward EPS'!$H$9 -> 3.6 | I12: ='Forward EPS'!$I$9 -> 3.4 | J12: =SUM($B12:$E12) -> 13.7 | K12: =SUM($F12:$I12) -> 13.9 | L12: 십억원
A13: 오토모티브 | B13: ='Forward EPS'!$B$10 -> 1 | C13: ='Forward EPS'!$C$10 -> 0.7 | D13: ='Forward EPS'!$D$10 -> 1.5 | E13: ='Forward EPS'!$E$10 -> 1.9 | F13: ='Forward EPS'!$F$10 -> 3.3 | G13: ='Forward EPS'!$G$10 -> 2.8 | H13: ='Forward EPS'!$H$10 -> 3.4 | I13: ='Forward EPS'!$I$10 -> 4.8 | J13: =SUM($B13:$E13) -> 5.1 | K13: =SUM($F13:$I13) -> 14.3 | L13: 십억원
A14: 웨어러블 | B14: ='Forward EPS'!$B$11 -> 0.7 | C14: ='Forward EPS'!$C$11 -> 0.7 | D14: ='Forward EPS'!$D$11 -> 0.8 | E14: ='Forward EPS'!$E$11 -> 1 | F14: ='Forward EPS'!$F$11 -> 0.8 | G14: ='Forward EPS'!$G$11 -> 0.8 | H14: ='Forward EPS'!$H$11 -> 0.9 | I14: ='Forward EPS'!$I$11 -> 0.9 | J14: =SUM($B14:$E14) -> 3.2 | K14: =SUM($F14:$I14) -> 3.4 | L14: 십억원
A15: LSI | B15: ='Forward EPS'!$B$12 -> 0 | C15: ='Forward EPS'!$C$12 -> 0 | D15: ='Forward EPS'!$D$12 -> 0 | E15: ='Forward EPS'!$E$12 -> 0 | F15: ='Forward EPS'!$F$12 -> 0 | G15: ='Forward EPS'!$G$12 -> 0 | H15: ='Forward EPS'!$H$12 -> 0 | I15: ='Forward EPS'!$I$12 -> 0 | J15: =SUM($B15:$E15) -> 0 | K15: =SUM($F15:$I15) -> 0 | L15: 십억원
A16: 기타 | B16: ='Forward EPS'!$B$13 -> 0.4 | C16: ='Forward EPS'!$C$13 -> 0.2 | D16: ='Forward EPS'!$D$13 -> 0.2 | E16: ='Forward EPS'!$E$13 -> 0 | F16: ='Forward EPS'!$F$13 -> 2 | G16: ='Forward EPS'!$G$13 -> 2.7 | H16: ='Forward EPS'!$H$13 -> 1.5 | I16: ='Forward EPS'!$I$13 -> 6.3 | J16: =SUM($B16:$E16) -> 0.8 | K16: =SUM($F16:$I16) -> 12.5 | L16: 십억원
A17: 매출액 | B17: =B$10+B$11+B$12+B$13+B$14+B$15+B$16 -> 31.7 | C17: =C$10+C$11+C$12+C$13+C$14+C$15+C$16 -> 51.7 | D17: =D$10+D$11+D$12+D$13+D$14+D$15+D$16 -> 64.5 | E17: =E$10+E$11+E$12+E$13+E$14+E$15+E$16 -> 72.3 | F17: =F$10+F$11+F$12+F$13+F$14+F$15+F$16 -> 66.4 | G17: =G$10+G$11+G$12+G$13+G$14+G$15+G$16 -> 71 | H17: =H$10+H$11+H$12+H$13+H$14+H$15+H$16 -> 77.2 | I17: =I$10+I$11+I$12+I$13+I$14+I$15+I$16 -> 88.3 | ... K17: =K$10+K$11+K$12+K$13+K$14+K$15+K$16 -> 302.9 | L17: 십억원
A18: YoY | B18: =B$17/'09_도표5_분기실적_수정전'!$B$5-1 -> -0.096866097 | C18: =C$17/'09_도표5_분기실적_수정전'!$C$5-1 -> 0.03815261 | D18: =D$17/'09_도표5_분기실적_수정전'!$D$5-1 -> 0.2797619 | E18: =E$17/'09_도표5_분기실적_수정전'!$E$5-1 -> 0.83969466 | F18: =F$17/B$17-1 -> 1.0946372 | G18: =G$17/C$17-1 -> 0.37330754 | H18: =H$17/D$17-1 -> 0.19689922 | I18: =I$17/E$17-1 -> 0.22130014 | J18: =$J$17/'09_도표5_분기실적_수정전'!$J$5-1 -> 0.26189112 | K18: =$K$17/$J$17-1 -> 0.37556767 | L18: %
A19: QoQ | B19: =$B$17/'09_도표5_분기실적_수정전'!$E$5-1 -> -0.19338422 | C19: =C$17/B$17-1 -> 0.63091483 | D19: =D$17/C$17-1 -> 0.24758221 | E19: =E$17/D$17-1 -> 0.12093023 | F19: =F$17/E$17-1 -> -0.081604426 | G19: =G$17/F$17-1 -> 0.069277108 | H19: =H$17/G$17-1 -> 0.087323944 | I19: =I$17/H$17-1 -> 0.14378238 | L19: %
A20: 영업이익 | B20: ='Forward EPS'!$B$20 -> 6.99 | C20: ='Forward EPS'!$C$20 -> 13.71 | D20: ='Forward EPS'!$D$20 -> 17.42 | E20: ='Forward EPS'!$E$20 -> 21.93 | F20: ='Forward EPS'!$F$20 -> 20.6 | G20: ='Forward EPS'!$G$20 -> 21.5 | H20: ='Forward EPS'!$H$20 -> 22.7 | I20: ='Forward EPS'!$I$20 -> 28.9 | J20: =SUM($B20:$E20) -> 60.05 | K20: =SUM($F20:$I20) -> 93.7 | L20: 십억원
A21: OPM | B21: =B$20/B$17 -> 0.22050473 | C21: =C$20/C$17 -> 0.26518375 | D21: =D$20/D$17 -> 0.27007752 | E21: =E$20/E$17 -> 0.3033195 | F21: =F$20/F$17 -> 0.31024096 | G21: =G$20/G$17 -> 0.3028169 | H21: =H$20/H$17 -> 0.29404145 | I21: =I$20/I$17 -> 0.32729332 | ... K21: =K$20/K$17 -> 0.30934302 | L21: %
A22: 영업이익 YoY | B22: =B$20/'09_도표5_분기실적_수정전'!$B$15-1 -> -0.1872093 | C22: =C$20/'09_도표5_분기실적_수정전'!$C$15-1 -> -0.079865772 | D22: =D$20/'09_도표5_분기실적_수정전'!$D$15-1 -> 0.26231884 | E22: =E$20/'09_도표5_분기실적_수정전'!$E$15-1 -> 1.924 | F22: =F$20/B$20-1 -> 1.9470672 | G22: =G$20/C$20-1 -> 0.5681984 | H22: =H$20/D$20-1 -> 0.30309989 | I22: =I$20/E$20-1 -> 0.31782946 | J22: =$J$20/'09_도표5_분기실적_수정전'!$J$15-1 -> 0.34040179 | K22: =$K$20/$J$20-1 -> 0.56036636 | L22: %
A23: 원문(도표 4) 매출액 대비 차이 | B23: =B$17-'08_도표4_분기실적_수정후'!$B$5 -> 0 | C23: =C$17-'08_도표4_분기실적_수정후'!$C$5 -> 0 | D23: =D$17-'08_도표4_분기실적_수정후'!$D$5 -> 0 | E23: =E$17-'08_도표4_분기실적_수정후'!$E$5 -> 0 | F23: =F$17-'08_도표4_분기실적_수정후'!$F$5 -> -0.1 | G23: =G$17-'08_도표4_분기실적_수정후'!$G$5 -> 0 | H23: =H$17-'08_도표4_분기실적_수정후'!$H$5 -> 0.1 | I23: =I$17-'08_도표4_분기실적_수정후'!$I$5 -> -0.1 | J23: =$J$17-'08_도표4_분기실적_수정후'!$K$5 -> 0.1 | K23: =$K$17-'08_도표4_분기실적_수정후'!$L$5 -> 0 | L23: 십억원
A24: 주) 매출액은 어플리케이션 7개 항목의 합으로 계산합니다. 원문 도표 4의 매출액과 0.1 내외 차이가 나는 것은 보고서가 각 항목을 소수 첫째자리로 반올림해 인쇄했기 때문입니다.
A26: ② 연간 실적 추정 → EPS·BPS·EBITDA 도출 (연청회색: 공시 확정치 / 노랑: 애널리스트 추정)
A27: 구분 | B27: 2023 | C27: 2024 | D27: 2025F | E27: 2026F | F27: 2027F | G27: 단위 | K27: 비고
A28: 매출액 | B28: ='15_p5_손익계산서'!$B$5 -> 140.2 | C28: ='15_p5_손익계산서'!$C$5 -> 174.5 | D28: =$J$17 -> 220.2 | E28: =$K$17 -> 302.9 | F28: =$E28*(1+$F29) -> 373.11222 | G28: 십억원 | K28: 2023·24는 15_p5_손익계산서, 2025F·26F는 ①의 분기 합계, 2027F는 아래 성장률 적용
A29: 매출 성장률 | B29: n/a | C29: =$C28/$B28-1 -> 0.2446505 | D29: =$D28/$C28-1 -> 0.26189112 | E29: =$E28/$D28-1 -> 0.37556767 | F29: 0.2318 | G29: % | K29: 2027F만 입력. 원문 2027F 매출 373.1십억원에 해당하는 성장률
A30: OPM | B30: =$B31/$B28 -> 0.076319544 | C30: =$C31/$C28 -> 0.25673352 | D30: =$J$21 -> 0.27270663 | E30: =$K$21 -> 0.30934302 | F30: 0.3353 | G30: % | K30: 2027F만 입력. 2025F·26F는 ①의 분기 합계 기준
A31: 영업이익 | B31: ='15_p5_손익계산서'!$B$9 -> 10.7 | C31: ='15_p5_손익계산서'!$C$9 -> 44.8 | D31: =$J$20 -> 60.05 | E31: =$K$20 -> 93.7 | F31: =$F28*$F30 -> 125.10453 | G31: 십억원 | K31: 2027F = 매출액 × OPM
A32: 영업외손익 합계 | B32: 6.8 | C32: 24.8 | D32: 6.5 | E32: 6.8 | F32: 12.7 | G32: 십억원 | K32: 2023·24는 공시 확정치(연청회색), 2025F~는 애널리스트 추정(노랑). 금융손익 + 종속/관계기업손익 + 기타영업외손익
A33: 세전이익 | B33: =$B31+$B32 -> 17.5 | C33: =$C31+$C32 -> 69.6 | D33: =$D31+$D32 -> 66.55 | E33: =$E31+$E32 -> 100.5 | F33: =$F31+$F32 -> 137.80453 | G33: 십억원 | K33: 영업이익 + 영업외손익 합계
A34: 유효법인세율 | B34: 0.2273 | C34: 0.2112 | D34: 0.1547 | E34: 0.1803 | F34: 0.1798 | G34: % | K34: 2023·24는 공시 확정치에서 역산(연청회색), 2025F~는 애널리스트 가정(노랑)
A35: 법인세 | B35: =$B33*$B34 -> 3.97775 | C35: =$C33*$C34 -> 14.69952 | D35: =$D33*$D34 -> 10.295285 | E35: =$E33*$E34 -> 18.12015 | F35: =$F33*$F34 -> 24.777254 | G35: 십억원 | K35: 세전이익 × 유효법인세율
A36: 당기순이익 | B36: =$B33-$B35 -> 13.52225 | C36: =$C33-$C35 -> 54.90048 | D36: =$D33-$D35 -> 56.254715 | E36: =$E33-$E35 -> 82.37985 | F36: =$F33-$F35 -> 113.02727 | G36: 십억원 | K36: 세전이익 − 법인세
A37: 비지배주주지분율 | B37: 0.0294 | C37: 0.0036 | D37: 0.0071 | E37: 0.0085 | F37: 0.0088 | G37: % | K37: 2023·24는 공시 확정치에서 역산(연청회색), 2025F~는 애널리스트 가정(노랑)
A38: 지배주주순이익 | B38: =$B36*(1-$B37) -> 13.124696 | C38: =$C36*(1-$C37) -> 54.702838 | D38: =$D36*(1-$D37) -> 55.855307 | E38: =$E36*(1-$E37) -> 81.679621 | F38: =$F36*(1-$F37) -> 112.03263 | G38: 십억원 | K38: 당기순이익 × (1 − 비지배주주지분율)
A39: EPS | B39: =$B38*1000000/$B$6 -> 619.17413 | C39: =$C38*1000000/$B$6 -> 2580.6756 | D39: =$D38*1000000/$B$6 -> 2635.0447 | E39: =$E38*1000000/$B$6 -> 3853.3394 | F39: =$F38*1000000/$B$6 -> 5285.2812 | G39: 원 | K39: 지배주주순이익 ÷ 발행주식수 → 02_목표주가 시트의 기준 EPS
A40: 지배주주지분 (자본) | B40: ='16_p5_대차대조표'!$B$28 -> 473.4 | C40: ='16_p5_대차대조표'!$C$28 -> 522.7 | D40: ='16_p5_대차대조표'!$D$28 -> 535.2 | E40: ='16_p5_대차대조표'!$E$28 -> 600.2 | F40: ='16_p5_대차대조표'!$F$28 -> 694.8 | G40: 십억원 | K40: 16_p5_대차대조표 참조 (자본은 별도 추정하지 않고 원문값 사용)
A41: BPS | B41: =$B40*1000000/$B$6 -> 22333.244 | C41: =$C40*1000000/$B$6 -> 24659.034 | D41: =$D40*1000000/$B$6 -> 25248.737 | E41: =$E40*1000000/$B$6 -> 28315.194 | F41: =$F40*1000000/$B$6 -> 32778.069 | G41: 원 | K41: 지배주주지분 ÷ 발행주식수 → 02_목표주가 시트의 기준 BPS
A42: 감가상각비 | B42: ='18_p5_현금흐름표'!$B$8 -> 8.7 | C42: ='18_p5_현금흐름표'!$C$8 -> 9.9 | D42: ='18_p5_현금흐름표'!$D$8 -> 9.9 | E42: ='18_p5_현금흐름표'!$E$8 -> 17.4 | F42: ='18_p5_현금흐름표'!$F$8 -> 18.2 | G42: 십억원 | K42: 18_p5_현금흐름표 참조
A43: EBITDA | B43: =$B31+$B42 -> 19.4 | C43: =$C31+$C42 -> 54.7 | D43: =$D31+$D42 -> 69.95 | E43: =$E31+$E42 -> 111.1 | F43: =$F31+$F42 -> 143.30453 | G43: 십억원 | K43: 영업이익 + 감가상각비 → 02_목표주가 시트의 기준 EBITDA
A44: 순현금 | B44: =-'16_p5_대차대조표'!$B$36 -> 276.9 | C44: =-'16_p5_대차대조표'!$C$36 -> 325.9 | D44: =-'16_p5_대차대조표'!$D$36 -> 330 | E44: =-'16_p5_대차대조표'!$E$36 -> 305.4 | F44: =-'16_p5_대차대조표'!$F$36 -> 381.5 | G44: 십억원 | K44: 16_p5_대차대조표 순금융부채의 부호를 뒤집은 값 (EV 계산용)
A46: ③ 원문 대조 (모델 산출값 vs 하나증권 원문)
A47: 체크 항목 | B47: 2023 | C47: 2024 | D47: 2025F | E47: 2026F | F47: 2027F | G47: 단위 | K47: 비고
A48: 매출액 차이 | B48: =$B$28-'15_p5_손익계산서'!$B$5 -> 0 | C48: =$C$28-'15_p5_손익계산서'!$C$5 -> 0 | D48: =$D$28-'15_p5_손익계산서'!$D$5 -> 0.01 | E48: =$E$28-'15_p5_손익계산서'!$E$5 -> 0 | F48: =$F$28-'15_p5_손익계산서'!$F$5 -> 0.01222 | K48: 모델 − 원문 (십억원)
A49: 영업이익 차이 | B49: =$B$31-'15_p5_손익계산서'!$B$9 -> 0 | C49: =$C$31-'15_p5_손익계산서'!$C$9 -> 0 | D49: =$D$31-'15_p5_손익계산서'!$D$9 -> 0 | E49: =$E$31-'15_p5_손익계산서'!$E$9 -> 0 | F49: =$F$31-'15_p5_손익계산서'!$F$9 -> 0.004527366 | K49: 모델 − 원문 (십억원)
A50: 지배주주순이익 차이 | B50: =$B$38-'15_p5_손익계산서'!$B$19 -> -0.07530415 | C50: =$C$38-'15_p5_손익계산서'!$C$19 -> 0.002838272 | D50: =$D$38-'15_p5_손익계산서'!$D$19 -> -0.26469348 | E50: =$E$38-'15_p5_손익계산서'!$E$19 -> 0.079621275 | F50: =$F$38-'15_p5_손익계산서'!$F$19 -> 0.03263334 | K50: 모델 − 원문 (십억원)
A51: EPS 차이 (%) | B51: =$B$39/'17_p5_투자지표'!$B$6-1 -> -0.14003594 | C51: =$C$39/'17_p5_투자지표'!$C$6-1 -> 0.00064970025 | D51: =$D$39/'17_p5_투자지표'!$D$6-1 -> -0.0011202713 | E51: =$E$39/'17_p5_투자지표'!$E$6-1 -> 0.00086738495 | F51: =$F$39/'17_p5_투자지표'!$F$6-1 -> 5.3200189e-05 | K51: 모델 ÷ 원문 − 1
A52: BPS 차이 (%) | B52: =$B$41/'17_p5_투자지표'!$B$7-1 -> -0.036238567 | C52: =$C$41/'17_p5_투자지표'!$C$7-1 -> -0.03324446 | D52: =$D$41/'17_p5_투자지표'!$D$7-1 -> -0.03228175 | E52: =$E$41/'17_p5_투자지표'!$E$7-1 -> -0.028938096 | F52: =$F$41/'17_p5_투자지표'!$F$7-1 -> -0.025129563 | K52: 모델 ÷ 원문 − 1
A53: EBITDA 차이 | B53: =$B$43-'15_p5_손익계산서'!$B$22 -> 0 | C53: =$C$43-'15_p5_손익계산서'!$C$22 -> 0.1 | D53: =$D$43-'15_p5_손익계산서'!$D$22 -> -0.05 | E53: =$E$43-'15_p5_손익계산서'!$E$22 -> 0 | F53: =$F$43-'15_p5_손익계산서'!$F$22 -> -0.095472634 | K53: 모델 − 원문 (십억원)
A55: 자료: ISC, 하나증권
A56: 주) 색 구분 기준입니다. 연청회색 = 공시에서 확정 확인이 되는 값(분기 매출·영업이익, 발행주식수, 2023·2024년 손익 항목)이라 서비스가 자동으로 채웁니다. 연노랑 = 아직 확정 공시가 없어 애널리스트가 넣어야 하는 값입니다. 2025년 매출·영업이익은 잠정실적 공시로 확정됐지만 영업외손익·유효법인세율·비지배주주지분율은 사업보고서 확정 전이라 노랑으로 뒀습니다.
A57: 주) 모델은 원문 표를 그대로 옮기는 대신 「매출 → 영업이익 → 세전 → 순이익 → EPS」 계산 사슬로 다시 조립한 것이므로, 반올림된 입력값 때문에 원문과 0.1십억원·0.1% 수준의 차이가 남습니다. 위 ③ 블록이 그 차이를 그대로 보여줍니다.
A58: 주) BPS는 지배주주지분을 현재 발행주식수로 나눈 값이라 원문 BPS보다 낮게 나옵니다. 원문은 자기주식을 제외한 유통주식수를 쓰는 것으로 추정됩니다 (원문 2026F BPS 29,159원 → 역산 주식수 약 20,583천주).

Sheet M2_목표주가_타겟멀티플
A1: 목표주가 도출 — 타겟 멀티플 설정
A2: M1_실적추정_모델에서 넘어온 EPS·BPS·EBITDA에 타겟 멀티플을 적용해 목표주가를 산출합니다. 연노랑 칸이 애널리스트 입력값, 연청회색 칸이 공시·시장 자동 수집값입니다.
A4: ① 기준 지표 (2026F 기준, M1_실적추정_모델에서 연동)
A5: 구분 | B5: 항목 | C5: 값 | D5: 단위 | E5: 비고
A6: 연동 | B6: 모델 EPS (2026F) | C6: =M1_실적추정_모델!$E$39 -> 3853.3394 | D6: 원 | E6: M1_실적추정_모델의 계산 사슬로 산출된 EPS
A7: 자동 | B7: 리포트 도표1 적용 EPS | C7: 4025 | D7: 원 | E7: 하나증권 도표 1에 인쇄된 26년 예상 EPS — 리포트에서 자동 수집 (사용자 입력 대상 아님)
A8: 입력 | B8: 적용 EPS 선택 (1=모델, 2=원문) | C8: 2 | D8: - | E8: 기본값 2 → 원문 기준으로 목표주가 180,000원이 재현됩니다. 1로 바꾸면 모델 EPS가 적용됩니다.
A9: 산출 | B9: 적용 EPS | C9: =IF($C$8=1,$C$6,$C$7) -> 4025 | D9: 원 | E9: 위 선택값에 따라 결정
A10: 연동 | B10: 모델 BPS (2026F) | C10: =M1_실적추정_모델!$E$41 -> 28315.194 | D10: 원 | E10: PBR 방식의 기준 지표
A11: 연동 | B11: 모델 EBITDA (2026F) | C11: =M1_실적추정_모델!$E$43 -> 111.1 | D11: 십억원 | E11: EV/EBITDA 방식의 기준 지표
A12: 연동 | B12: 순현금 (2026F) | C12: =M1_실적추정_모델!$E$44 -> 305.4 | D12: 십억원 | E12: EV → 시가총액 환산에 사용 (순현금이므로 EV에 더함)
A13: 연동 | B13: 발행주식수 | C13: =M1_실적추정_모델!$B$6 -> 21197.1 | D13: 천주 | E13: M1_실적추정_모델 공통 가정
A14: 자동 | B14: 현재주가 | C14: 143100 | D14: 원 | E14: 2026.02.04 종가 — 시장 데이터에서 자동 수집
A16: ② 타겟 멀티플 설정 (전부 애널리스트 입력)
A17: 구분 | B17: 항목 | C17: 값 | D17: 단위 | E17: 비고
A18: 입력 | B18: 비교 P/E | C18: 62.6 | D18: 배 | E18: 글로벌 경쟁사 Winway 26년 예상 PER
A19: 입력 | B19: 할인율 | C19: 0.3 | D19: % | E19: 최근 주가 급등 및 사업 포트폴리오 차이에 따른 할인율
A20: 산출 | B20: Target P/E | C20: =$C$18*(1-$C$19) -> 43.82 | D20: 배 | E20: 비교 P/E × (1 − 할인율) → 원문 43.82배
A21: 입력 | B21: Target P/B | C21: 6.17 | D21: 배 | E21: 참고 방식. 기본값은 원문 목표주가 180,000원 ÷ 원문 2026F BPS 29,159원으로 역산한 배수
A22: 입력 | B22: Target EV/EBITDA | C22: 31.6 | D22: 배 | E22: 참고 방식. 기본값은 원문 목표주가에서 역산한 배수
A24: ③ 방식별 목표주가
A25: 구분 | B25: 방식 | C25: 목표주가 (원) | D25: 가중치 | E25: 산식 / 비고
A26: 산출 | B26: PER 방식 | C26: =$C$9*$C$20 -> 176375.5 | D26: 1 | E26: 적용 EPS × Target P/E ← 하나증권 원문이 사용한 방식
A27: 산출 | B27: PBR 방식 | C27: =$C$10*$C$21 -> 174704.75 | D27: 0 | E27: 모델 BPS × Target P/B
A28: 산출 | B28: EV/EBITDA 방식 | C28: =($C$11*$C$22+$C$12)*1000000/$C$13 -> 180032.17 | D28: 0 | E28: (EBITDA × Target EV/EBITDA + 순현금) ÷ 발행주식수
B29: 가중치 합계 검산 | D29: =$D$26+$D$27+$D$28 -> 1 | E29: 100%가 되어야 합니다. 원문 재현 기준은 PER 100%입니다.
A31: ④ 최종 목표주가
A32: 구분 | B32: 항목 | C32: 값 | D32: 단위 | E32: 비고
A33: 산출 | B33: 가중평균 목표주가 | C33: =$C$26*$D$26+$C$27*$D$27+$C$28*$D$28 -> 176375.5 | D33: 원 | E33: 방식별 목표주가 × 가중치의 합
A34: 입력 | B34: 반올림 단위 | C34: 10000 | D34: 원 | E34: 제시 목표주가 라운딩 단위
A35: 산출 | B35: 제시 목표주가 | C35: =ROUND($C$33/$C$34,0)*$C$34 -> 180000 | D35: 원 | E35: 가중평균 목표주가를 반올림 단위로 라운딩
A36: 산출 | B36: 상승여력 | C36: =$C$35/$C$14-1 -> 0.25786164 | D36: % | E36: 제시 목표주가 ÷ 현재주가 − 1
A37: 산출 | B37: 투자의견 (하나증권 기준 자동 판정) | C37: =IF($C$36>=0.15,"BUY",IF($C$36>=-0.15,"Neutral","Reduce")) -> BUY | E37: 상승여력 15% 이상 BUY / −15%~15% Neutral / −15% 이하 Reduce (20_p6_투자등급_비율공시 기준)
A39: ⑤ 원문 대조 및 내재 배수 검증
A40: 구분 | B40: 항목 | C40: 값 | D40: 원문값 | E40: 비고
A41: 대조 | B41: Target P/E | C41: =$C$20 -> 43.82 | D41: 43.82 | E41: 원문 도표 1
A42: 대조 | B42: 제시 목표주가 | C42: =$C$35 -> 180000 | D42: 180000 | E42: 원문 도표 1
A43: 대조 | B43: 상승여력 | C43: =$C$36 -> 0.25786164 | D43: 0.26 | E43: 원문 도표 1 (반올림 표기)
A44: 검증 | B44: 제시 목표주가 내재 P/E | C44: =$C$35/$C$9 -> 44.720497 | E44: 제시 목표주가 ÷ 적용 EPS
A45: 검증 | B45: 제시 목표주가 내재 P/B | C45: =$C$35/$C$10 -> 6.357011 | E45: 제시 목표주가 ÷ 모델 BPS
A46: 검증 | B46: 제시 목표주가 내재 EV/EBITDA | C46: =($C$35*$C$13/1000000-$C$12)/$C$11 -> 31.593861 | E46: (목표시가총액 − 순현금) ÷ EBITDA
A47: 검증 | B47: 현재주가 내재 P/E | C47: =$C$14/$C$9 -> 35.552795 | E47: 현재주가 ÷ 적용 EPS
A49: 자료: ISC, 하나증권
A50: 주) 하나증권 원문은 PER 단일 방식입니다. PBR·EV/EBITDA 방식은 교차 검증용으로 덧붙인 것이며, 기본 가중치를 PER 100%로 두었기 때문에 초기 상태에서는 원문 목표주가 180,000원이 그대로 재현됩니다. 가중치를 바꾸면 세 방식의 가중평균으로 목표주가가 다시 계산됩니다.
A51: 주) 적용 EPS 선택을 1(모델)로 바꾸면 M1_실적추정_모델이 계산한 EPS가 적용됩니다. 모델 EPS는 반올림된 입력값 때문에 원문 도표1 EPS(4,025원)와 차이가 있어 목표주가도 달라집니다.
A52: 주) 할인율·비교 P/E 조합별 민감도는 M3_민감도분석 시트에서 확인할 수 있습니다 (05_도표1_Valuation 시트의 입력값 기준).

Sheet M3_민감도분석
A1: 민감도 분석 — 할인율 × 비교 P/E
A2: 05_도표1_Valuation 시트의 입력값을 기준으로 자동 계산됩니다. 연청색으로 강조된 칸이 현재 시나리오(할인율 30% / 비교 P/E 62.6배)입니다. 이 시트에는 입력 칸이 없고 08번 시트의 입력값을 받아 전부 수식으로 계산됩니다.
A4: ① 목표주가 (원)
B5: 할인율 ＼ 비교 P/E (배) | C5: ='05_도표1_Valuation'!$C$7-10 -> 52.6 | D5: ='05_도표1_Valuation'!$C$7-5 -> 57.6 | E5: ='05_도표1_Valuation'!$C$7+0 -> 62.6 | F5: ='05_도표1_Valuation'!$C$7+5 -> 67.6 | G5: ='05_도표1_Valuation'!$C$7+10 -> 72.6
B6: ='05_도표1_Valuation'!$C$8-0.1 -> 0.2 | C6: =ROUND('05_도표1_Valuation'!$C$6*C$5*(1-$B6)/'05_도표1_Valuation'!$C$10,0)*'05_도표1_Valuation'!$C$10 -> 170000 | D6: =ROUND('05_도표1_Valuation'!$C$6*D$5*(1-$B6)/'05_도표1_Valuation'!$C$10,0)*'05_도표1_Valuation'!$C$10 -> 190000 | E6: =ROUND('05_도표1_Valuation'!$C$6*E$5*(1-$B6)/'05_도표1_Valuation'!$C$10,0)*'05_도표1_Valuation'!$C$10 -> 200000 | F6: =ROUND('05_도표1_Valuation'!$C$6*F$5*(1-$B6)/'05_도표1_Valuation'!$C$10,0)*'05_도표1_Valuation'!$C$10 -> 220000 | G6: =ROUND('05_도표1_Valuation'!$C$6*G$5*(1-$B6)/'05_도표1_Valuation'!$C$10,0)*'05_도표1_Valuation'!$C$10 -> 230000
B7: ='05_도표1_Valuation'!$C$8-0.05 -> 0.25 | C7: =ROUND('05_도표1_Valuation'!$C$6*C$5*(1-$B7)/'05_도표1_Valuation'!$C$10,0)*'05_도표1_Valuation'!$C$10 -> 160000 | D7: =ROUND('05_도표1_Valuation'!$C$6*D$5*(1-$B7)/'05_도표1_Valuation'!$C$10,0)*'05_도표1_Valuation'!$C$10 -> 170000 | E7: =ROUND('05_도표1_Valuation'!$C$6*E$5*(1-$B7)/'05_도표1_Valuation'!$C$10,0)*'05_도표1_Valuation'!$C$10 -> 190000 | F7: =ROUND('05_도표1_Valuation'!$C$6*F$5*(1-$B7)/'05_도표1_Valuation'!$C$10,0)*'05_도표1_Valuation'!$C$10 -> 200000 | G7: =ROUND('05_도표1_Valuation'!$C$6*G$5*(1-$B7)/'05_도표1_Valuation'!$C$10,0)*'05_도표1_Valuation'!$C$10 -> 220000
B8: ='05_도표1_Valuation'!$C$8+0 -> 0.3 | C8: =ROUND('05_도표1_Valuation'!$C$6*C$5*(1-$B8)/'05_도표1_Valuation'!$C$10,0)*'05_도표1_Valuation'!$C$10 -> 150000 | D8: =ROUND('05_도표1_Valuation'!$C$6*D$5*(1-$B8)/'05_도표1_Valuation'!$C$10,0)*'05_도표1_Valuation'!$C$10 -> 160000 | E8: =ROUND('05_도표1_Valuation'!$C$6*E$5*(1-$B8)/'05_도표1_Valuation'!$C$10,0)*'05_도표1_Valuation'!$C$10 -> 180000 | F8: =ROUND('05_도표1_Valuation'!$C$6*F$5*(1-$B8)/'05_도표1_Valuation'!$C$10,0)*'05_도표1_Valuation'!$C$10 -> 190000 | G8: =ROUND('05_도표1_Valuation'!$C$6*G$5*(1-$B8)/'05_도표1_Valuation'!$C$10,0)*'05_도표1_Valuation'!$C$10 -> 200000
B9: ='05_도표1_Valuation'!$C$8+0.05 -> 0.35 | C9: =ROUND('05_도표1_Valuation'!$C$6*C$5*(1-$B9)/'05_도표1_Valuation'!$C$10,0)*'05_도표1_Valuation'!$C$10 -> 140000 | D9: =ROUND('05_도표1_Valuation'!$C$6*D$5*(1-$B9)/'05_도표1_Valuation'!$C$10,0)*'05_도표1_Valuation'!$C$10 -> 150000 | E9: =ROUND('05_도표1_Valuation'!$C$6*E$5*(1-$B9)/'05_도표1_Valuation'!$C$10,0)*'05_도표1_Valuation'!$C$10 -> 160000 | F9: =ROUND('05_도표1_Valuation'!$C$6*F$5*(1-$B9)/'05_도표1_Valuation'!$C$10,0)*'05_도표1_Valuation'!$C$10 -> 180000 | G9: =ROUND('05_도표1_Valuation'!$C$6*G$5*(1-$B9)/'05_도표1_Valuation'!$C$10,0)*'05_도표1_Valuation'!$C$10 -> 190000
B10: ='05_도표1_Valuation'!$C$8+0.1 -> 0.4 | C10: =ROUND('05_도표1_Valuation'!$C$6*C$5*(1-$B10)/'05_도표1_Valuation'!$C$10,0)*'05_도표1_Valuation'!$C$10 -> 130000 | D10: =ROUND('05_도표1_Valuation'!$C$6*D$5*(1-$B10)/'05_도표1_Valuation'!$C$10,0)*'05_도표1_Valuation'!$C$10 -> 140000 | E10: =ROUND('05_도표1_Valuation'!$C$6*E$5*(1-$B10)/'05_도표1_Valuation'!$C$10,0)*'05_도표1_Valuation'!$C$10 -> 150000 | F10: =ROUND('05_도표1_Valuation'!$C$6*F$5*(1-$B10)/'05_도표1_Valuation'!$C$10,0)*'05_도표1_Valuation'!$C$10 -> 160000 | G10: =ROUND('05_도표1_Valuation'!$C$6*G$5*(1-$B10)/'05_도표1_Valuation'!$C$10,0)*'05_도표1_Valuation'!$C$10 -> 180000
A11: 주) 각 칸 = ROUND(EPS × 비교 P/E × (1 − 할인율) ÷ 반올림단위, 0) × 반올림단위
A13: ② 상승여력 (%)
B14: 할인율 ＼ 비교 P/E (배) | C14: ='05_도표1_Valuation'!$C$7-10 -> 52.6 | D14: ='05_도표1_Valuation'!$C$7-5 -> 57.6 | E14: ='05_도표1_Valuation'!$C$7+0 -> 62.6 | F14: ='05_도표1_Valuation'!$C$7+5 -> 67.6 | G14: ='05_도표1_Valuation'!$C$7+10 -> 72.6
B15: ='05_도표1_Valuation'!$C$8-0.1 -> 0.2 | C15: =ROUND('05_도표1_Valuation'!$C$6*C$14*(1-$B15)/'05_도표1_Valuation'!$C$10,0)*'05_도표1_Valuation'!$C$10/'05_도표1_Valuation'!$C$9-1 -> 0.18798043 | D15: =ROUND('05_도표1_Valuation'!$C$6*D$14*(1-$B15)/'05_도표1_Valuation'!$C$10,0)*'05_도표1_Valuation'!$C$10/'05_도표1_Valuation'!$C$9-1 -> 0.32774284 | E15: =ROUND('05_도표1_Valuation'!$C$6*E$14*(1-$B15)/'05_도표1_Valuation'!$C$10,0)*'05_도표1_Valuation'!$C$10/'05_도표1_Valuation'!$C$9-1 -> 0.39762404 | F15: =ROUND('05_도표1_Valuation'!$C$6*F$14*(1-$B15)/'05_도표1_Valuation'!$C$10,0)*'05_도표1_Valuation'!$C$10/'05_도표1_Valuation'!$C$9-1 -> 0.53738644 | G15: =ROUND('05_도표1_Valuation'!$C$6*G$14*(1-$B15)/'05_도표1_Valuation'!$C$10,0)*'05_도표1_Valuation'!$C$10/'05_도표1_Valuation'!$C$9-1 -> 0.60726765
B16: ='05_도표1_Valuation'!$C$8-0.05 -> 0.25 | C16: =ROUND('05_도표1_Valuation'!$C$6*C$14*(1-$B16)/'05_도표1_Valuation'!$C$10,0)*'05_도표1_Valuation'!$C$10/'05_도표1_Valuation'!$C$9-1 -> 0.11809923 | D16: =ROUND('05_도표1_Valuation'!$C$6*D$14*(1-$B16)/'05_도표1_Valuation'!$C$10,0)*'05_도표1_Valuation'!$C$10/'05_도표1_Valuation'!$C$9-1 -> 0.18798043 | E16: =ROUND('05_도표1_Valuation'!$C$6*E$14*(1-$B16)/'05_도표1_Valuation'!$C$10,0)*'05_도표1_Valuation'!$C$10/'05_도표1_Valuation'!$C$9-1 -> 0.32774284 | F16: =ROUND('05_도표1_Valuation'!$C$6*F$14*(1-$B16)/'05_도표1_Valuation'!$C$10,0)*'05_도표1_Valuation'!$C$10/'05_도표1_Valuation'!$C$9-1 -> 0.39762404 | G16: =ROUND('05_도표1_Valuation'!$C$6*G$14*(1-$B16)/'05_도표1_Valuation'!$C$10,0)*'05_도표1_Valuation'!$C$10/'05_도표1_Valuation'!$C$9-1 -> 0.53738644
B17: ='05_도표1_Valuation'!$C$8+0 -> 0.3 | C17: =ROUND('05_도표1_Valuation'!$C$6*C$14*(1-$B17)/'05_도표1_Valuation'!$C$10,0)*'05_도표1_Valuation'!$C$10/'05_도표1_Valuation'!$C$9-1 -> 0.048218029 | D17: =ROUND('05_도표1_Valuation'!$C$6*D$14*(1-$B17)/'05_도표1_Valuation'!$C$10,0)*'05_도표1_Valuation'!$C$10/'05_도표1_Valuation'!$C$9-1 -> 0.11809923 | E17: =ROUND('05_도표1_Valuation'!$C$6*E$14*(1-$B17)/'05_도표1_Valuation'!$C$10,0)*'05_도표1_Valuation'!$C$10/'05_도표1_Valuation'!$C$9-1 -> 0.25786164 | F17: =ROUND('05_도표1_Valuation'!$C$6*F$14*(1-$B17)/'05_도표1_Valuation'!$C$10,0)*'05_도표1_Valuation'!$C$10/'05_도표1_Valuation'!$C$9-1 -> 0.32774284 | G17: =ROUND('05_도표1_Valuation'!$C$6*G$14*(1-$B17)/'05_도표1_Valuation'!$C$10,0)*'05_도표1_Valuation'!$C$10/'05_도표1_Valuation'!$C$9-1 -> 0.39762404
B18: ='05_도표1_Valuation'!$C$8+0.05 -> 0.35 | C18: =ROUND('05_도표1_Valuation'!$C$6*C$14*(1-$B18)/'05_도표1_Valuation'!$C$10,0)*'05_도표1_Valuation'!$C$10/'05_도표1_Valuation'!$C$9-1 -> -0.021663173 | D18: =ROUND('05_도표1_Valuation'!$C$6*D$14*(1-$B18)/'05_도표1_Valuation'!$C$10,0)*'05_도표1_Valuation'!$C$10/'05_도표1_Valuation'!$C$9-1 -> 0.048218029 | E18: =ROUND('05_도표1_Valuation'!$C$6*E$14*(1-$B18)/'05_도표1_Valuation'!$C$10,0)*'05_도표1_Valuation'!$C$10/'05_도표1_Valuation'!$C$9-1 -> 0.11809923 | F18: =ROUND('05_도표1_Valuation'!$C$6*F$14*(1-$B18)/'05_도표1_Valuation'!$C$10,0)*'05_도표1_Valuation'!$C$10/'05_도표1_Valuation'!$C$9-1 -> 0.25786164 | G18: =ROUND('05_도표1_Valuation'!$C$6*G$14*(1-$B18)/'05_도표1_Valuation'!$C$10,0)*'05_도표1_Valuation'!$C$10/'05_도표1_Valuation'!$C$9-1 -> 0.32774284
B19: ='05_도표1_Valuation'!$C$8+0.1 -> 0.4 | C19: =ROUND('05_도표1_Valuation'!$C$6*C$14*(1-$B19)/'05_도표1_Valuation'!$C$10,0)*'05_도표1_Valuation'!$C$10/'05_도표1_Valuation'!$C$9-1 -> -0.091544375 | D19: =ROUND('05_도표1_Valuation'!$C$6*D$14*(1-$B19)/'05_도표1_Valuation'!$C$10,0)*'05_도표1_Valuation'!$C$10/'05_도표1_Valuation'!$C$9-1 -> -0.021663173 | E19: =ROUND('05_도표1_Valuation'!$C$6*E$14*(1-$B19)/'05_도표1_Valuation'!$C$10,0)*'05_도표1_Valuation'!$C$10/'05_도표1_Valuation'!$C$9-1 -> 0.048218029 | F19: =ROUND('05_도표1_Valuation'!$C$6*F$14*(1-$B19)/'05_도표1_Valuation'!$C$10,0)*'05_도표1_Valuation'!$C$10/'05_도표1_Valuation'!$C$9-1 -> 0.11809923 | G19: =ROUND('05_도표1_Valuation'!$C$6*G$14*(1-$B19)/'05_도표1_Valuation'!$C$10,0)*'05_도표1_Valuation'!$C$10/'05_도표1_Valuation'!$C$9-1 -> 0.25786164
A20: 주) 각 칸 = 해당 시나리오 목표주가 ÷ 현재주가 − 1
A22: ③ Target P/E (배)
B23: 할인율 ＼ 비교 P/E (배) | C23: ='05_도표1_Valuation'!$C$7-10 -> 52.6 | D23: ='05_도표1_Valuation'!$C$7-5 -> 57.6 | E23: ='05_도표1_Valuation'!$C$7+0 -> 62.6 | F23: ='05_도표1_Valuation'!$C$7+5 -> 67.6 | G23: ='05_도표1_Valuation'!$C$7+10 -> 72.6
B24: ='05_도표1_Valuation'!$C$8-0.1 -> 0.2 | C24: =C$23*(1-$B24) -> 42.08 | D24: =D$23*(1-$B24) -> 46.08 | E24: =E$23*(1-$B24) -> 50.08 | F24: =F$23*(1-$B24) -> 54.08 | G24: =G$23*(1-$B24) -> 58.08
B25: ='05_도표1_Valuation'!$C$8-0.05 -> 0.25 | C25: =C$23*(1-$B25) -> 39.45 | D25: =D$23*(1-$B25) -> 43.2 | E25: =E$23*(1-$B25) -> 46.95 | F25: =F$23*(1-$B25) -> 50.7 | G25: =G$23*(1-$B25) -> 54.45
B26: ='05_도표1_Valuation'!$C$8+0 -> 0.3 | C26: =C$23*(1-$B26) -> 36.82 | D26: =D$23*(1-$B26) -> 40.32 | E26: =E$23*(1-$B26) -> 43.82 | F26: =F$23*(1-$B26) -> 47.32 | G26: =G$23*(1-$B26) -> 50.82
B27: ='05_도표1_Valuation'!$C$8+0.05 -> 0.35 | C27: =C$23*(1-$B27) -> 34.19 | D27: =D$23*(1-$B27) -> 37.44 | E27: =E$23*(1-$B27) -> 40.69 | F27: =F$23*(1-$B27) -> 43.94 | G27: =G$23*(1-$B27) -> 47.19
B28: ='05_도표1_Valuation'!$C$8+0.1 -> 0.4 | C28: =C$23*(1-$B28) -> 31.56 | D28: =D$23*(1-$B28) -> 34.56 | E28: =E$23*(1-$B28) -> 37.56 | F28: =F$23*(1-$B28) -> 40.56 | G28: =G$23*(1-$B28) -> 43.56
A29: 주) 각 칸 = 비교 P/E × (1 − 할인율)
A31: ④ EPS 시나리오별 목표주가 (Target P/E 고정)
B32: 26F EPS (원) | C32: ='05_도표1_Valuation'!$C$6-400 -> 3625 | D32: ='05_도표1_Valuation'!$C$6-200 -> 3825 | E32: ='05_도표1_Valuation'!$C$6+0 -> 4025 | F32: ='05_도표1_Valuation'!$C$6+200 -> 4225 | G32: ='05_도표1_Valuation'!$C$6+400 -> 4425
B33: 목표주가 (원) | C33: =ROUND(C$32*'05_도표1_Valuation'!$C$14/'05_도표1_Valuation'!$C$10,0)*'05_도표1_Valuation'!$C$10 -> 160000 | D33: =ROUND(D$32*'05_도표1_Valuation'!$C$14/'05_도표1_Valuation'!$C$10,0)*'05_도표1_Valuation'!$C$10 -> 170000 | E33: =ROUND(E$32*'05_도표1_Valuation'!$C$14/'05_도표1_Valuation'!$C$10,0)*'05_도표1_Valuation'!$C$10 -> 180000 | F33: =ROUND(F$32*'05_도표1_Valuation'!$C$14/'05_도표1_Valuation'!$C$10,0)*'05_도표1_Valuation'!$C$10 -> 190000 | G33: =ROUND(G$32*'05_도표1_Valuation'!$C$14/'05_도표1_Valuation'!$C$10,0)*'05_도표1_Valuation'!$C$10 -> 190000
B34: 상승여력 (%) | C34: =ROUND(C$32*'05_도표1_Valuation'!$C$14/'05_도표1_Valuation'!$C$10,0)*'05_도표1_Valuation'!$C$10/'05_도표1_Valuation'!$C$9-1 -> 0.11809923 | D34: =ROUND(D$32*'05_도표1_Valuation'!$C$14/'05_도표1_Valuation'!$C$10,0)*'05_도표1_Valuation'!$C$10/'05_도표1_Valuation'!$C$9-1 -> 0.18798043 | E34: =ROUND(E$32*'05_도표1_Valuation'!$C$14/'05_도표1_Valuation'!$C$10,0)*'05_도표1_Valuation'!$C$10/'05_도표1_Valuation'!$C$9-1 -> 0.25786164 | F34: =ROUND(F$32*'05_도표1_Valuation'!$C$14/'05_도표1_Valuation'!$C$10,0)*'05_도표1_Valuation'!$C$10/'05_도표1_Valuation'!$C$9-1 -> 0.32774284 | G34: =ROUND(G$32*'05_도표1_Valuation'!$C$14/'05_도표1_Valuation'!$C$10,0)*'05_도표1_Valuation'!$C$10/'05_도표1_Valuation'!$C$9-1 -> 0.32774284
A35: 주) Target P/E는 05_도표1_Valuation 시트의 산출값(43.82배)으로 고정하고 EPS만 변화시킨 경우입니다.
A37: 자료: 하나증권 도표 1 기준, 민감도는 자체 계산

Sheet 01_p1_투자의견_KeyData
A1: 투자의견 및 Key Data
A2: 하나증권 ISC(095340) 4Q25 Earnings Review 표지 (2026.02.04)
A4: ① 리포트 개요
A5: 구분 | B5: 항목 | C5: 값 | D5: 단위 | E5: 비고
A6: 개요 | B6: 종목명 | C6: ISC | E6: 코스닥 상장
A7: 개요 | B7: 종목코드 | C7: 095340
A8: 개요 | B8: 발간일 | C8: 2026-02-04 | E8: 기업분석_Earnings Review
A9: 개요 | B9: 리포트 제목 | C9: 이유 없는 증설은 없다
A10: 개요 | B10: 증권사 | C10: 하나증권 리서치센터
A11: 개요 | B11: Analyst | C11: 김민경 | E11: minkyung.kim@hanafn.com
A12: 개요 | B12: 투자의견 | C12: BUY | E12: 유지
A13: 개요 | B13: 목표주가 (12M) | C13: 180000 | D13: 원 | E13: 상향 (기존 130,000원)
A14: 개요 | B14: 현재주가 | C14: 143100 | D14: 원 | E14: 2026.02.04 종가
B15: 상승여력 | C15: ='05_도표1_Valuation'!$C$17 -> 0.25786164 | D15: % | E15: 05_도표1_Valuation 시트 산출값 참조
A17: ② Key Data
A18: 구분 | B18: 항목 | C18: 값 | D18: 단위 | E18: 비고
A19: Key Data | B19: KOSDAQ 지수 | C19: 1149.43 | D19: pt
A20: Key Data | B20: 52주 최고/최저 | C20: 150,700/43,600 | D20: 원 | E20: 원문 표기 그대로 한 행 (최고 150,700원 / 최저 43,600원)
A21: Key Data | B21: 시가총액 | C21: 3033.3 | D21: 십억원
A22: Key Data | B22: 시가총액비중 | C22: 0.0048 | D22: % | E22: 코스닥 시장 내 비중
A23: Key Data | B23: 발행주식수 | C23: 21197.1 | D23: 천주
A24: Key Data | B24: 60일 평균 거래량 | C24: 277.5 | D24: 천주
A25: Key Data | B25: 60일 평균 거래대금 | C25: 29.7 | D25: 십억원
A26: Key Data | B26: 외국인지분율 | C26: 0.2052 | D26: %
B27: 주요주주 지분율 — SKC 외 2인 | C27: 0.4516 | D27: %
B28: 주요주주 지분율 — 국민연금공단 | C28: 0.0616 | D28: %
A30: ③ 정합성 체크
A31: 구분 | B31: 항목 | C31: 계산값 | D31: 원문값 | E31: 비고
B32: 시가총액 = 현재주가 × 발행주식수 | C32: =143100*$C$23/1000000 -> 3033.305 | D32: =$C$21 -> 3033.3 | E32: 143,100원 × 21,197.1천주 ÷ 1,000,000 = 십억원
B33: 차이 | C33: =$C$32-$D$32 -> 0.00501 | E33: 0에 가까우면 정상 (반올림 표기 차이)
B34: 52주 최고 대비 현재주가 | C34: =143100/150700-1 -> -0.050431321 | E34: 52주 최고가 150,700원 대비
B35: 52주 최저 대비 현재주가 | C35: =143100/43600-1 -> 2.2821101 | E35: 52주 최저가 43,600원 대비
A37: 자료: 하나증권

Sheet 02_p1_Consensus
A1: Consensus Data
A2: 하나증권 리포트 p.1 게재 시장 컨센서스
A4: ① 컨센서스 (원문)
A5: 구분 | B5: 항목 | C5: 2025 | D5: 2026 | E5: 단위
A6: 컨센서스 | B6: 매출액 | C6: 215.9 | D6: 282.7 | E6: 십억원
A7: 컨센서스 | B7: 영업이익 | C7: 56.9 | D7: 79.6 | E7: 십억원
A8: 컨센서스 | B8: 순이익 | C8: 54.1 | D8: 75 | E8: 십억원
A9: 컨센서스 | B9: EPS | C9: 2555 | D9: 3563 | E9: 원
A10: 컨센서스 | B10: BPS | C10: 26243 | D10: 29064 | E10: 원
A11: 정합성 체크 (원문에 없는 파생 계산)
A12: 구분 | B12: 항목 | C12: 2025 | D12: 2026 | E12: 단위
B13: 영업이익률 (OPM) | C13: =$C$7/$C$6 -> 0.26354794 | D13: =$D$7/$D$6 -> 0.28157057 | E13: %
B14: 순이익률 | C14: =$C$8/$C$6 -> 0.25057897 | D14: =$D$8/$D$6 -> 0.2652989 | E14: %
A16: 자료: 하나증권
A17: 주) 위 표는 리포트 p.1 Consensus Data 를 행 순서 그대로 옮긴 것입니다. 하나증권 추정치와의 괴리율은 원문에 없는 파생 계산이라 D1_컨센서스_괴리율 시트로 분리했습니다.

Sheet 03_p1_주가추이
A1: p.1 Stock Price — 주가 및 시가총액 추이
A2: 원문 차트는 25.1~26.1 월별 주가와 KOSDAQ 상대지수입니다. 월별·지수 시계열은 공개 자료로 확보하지 못해 분기말 종가·시가총액으로 대체했습니다 (확보 구간 1Q22~2Q26).
A4: 구분 | B4: 1Q22 | C4: 2Q22 | D4: 3Q22 | E4: 4Q22 | F4: 1Q23 | G4: 2Q23 | H4: 3Q23 | I4: 4Q23 | J4: 1Q24 | K4: 2Q24 | L4: 3Q24 | M4: 4Q24 | N4: 1Q25 | O4: 2Q25 | P4: 3Q25 | Q4: 4Q25 | R4: 1Q26 | S4: 2Q26 | T4: 단위
A5: 분기말 종가 | B5: 29750 | C5: 31200 | D5: 32200 | E5: 31350 | F5: 40000 | G5: 55200 | H5: 78800 | I5: 80300 | J5: 98000 | K5: 65500 | L5: 57900 | M5: 72100 | N5: 51800 | O5: 59800 | P5: 77800 | Q5: 111100 | R5: 233000 | S5: 181500 | T5: 원
A6: 상장주식수 | B6: 17339.471 | C6: 17339.471 | D6: 17339.471 | E6: 17339.471 | F6: 17339.471 | G6: 17339.471 | H6: 17339.471 | I6: 21137.058 | J6: 21137.058 | K6: 21137.058 | L6: 21137.058 | M6: 21137.058 | N6: 21137.058 | O6: 21137.058 | P6: 21137.058 | Q6: 21197.058 | R6: 21197.058 | S6: 21197.058 | T6: 천주
A7: 시가총액 | B7: =B$5*B$6/1000000 -> 515.84926 | C7: =C$5*C$6/1000000 -> 540.9915 | D7: =D$5*D$6/1000000 -> 558.33097 | E7: =E$5*E$6/1000000 -> 543.59242 | F7: =F$5*F$6/1000000 -> 693.57884 | G7: =G$5*G$6/1000000 -> 957.1388 | H7: =H$5*H$6/1000000 -> 1366.3503 | I7: =I$5*I$6/1000000 -> 1697.3058 | ... S7: =S$5*S$6/1000000 -> 3847.266 | T7: 십억원
A8: 직전 분기 대비 등락률 | C8: =C$5/B$5-1 -> 0.048739496 | D8: =D$5/C$5-1 -> 0.032051282 | E8: =E$5/D$5-1 -> -0.026397516 | F8: =F$5/E$5-1 -> 0.27591707 | G8: =G$5/F$5-1 -> 0.38 | H8: =H$5/G$5-1 -> 0.42753623 | I8: =I$5/H$5-1 -> 0.019035533 | J8: =J$5/I$5-1 -> 0.22042341 | ... S8: =S$5/R$5-1 -> -0.22103004 | T8: %
A10: 리포트 표지 기재값 대조
A11: 현재주가 (2026.02.04) | B11: ='01_p1_투자의견_KeyData'!$C$14 -> 143100 | C11: 01_p1_투자의견_KeyData 참조
A12: 시가총액 (2026.02.04) | B12: ='01_p1_투자의견_KeyData'!$C$21 -> 3033.3 | C12: 01_p1_투자의견_KeyData 참조. 143,100원 × 21,197,058주
A13: 52주 최고 | B13: 150700 | C13: 1Q26 분기말 종가 233,000원보다 낮은 것은 리포트 발간일(2026.02.04) 기준이기 때문
A14: 52주 최저 | B14: 43600 | C14: 원문 Key Data는 최고/최저를 한 행에 묶어 표기하므로 여기서는 숫자로 분리해 실었습니다
A15: KOSDAQ 지수 (2026.02.04) | B15: ='01_p1_투자의견_KeyData'!$C$19 -> 1149.43 | C15: 상대지수 계산에 쓸 수 있는 유일한 지수 데이터
A17: 출처 (셀 단위 근거)
A18: 항목 | B18: 출처 | I18: URL / 접수번호
A19: 분기말 종가 1Q22~2Q26 | B19: stockanalysis.com 분기 시가총액 ÷ 주식수 역산값. 4Q21·4Q22·4Q23·4Q24 연말 종가는 MarketScreener 무수정 종가와 정확히 일치해 교차검증됨. 전 분기 값이 호가단위(50원)에 정확히 떨어짐 | I19: stockanalysis.com/quote/kosdaq/095340
A20: 상장주식수 | B20: 2023년 8월 유상증자(신주 3,797,587주, 발행가 52,665원) 전 17,339,471주 / 후 21,137,058주 / 2026년 21,197,058주 | I20: SK증권 2023.07.10 리포트, wisereport
A44: 주) 원문 표지 차트의 KOSDAQ 상대지수 시계열은 확보하지 못했습니다. 지수 대비 상대강도가 필요하면 KOSDAQ 지수 분기말 종가를 한 줄 추가해 계산하면 됩니다 (01_p1_투자의견_KeyData 시트에 2026.02.04 지수 1,149.43만 있음).

Sheet 04_p1_FinancialData
A1: Financial Data (요약 투자지표)
A2: 하나증권 리포트 p.1 게재 / 단위: 십억원, %, 배, 원
A4: 투자지표 | B4: 2023 | C4: 2024 | D4: 2025F | E4: 2026F | F4: 단위
A5: 매출액 | B5: 140.2 | C5: 174.5 | D5: 220.2 | E5: 302.9 | F5: 십억원
A6: 영업이익 | B6: 10.7 | C6: 44.8 | D6: 60.1 | E6: 93.7 | F6: 십억원
A7: 세전이익 | B7: 17.6 | C7: 69.6 | D7: 66.6 | E7: 100.4 | F7: 십억원
A8: 순이익 | B8: 13.2 | C8: 54.7 | D8: 55.9 | E8: 81.6 | F8: 십억원
A9: EPS | B9: 720 | C9: 2579 | D9: 2638 | E9: 3850 | F9: 원
A10: 증감율 | B10: -0.7156 | C10: 2.5819 | D10: 0.0229 | E10: 0.4594 | F10: %
A11: PER | B11: 111.53 | C11: 27.96 | D11: 42.12 | E11: 37.17 | F11: 배
A12: PBR | B12: 3.47 | C12: 2.83 | D12: 4.26 | E12: 4.91 | F12: 배
A13: EV/EBITDA | B13: 73.34 | C13: 22.01 | D13: 28.94 | E13: 24.56 | F13: 배
A14: ROE | B14: 0.0356 | C14: 0.1098 | D14: 0.1057 | E14: 0.1438 | F14: %
A15: BPS | B15: 23173 | C15: 25507 | D15: 26091 | E15: 29159 | F15: 원
A16: DPS | B16: 200 | C16: 810 | D16: 810 | E16: 850 | F16: 원
A18: 정합성 체크 (원문 수치를 수식으로 재계산)
A19: 체크 항목 | B19: 2023 | C19: 2024 | D19: 2025F | E19: 2026F | F19: 비고
A20: 영업이익률 = 영업이익 / 매출액 | B20: =B$6/B$5 -> 0.076319544 | C20: =C$6/C$5 -> 0.25673352 | D20: =D$6/D$5 -> 0.2729337 | E20: =E$6/E$5 -> 0.30934302 | F20: 17_p5_투자지표 영업이익률과 대조
A21: PER 재계산 = 주가 / EPS | B21: =B$11*B$9 -> 80301.6 | C21: =C$11*C$9 -> 72108.84 | D21: =D$11*D$9 -> 111112.56 | E21: =E$11*E$9 -> 143104.5 | F21: PER × EPS = 해당 연도 기준주가(원)
A22: PBR 재계산 = 주가 / BPS | B22: =B$12*B$15 -> 80410.31 | C22: =C$12*C$15 -> 72184.81 | D22: =D$12*D$15 -> 111147.66 | E22: =E$12*E$15 -> 143170.69 | F22: PBR × BPS = 해당 연도 기준주가(원)
A23: EPS 증감율 재계산 | B23: n/a | C23: =IFERROR(C$9/B$9-1,"n/a") -> 2.5819444 | D23: =IFERROR(D$9/C$9-1,"n/a") -> 0.022877084 | E23: =IFERROR(E$9/D$9-1,"n/a") -> 0.45943897 | F23: 원문 증감율과 대조 (2023년은 전기 미제공)
A24: 배당성향 = DPS / EPS | B24: =B$16/B$9 -> 0.27777778 | C24: =C$16/C$9 -> 0.31407522 | D24: =D$16/D$9 -> 0.3070508 | E24: =E$16/E$9 -> 0.22077922 | F24: 주당배당금 ÷ 주당순이익
A26: 자료: 하나증권
A27: 주) 여기서 '순이익'은 지배주주순이익 기준입니다 (15_p5_손익계산서의 지배주주순이익과 일치). PER·PBR × EPS·BPS로 역산되는 기준주가는 각 연도 기말/평균 주가 기준이며 현재주가와 다릅니다.

Sheet 05_도표1_Valuation
A1: 도표 1. ISC의 Valuation — 수식 연동 모델
A2: 연노랑 칸(입력)만 바꾸면 Target P/E · 목표주가 · 상승여력과 M3_민감도분석 시트가 자동으로 다시 계산됩니다.
A4: ① 입력값 — 노랑: 애널리스트 추정 입력 / 연청회색: 공시·시장 자동 수집
A5: 구분 | B5: 항목 | C5: 입력값 | D5: 단위 | E5: 비고 (원문 기준)
A6: 입력 | B6: EPS | C6: 4025 | D6: 원 | E6: 26년 예상 EPS (도표 1) — 애널리스트 추정
A7: 입력 | B7: 비교 P/E | C7: 62.6 | D7: 배 | E7: 글로벌 경쟁사 Winway 26년 예상 PER — 애널리스트 가정
A8: 입력 | B8: 할인율 | C8: 0.3 | D8: % | E8: 최근 주가 급등 및 사업 포트폴리오 차이에 따른 할인율 — 애널리스트 가정
A9: 자동 | B9: 현재주가 | C9: 143100 | D9: 원 | E9: 2026.02.04 종가 — 시장 데이터에서 자동 수집
A10: 입력 | B10: 목표주가 반올림 단위 | C10: 10000 | D10: 원 | E10: 제시 목표주가 라운딩 단위 (18만원 = 1만원 단위 반올림)
A12: ② 산출 (Output)
A13: 구분 | B13: 항목 | C13: 산출값 | D13: 단위 | E13: 산식
A14: 산출 | B14: Target P/E | C14: =$C$7*(1-$C$8) -> 43.82 | D14: 배 | E14: 비교 P/E × (1 − 할인율)
A15: 산출 | B15: 목표주가 (산출) | C15: =$C$6*$C$14 -> 176375.5 | D15: 원 | E15: EPS × Target P/E
A16: 산출 | B16: 목표주가 (제시) | C16: =ROUND($C$15/$C$10,0)*$C$10 -> 180000 | D16: 원 | E16: 산출 목표주가를 반올림 단위로 라운딩
A17: 산출 | B17: 상승여력 | C17: =$C$16/$C$9-1 -> 0.25786164 | D17: % | E17: 목표주가(제시) ÷ 현재주가 − 1
A18: 산출 | B18: 현재주가 내재 P/E | C18: =$C$9/$C$6 -> 35.552795 | D18: 배 | E18: 현재주가 ÷ EPS
A19: 산출 | B19: 비교사 대비 할인율(현재) | C19: =1-$C$18/$C$7 -> 0.43206398 | D19: % | E19: 1 − 현재 내재 P/E ÷ 비교 P/E
A21: ③ 원문 대조 및 EPS 기준 비교 (정합성 체크)
A22: 구분 | B22: 항목 | C22: 값 | D22: 원문값 | E22: 비고
A23: 체크 | B23: Target P/E (모델) | C23: =$C$14 -> 43.82 | D23: 43.82 | E23: 원문 도표1 Target P/E
A24: 체크 | B24: 목표주가 (모델, 제시) | C24: =$C$16 -> 180000 | D24: 180000 | E24: 원문 도표1 목표주가
A25: 체크 | B25: 상승여력 (모델) | C25: =$C$17 -> 0.25786164 | D25: 0.26 | E25: 원문 도표1 상승여력 (반올림 표기)
A26: 비교 | B26: 도표1 밸류에이션 적용 EPS (26F) | C26: =$C$6 -> 4025 | E26: 밸류에이션에 실제 적용된 EPS
A27: 비교 | B27: 추정재무제표 2026F EPS | C27: ='17_p5_투자지표'!$E$6 -> 3850 | E27: 17_p5_투자지표 시트 참조 (원문 3,850원)
A28: 비교 | B28: 컨센서스 2026 EPS | C28: ='02_p1_Consensus'!$D$9 -> 3563 | E28: 02_p1_Consensus 시트 참조 (원문 3,563원)
B29: 적용 EPS vs 추정재무제표 EPS 차이 | C29: =$C$26/$C$27-1 -> 0.045454545 | E29: 도표1 EPS가 추정재무제표 2026F EPS를 상회하는 폭
A31: 자료: ISC, 하나증권
A32: 주) 목표주가 산출값(≈176,376원)을 1만원 단위로 반올림해 원문 제시 목표주가 180,000원이 재현됩니다. 상승여력은 제시 목표주가 기준으로 25.8%이며 원문은 26%로 반올림 표기했습니다.

Sheet 06_도표2_PER_Band
A1: 도표 2. ISC 12MF P/E Band
A2: 원문은 차트여서 주가 시계열이 인쇄되어 있지 않습니다. 인쇄된 밴드 배수만 옮겼습니다.
A4: 밴드 | B4: 배수 (배) | E4: 비고
A5: Band 1 (상단) | B5: 57 | E5: 원문 차트에 표기된 밴드 배수
A6: Band 2 | B6: 45.1 | E6: 원문 차트에 표기된 밴드 배수
A7: Band 3 (중단) | B7: 33.3 | E7: 원문 차트에 표기된 밴드 배수
A8: Band 4 | B8: 21.4 | E8: 원문 차트에 표기된 밴드 배수
A9: Band 5 (하단) | B9: 5 | E9: 원문 차트에 표기된 밴드 배수
A10: 자료: FnGuide, 하나증권
A12: 정합성 체크 (밴드 배수 기준 내재주가 — 원문에 없는 파생 계산)
A13: 밴드 | B13: 배수 (배) | C13: 내재주가 (원) | D13: 현재주가 대비 | E13: 비고
A14: Band 1 (상단) | B14: =$B$5 -> 57 | C14: =$B14*'17_p5_투자지표'!$E$6 -> 219450 | D14: =$C14/'05_도표1_Valuation'!$C$9-1 -> 0.53354298 | E14: 2026F EPS 3,850원 적용 (참고용)
A15: Band 2 | B15: =$B$6 -> 45.1 | C15: =$B15*'17_p5_투자지표'!$E$6 -> 173635 | D15: =$C15/'05_도표1_Valuation'!$C$9-1 -> 0.21338225 | E15: 2026F EPS 3,850원 적용 (참고용)
A16: Band 3 (중단) | B16: =$B$7 -> 33.3 | C16: =$B16*'17_p5_투자지표'!$E$6 -> 128205 | D16: =$C16/'05_도표1_Valuation'!$C$9-1 -> -0.10408805 | E16: 2026F EPS 3,850원 적용 (참고용)
A17: Band 4 | B17: =$B$8 -> 21.4 | C17: =$B17*'17_p5_투자지표'!$E$6 -> 82390 | D17: =$C17/'05_도표1_Valuation'!$C$9-1 -> -0.42424878 | E17: 2026F EPS 3,850원 적용 (참고용)
A18: Band 5 (하단) | B18: =$B$9 -> 5 | C18: =$B18*'17_p5_투자지표'!$E$6 -> 19250 | D18: =$C18/'05_도표1_Valuation'!$C$9-1 -> -0.86547869 | E18: 2026F EPS 3,850원 적용 (참고용)
A19: 현재 내재 P/E | B19: ='05_도표1_Valuation'!$C$18 -> 35.552795 | C19: ='05_도표1_Valuation'!$C$9 -> 143100 | E19: 현재주가 143,100원 ÷ 도표1 적용 EPS 4,025원
A20: Target P/E | B20: ='05_도표1_Valuation'!$C$14 -> 43.82 | C20: ='05_도표1_Valuation'!$C$16 -> 180000 | D20: ='05_도표1_Valuation'!$C$17 -> 0.25786164 | E20: 05_도표1_Valuation 시트 산출값
A22: 주) 원문 도표 2는 21.1~26.1 구간의 수정주가와 5개 밴드선을 그린 차트입니다. 주가 시계열에 데이터 라벨이 없어 눈금으로 추정하면 오차가 커지므로 옮기지 않았고, 인쇄된 밴드 배수만 위 표에 실었습니다.

Sheet 07_도표3_PBR_Band
A1: 도표 3. ISC 12MF P/B Band
A2: 원문은 차트여서 주가 시계열이 인쇄되어 있지 않습니다. 인쇄된 밴드 배수만 옮겼습니다.
A4: 밴드 | B4: 배수 (배) | E4: 비고
A5: Band 1 (상단) | B5: 5.1 | E5: 원문 차트에 표기된 밴드 배수
A6: Band 2 | B6: 4.2 | E6: 원문 차트에 표기된 밴드 배수
A7: Band 3 (중단) | B7: 3.2 | E7: 원문 차트에 표기된 밴드 배수
A8: Band 4 | B8: 2.3 | E8: 원문 차트에 표기된 밴드 배수
A9: Band 5 (하단) | B9: 1.3 | E9: 원문 차트에 표기된 밴드 배수
A10: 자료: FnGuide, 하나증권
A12: 정합성 체크 (밴드 배수 기준 내재주가 — 원문에 없는 파생 계산)
A13: 밴드 | B13: 배수 (배) | C13: 내재주가 (원) | D13: 현재주가 대비 | E13: 비고
A14: Band 1 (상단) | B14: =$B$5 -> 5.1 | C14: =$B14*'17_p5_투자지표'!$E$7 -> 148710.9 | D14: =$C14/'05_도표1_Valuation'!$C$9-1 -> 0.039209644 | E14: 2026F BPS 29,159원 적용 (참고용)
A15: Band 2 | B15: =$B$6 -> 4.2 | C15: =$B15*'17_p5_투자지표'!$E$7 -> 122467.8 | D15: =$C15/'05_도표1_Valuation'!$C$9-1 -> -0.14418029 | E15: 2026F BPS 29,159원 적용 (참고용)
A16: Band 3 (중단) | B16: =$B$7 -> 3.2 | C16: =$B16*'17_p5_투자지표'!$E$7 -> 93308.8 | D16: =$C16/'05_도표1_Valuation'!$C$9-1 -> -0.34794689 | E16: 2026F BPS 29,159원 적용 (참고용)
A17: Band 4 | B17: =$B$8 -> 2.3 | C17: =$B17*'17_p5_투자지표'!$E$7 -> 67065.7 | D17: =$C17/'05_도표1_Valuation'!$C$9-1 -> -0.53133683 | E17: 2026F BPS 29,159원 적용 (참고용)
A18: Band 5 (하단) | B18: =$B$9 -> 1.3 | C18: =$B18*'17_p5_투자지표'!$E$7 -> 37906.7 | D18: =$C18/'05_도표1_Valuation'!$C$9-1 -> -0.73510342 | E18: 2026F BPS 29,159원 적용 (참고용)
A19: 현재 내재 P/B | B19: ='05_도표1_Valuation'!$C$9/'17_p5_투자지표'!$E$7 -> 4.9075757 | C19: ='05_도표1_Valuation'!$C$9 -> 143100 | E19: 현재주가 ÷ 2026F BPS. 원문 투자지표의 2026F PBR 4.91배와 일치
A21: 주) 원문 도표 3은 21.1~26.1 구간의 수정주가와 5개 밴드선을 그린 차트입니다. 도표 2와 같은 이유로 밴드 배수만 옮겼습니다.

Sheet 08_도표4_분기실적_수정후
A1: 도표 4. ISC의 분기별 실적 전망 (수정 후)
A2: 단위: 십억원, % / 음영 = 전망치(F) 및 연간 열
A4: 구분 | B4: 1Q25 | C4: 2Q25 | D4: 3Q25 | E4: 4Q25 | F4: 1Q26F | G4: 2Q26F | H4: 3Q26F | I4: 4Q26F | J4: 2024 | K4: 2025 | L4: 2026F | M4: 단위
A5: 매출액 | B5: 31.7 | C5: 51.7 | D5: 64.5 | E5: 72.3 | F5: 66.5 | G5: 71 | H5: 77.1 | I5: 88.4 | J5: 174.5 | K5: 220.1 | L5: 302.9 | M5: 십억원
A6: YoY | B6: -0.1 | C6: 0.04 | D6: 0.28 | E6: 0.84 | F6: 1.1 | G6: 0.37 | H6: 0.2 | I6: 0.22 | J6: 0.24 | K6: 0.26 | L6: 0.38 | M6: %
A7: QoQ | B7: -0.19 | C7: 0.63 | D7: 0.25 | E7: 0.12 | F7: -0.08 | G7: 0.07 | H7: 0.09 | I7: 0.15 | M7: %
A8: 데이터센터 | B8: 16.9 | C8: 33.1 | D8: 44 | E8: 54.4 | F8: 47.3 | G8: 50.6 | H8: 57.2 | I8: 62.9 | J8: 78.8 | K8: 148.4 | L8: 218.1 | M8: 십억원
A9: 스마트폰 | B9: 9.5 | C9: 14 | D9: 13.5 | E9: 12 | F9: 9.6 | G9: 10.6 | H9: 10.6 | I9: 10 | J9: 46.1 | K9: 49 | L9: 40.8 | M9: 십억원
A10: PC/Laptop | B10: 3.2 | C10: 3 | D10: 4.5 | E10: 3 | F10: 3.4 | G10: 3.5 | H10: 3.6 | I10: 3.4 | J10: 29.2 | K10: 13.7 | L10: 13.9 | M10: 십억원
A11: 오토모티브 | B11: 1 | C11: 0.7 | D11: 1.5 | E11: 1.9 | F11: 3.3 | G11: 2.8 | H11: 3.4 | I11: 4.8 | J11: 8.2 | K11: 5.1 | L11: 14.3 | M11: 십억원
A12: 웨어러블 | B12: 0.7 | C12: 0.7 | D12: 0.8 | E12: 1 | F12: 0.8 | G12: 0.8 | H12: 0.9 | I12: 0.9 | J12: 5.6 | K12: 3.2 | L12: 3.4 | M12: 십억원
A13: LSI | B13: 0 | C13: 0 | D13: 0 | E13: 0 | F13: 0 | G13: 0 | H13: 0 | I13: 0 | J13: 4.7 | K13: 0 | L13: 0 | M13: 십억원
A14: 기타 | B14: 0.4 | C14: 0.2 | D14: 0.2 | E14: 0 | F14: 2 | G14: 2.7 | H14: 1.5 | I14: 6.3 | J14: 2 | K14: 0.8 | L14: 12.5 | M14: 십억원
A15: 영업이익 | B15: 7 | C15: 13.7 | D15: 17.4 | E15: 21.9 | F15: 20.6 | G15: 21.5 | H15: 22.7 | I15: 28.9 | J15: 44.8 | K15: 60 | L15: 93.7 | M15: 십억원
A16: YoY | B16: -0.18 | C16: -0.08 | D16: 0.26 | E16: 1.92 | F16: 1.94 | G16: 0.57 | H16: 0.31 | I16: 0.32 | J16: 3.17 | K16: 0.34 | L16: 0.56 | M16: %
A17: QoQ | B17: -0.07 | C17: 0.96 | D17: 0.27 | E17: 0.26 | F17: -0.06 | G17: 0.05 | H17: 0.06 | I17: 0.27 | M17: %
A18: OPM | B18: 0.22 | C18: 0.27 | D18: 0.27 | E18: 0.3 | F18: 0.31 | G18: 0.3 | H18: 0.29 | I18: 0.33 | J18: 0.26 | K18: 0.27 | L18: 0.31 | M18: %
A19: 자료: ISC, 하나증권
A21: 정합성 체크 (원문 수치를 수식으로 재계산)
A22: 체크 항목 | B22: 1Q25 | C22: 2Q25 | D22: 3Q25 | E22: 4Q25 | F22: 1Q26F | G22: 2Q26F | H22: 3Q26F | I22: 4Q26F | J22: 2024 | K22: 2025 | L22: 2026F | M22: 단위
A23: 어플리케이션 합계 | B23: =B$8+B$9+B$10+B$11+B$12+B$13+B$14 -> 31.7 | C23: =C$8+C$9+C$10+C$11+C$12+C$13+C$14 -> 51.7 | D23: =D$8+D$9+D$10+D$11+D$12+D$13+D$14 -> 64.5 | E23: =E$8+E$9+E$10+E$11+E$12+E$13+E$14 -> 72.3 | F23: =F$8+F$9+F$10+F$11+F$12+F$13+F$14 -> 66.4 | G23: =G$8+G$9+G$10+G$11+G$12+G$13+G$14 -> 71 | H23: =H$8+H$9+H$10+H$11+H$12+H$13+H$14 -> 77.2 | I23: =I$8+I$9+I$10+I$11+I$12+I$13+I$14 -> 88.3 | ... L23: =L$8+L$9+L$10+L$11+L$12+L$13+L$14 -> 303 | M23: 십억원
A24: vs 원문 매출액 (차이) | B24: =B$23-B$5 -> 0 | C24: =C$23-C$5 -> 0 | D24: =D$23-D$5 -> 0 | E24: =E$23-E$5 -> 0 | F24: =F$23-F$5 -> -0.1 | G24: =G$23-G$5 -> 0 | H24: =H$23-H$5 -> 0.1 | I24: =I$23-I$5 -> -0.1 | ... L24: =L$23-L$5 -> 0.1 | M24: 십억원
A25: OPM 재계산 (영업이익/매출액) | B25: =IFERROR(B$15/B$5,"") -> 0.22082019 | C25: =IFERROR(C$15/C$5,"") -> 0.26499033 | D25: =IFERROR(D$15/D$5,"") -> 0.26976744 | E25: =IFERROR(E$15/E$5,"") -> 0.30290456 | F25: =IFERROR(F$15/F$5,"") -> 0.30977444 | G25: =IFERROR(G$15/G$5,"") -> 0.3028169 | H25: =IFERROR(H$15/H$5,"") -> 0.29442283 | I25: =IFERROR(I$15/I$5,"") -> 0.32692308 | ... L25: =IFERROR(L$15/L$5,"") -> 0.30934302 | M25: %
A26: 매출 QoQ 재계산 | C26: =C$5/B$5-1 -> 0.63091483 | D26: =D$5/C$5-1 -> 0.24758221 | E26: =E$5/D$5-1 -> 0.12093023 | F26: =F$5/E$5-1 -> -0.0802213 | G26: =G$5/F$5-1 -> 0.067669173 | H26: =H$5/G$5-1 -> 0.085915493 | I26: =I$5/H$5-1 -> 0.14656291 | M26: %
A27: 매출 YoY 재계산 (2026F/2025) | L27: =L$5/K$5-1 -> 0.37619264 | M27: %
A28: 영업이익 YoY 재계산 (2026F/2025) | L28: =L$15/K$15-1 -> 0.56166667 | M28: %
A29: 분기 합계 (1Q~4Q) | K29: =SUM(B$5:E$5) -> 220.2 | L29: =SUM(F$5:I$5) -> 303 | M29: 십억원
A31: 주) 원문 연간 수치와 분기 합계 사이의 0.1 내외 차이는 보고서의 소수 첫째자리 반올림 표기에서 발생하는 것으로, 오기입이 아닙니다. YoY·QoQ의 원문값(기울임 파란 글씨)은 반올림 정수 %이며, 재계산값과 1%p 내외 차이가 날 수 있습니다.

Sheet 09_도표5_분기실적_수정전
A1: 도표 5. ISC의 분기별 실적 전망 (수정 전)
A2: 단위: 십억원, % / 음영 = 전망치(F) 및 연간 열
A4: 구분 | B4: 1Q24 | C4: 2Q24 | D4: 3Q24 | E4: 4Q24 | F4: 1Q25 | G4: 2Q25 | H4: 3Q25 | I4: 4Q25F | J4: 2024 | K4: 2025F | L4: 2026F | M4: 단위
A5: 매출액 | B5: 35.1 | C5: 49.8 | D5: 50.4 | E5: 39.3 | F5: 31.7 | G5: 51.7 | H5: 64.5 | I5: 68.2 | J5: 174.5 | K5: 216.1 | L5: 301.6 | M5: 십억원
A6: YoY | B6: -0.24 | C6: 0.38 | D6: 0.53 | E6: 0.57 | F6: -0.1 | G6: 0.04 | H6: 0.28 | I6: 0.74 | J6: 0.24 | K6: 0.24 | L6: 0.4 | M6: %
A7: QoQ | B7: 0.41 | C7: 0.42 | D7: 0.01 | E7: -0.22 | F7: -0.19 | G7: 0.63 | H7: 0.25 | I7: 0.06 | M7: %
A8: 데이터센터 | B8: 17.6 | C8: 19.8 | D8: 22.5 | E8: 19 | F8: 16.9 | G8: 33.1 | H8: 44 | I8: 48.4 | J8: 78.8 | K8: 142.4 | L8: 226.1 | M8: 십억원
A9: 스마트폰 | B9: 10.5 | C9: 12 | D9: 15 | E9: 8.6 | F9: 9.5 | G9: 14 | H9: 13.5 | I9: 8.1 | J9: 46.1 | K9: 45.1 | L9: 34.5 | M9: 십억원
A10: PC/Laptop | B10: 2.9 | C10: 8 | D10: 10 | E10: 8.3 | F10: 3.2 | G10: 3 | H10: 4.5 | I10: 4.8 | J10: 29.2 | K10: 15.5 | L10: 16.4 | M10: 십억원
A11: 오토모티브 | B11: 1.8 | C11: 2 | D11: 1.5 | E11: 2.9 | F11: 1 | G11: 0.7 | H11: 1.5 | I11: 2.5 | J11: 8.2 | K11: 5.7 | L11: 11.3 | M11: 십억원
A12: 웨어러블 | B12: 1.8 | C12: 2.8 | D12: 1 | E12: 0 | F12: 0.7 | G12: 0.7 | H12: 0.8 | I12: 0.6 | J12: 5.6 | K12: 2.8 | L12: 2.7 | M12: 십억원
A13: LSI | B13: 0 | C13: 4.7 | D13: 0 | E13: 0 | F13: 0 | G13: 0 | H13: 0 | I13: 0 | J13: 4.7 | K13: 0 | L13: 0 | M13: 십억원
A14: 기타 | B14: 0.5 | C14: 0.5 | D14: 0.5 | E14: 0.5 | F14: 0.4 | G14: 0.2 | H14: 0.2 | I14: 3.9 | J14: 2 | K14: 4.7 | L14: 10.6 | M14: 십억원
A15: 영업이익 | B15: 8.6 | C15: 14.9 | D15: 13.8 | E15: 7.5 | F15: 7 | G15: 13.7 | H15: 17.4 | I15: 19.4 | J15: 44.8 | K15: 57.5 | L15: 86.5 | M15: 십억원
A16: YoY | B16: -0.12 | C16: 1.3 | D16: -2.73 | E16: 2.04 | F16: -0.18 | G16: -0.08 | H16: 0.26 | I16: 1.59 | J16: 3.17 | K16: 0.28 | L16: 0.5 | M16: %
A17: QoQ | B17: 2.47 | C17: 0.74 | D17: -0.07 | E17: -0.46 | F17: -0.07 | G17: 0.96 | H17: 0.27 | I17: 0.12 | M17: %
A18: OPM | B18: 0.24 | C18: 0.3 | D18: 0.27 | E18: 0.19 | F18: 0.22 | G18: 0.27 | H18: 0.27 | I18: 0.28 | J18: 0.26 | K18: 0.27 | L18: 0.29 | M18: %
A19: 자료: ISC, 하나증권
A21: 정합성 체크 (원문 수치를 수식으로 재계산)
A22: 체크 항목 | B22: 1Q24 | C22: 2Q24 | D22: 3Q24 | E22: 4Q24 | F22: 1Q25 | G22: 2Q25 | H22: 3Q25 | I22: 4Q25F | J22: 2024 | K22: 2025F | L22: 2026F | M22: 단위
A23: 어플리케이션 합계 | B23: =B$8+B$9+B$10+B$11+B$12+B$13+B$14 -> 35.1 | C23: =C$8+C$9+C$10+C$11+C$12+C$13+C$14 -> 49.8 | D23: =D$8+D$9+D$10+D$11+D$12+D$13+D$14 -> 50.5 | E23: =E$8+E$9+E$10+E$11+E$12+E$13+E$14 -> 39.3 | F23: =F$8+F$9+F$10+F$11+F$12+F$13+F$14 -> 31.7 | G23: =G$8+G$9+G$10+G$11+G$12+G$13+G$14 -> 51.7 | H23: =H$8+H$9+H$10+H$11+H$12+H$13+H$14 -> 64.5 | I23: =I$8+I$9+I$10+I$11+I$12+I$13+I$14 -> 68.3 | ... L23: =L$8+L$9+L$10+L$11+L$12+L$13+L$14 -> 301.6 | M23: 십억원
A24: vs 원문 매출액 (차이) | B24: =B$23-B$5 -> 0 | C24: =C$23-C$5 -> 0 | D24: =D$23-D$5 -> 0.1 | E24: =E$23-E$5 -> 0 | F24: =F$23-F$5 -> 0 | G24: =G$23-G$5 -> 0 | H24: =H$23-H$5 -> 0 | I24: =I$23-I$5 -> 0.1 | ... L24: =L$23-L$5 -> 0 | M24: 십억원
A25: OPM 재계산 (영업이익/매출액) | B25: =IFERROR(B$15/B$5,"") -> 0.24501425 | C25: =IFERROR(C$15/C$5,"") -> 0.29919679 | D25: =IFERROR(D$15/D$5,"") -> 0.27380952 | E25: =IFERROR(E$15/E$5,"") -> 0.19083969 | F25: =IFERROR(F$15/F$5,"") -> 0.22082019 | G25: =IFERROR(G$15/G$5,"") -> 0.26499033 | H25: =IFERROR(H$15/H$5,"") -> 0.26976744 | I25: =IFERROR(I$15/I$5,"") -> 0.28445748 | ... L25: =IFERROR(L$15/L$5,"") -> 0.28680371 | M25: %
A26: 매출 QoQ 재계산 | C26: =C$5/B$5-1 -> 0.41880342 | D26: =D$5/C$5-1 -> 0.012048193 | E26: =E$5/D$5-1 -> -0.2202381 | F26: =F$5/E$5-1 -> -0.19338422 | G26: =G$5/F$5-1 -> 0.63091483 | H26: =H$5/G$5-1 -> 0.24758221 | I26: =I$5/H$5-1 -> 0.057364341 | M26: %
A27: 매출 YoY 재계산 (2026F/2025) | L27: =L$5/K$5-1 -> 0.39565016 | M27: %
A28: 영업이익 YoY 재계산 (2026F/2025) | L28: =L$15/K$15-1 -> 0.50434783 | M28: %
A29: 분기 합계 (1Q~4Q) | K29: =SUM(B$5:E$5) -> 174.6 | L29: =SUM(F$5:I$5) -> 216.1 | M29: 십억원
A31: 주) 원문 연간 수치와 분기 합계 사이의 0.1 내외 차이는 보고서의 소수 첫째자리 반올림 표기에서 발생하는 것으로, 오기입이 아닙니다. YoY·QoQ의 원문값(기울임 파란 글씨)은 반올림 정수 %이며, 재계산값과 1%p 내외 차이가 날 수 있습니다.

Sheet 10_도표6_사업개요_시너지
A1: 도표 6. 아이세미 / 테크드림 사업개요 및 시너지 효과
A2: 장비 소재 사업 부문과의 시너지 효과 본격화 기대
A4: 회사 | B4: 사업 부문 | C4: 사업 개요 | D4: ISC 시너지
A5: 아이세미 | B5: 모듈 테스터 | C5: DRAM 모듈의 CPU 호환성 및 신뢰성 평가 장비 제작/판매 | D5: • HBM, 글로벌 CPU, GPU 고객사 실장 테스트소켓 공동개발 및 장비/소켓 턴키 공급 • LPCAMM, SOCAMM 모듈 테스트 솔루션 개발
A6: 아이세미 | B6: 번인 테스터 (신규사업) | C6: 고온/저온 환경에서 고속으로 NAND 패키지의 성능 평가 장비 제작/판매 | D6: • 기존 번인소켓 대비 소켓 탑재량이 증가하면서 번인소켓 매출 증가 효과
A7: 아이세미 | B7: 세정용 케미컬 | C7: • 식각 공정 후 발생된 이물질 제거를 위해 세정 시 사용하는 용액 제작/판매 • 업계 유일 초순수를 사용 | D7: • HBM 소재부품 매출 증가 효과
A8: 아이세미 | B8: EFEM (신규사업) | C8: 반도체 웨이퍼 등의 이동, 로딩/언로딩, 정렬 장비 제작/판매 | D8: • 신사업 포트폴리오 확장
A9: 테크드림 | B9: PCB 기판 | C9: 모듈 제작용 PCB 회로 기판 중개 판매 | D9: • 테스터-보드-소켓의 Total Test Solution 라인업 구축
A11: 자료: ISC, 하나증권
A12: 주) 원문은 이미지 형태의 도식이며, 인쇄된 문구를 그대로 옮겼습니다. 각 사업 부문의 제품 사진은 옮기지 않았습니다.

Sheet 11_도표7_영업이익_시가총액
A1: 도표 7. ISC 분기 영업이익 vs 시가총액 추이
A2: 원문은 20.1~26.1 구간 이중축 차트입니다. 분기 영업이익은 1Q23부터, 시가총액은 1Q22부터 공개 자료로 확보했습니다. 회색 칸은 미확보 구간입니다.
A4: 구분 | B4: 1Q22 | C4: 2Q22 | D4: 3Q22 | E4: 4Q22 | F4: 1Q23 | G4: 2Q23 | H4: 3Q23 | I4: 4Q23 | J4: 1Q24 | K4: 2Q24 | L4: 3Q24 | M4: 4Q24 | N4: 1Q25 | O4: 2Q25 | P4: 3Q25 | Q4: 4Q25 | R4: 1Q26 | S4: 2Q26 | T4: 3Q26F | U4: 4Q26F | V4: 단위
A5: 영업이익 (확정) | F5: 9.8 | G5: 6.5 | H5: -8 | I5: 2.5 | J5: ='09_도표5_분기실적_수정전'!$B$15 -> 8.6 | K5: ='09_도표5_분기실적_수정전'!$C$15 -> 14.9 | L5: ='09_도표5_분기실적_수정전'!$D$15 -> 13.8 | M5: ='09_도표5_분기실적_수정전'!$E$15 -> 7.5 | N5: ='08_도표4_분기실적_수정후'!$B$15 -> 7 | O5: ='08_도표4_분기실적_수정후'!$C$15 -> 13.7 | P5: ='08_도표4_분기실적_수정후'!$D$15 -> 17.4 | Q5: ='08_도표4_분기실적_수정후'!$E$15 -> 21.9 | R5: 23.6 | V5: 십억원
A6: 영업이익 (하나증권 추정) | R6: ='08_도표4_분기실적_수정후'!$F$15 -> 20.6 | S6: ='08_도표4_분기실적_수정후'!$G$15 -> 21.5 | T6: ='08_도표4_분기실적_수정후'!$H$15 -> 22.7 | U6: ='08_도표4_분기실적_수정후'!$I$15 -> 28.9 | V6: 십억원
A7: 매출액 (확정) | F7: 46.4 | G7: 36 | H7: 32.9 | I7: 24.9 | J7: ='09_도표5_분기실적_수정전'!$B$5 -> 35.1 | K7: ='09_도표5_분기실적_수정전'!$C$5 -> 49.8 | L7: ='09_도표5_분기실적_수정전'!$D$5 -> 50.4 | M7: ='09_도표5_분기실적_수정전'!$E$5 -> 39.3 | N7: ='08_도표4_분기실적_수정후'!$B$5 -> 31.7 | O7: ='08_도표4_분기실적_수정후'!$C$5 -> 51.7 | P7: ='08_도표4_분기실적_수정후'!$D$5 -> 64.5 | Q7: ='08_도표4_분기실적_수정후'!$E$5 -> 72.3 | R7: 68.3 | V7: 십억원
A8: OPM (확정) | B8: =IFERROR(B$5/B$7,"") | C8: =IFERROR(C$5/C$7,"") | D8: =IFERROR(D$5/D$7,"") | E8: =IFERROR(E$5/E$7,"") | F8: =IFERROR(F$5/F$7,"") -> 0.2112069 | G8: =IFERROR(G$5/G$7,"") -> 0.18055556 | H8: =IFERROR(H$5/H$7,"") -> -0.24316109 | I8: =IFERROR(I$5/I$7,"") -> 0.10040161 | ... U8: =IFERROR(U$5/U$7,"") | V8: %
A9: 분기말 종가 | B9: 29750 | C9: 31200 | D9: 32200 | E9: 31350 | F9: 40000 | G9: 55200 | H9: 78800 | I9: 80300 | J9: 98000 | K9: 65500 | L9: 57900 | M9: 72100 | N9: 51800 | O9: 59800 | P9: 77800 | Q9: 111100 | R9: 233000 | S9: 181500 | V9: 원
A10: 상장주식수 | B10: 17339.471 | C10: 17339.471 | D10: 17339.471 | E10: 17339.471 | F10: 17339.471 | G10: 17339.471 | H10: 17339.471 | I10: 21137.058 | J10: 21137.058 | K10: 21137.058 | L10: 21137.058 | M10: 21137.058 | N10: 21137.058 | O10: 21137.058 | P10: 21137.058 | Q10: 21197.058 | R10: 21197.058 | S10: 21197.058 | V10: 천주
A11: 시가총액 | B11: =B$9*B$10/1000000 -> 515.84926 | C11: =C$9*C$10/1000000 -> 540.9915 | D11: =D$9*D$10/1000000 -> 558.33097 | E11: =E$9*E$10/1000000 -> 543.59242 | F11: =F$9*F$10/1000000 -> 693.57884 | G11: =G$9*G$10/1000000 -> 957.1388 | H11: =H$9*H$10/1000000 -> 1366.3503 | I11: =I$9*I$10/1000000 -> 1697.3058 | ... S11: =S$9*S$10/1000000 -> 3847.266 | V11: 십억원
A12: 영업이익 연율화 (당분기 ×4) | B12: =IF(B$5="","",B$5*4) | C12: =IF(C$5="","",C$5*4) | D12: =IF(D$5="","",D$5*4) | E12: =IF(E$5="","",E$5*4) | F12: =IF(F$5="","",F$5*4) -> 39.2 | G12: =IF(G$5="","",G$5*4) -> 26 | H12: =IF(H$5="","",H$5*4) -> -32 | I12: =IF(I$5="","",I$5*4) -> 10 | ... U12: =IF(U$5="","",U$5*4) | V12: 십억원
A13: 영업이익 TTM (최근 4개 분기 합) | E13: =IF(COUNT(B$5:E$5)<4,"",SUM(B$5:E$5)) | F13: =IF(COUNT(C$5:F$5)<4,"",SUM(C$5:F$5)) | G13: =IF(COUNT(D$5:G$5)<4,"",SUM(D$5:G$5)) | H13: =IF(COUNT(E$5:H$5)<4,"",SUM(E$5:H$5)) | I13: =IF(COUNT(F$5:I$5)<4,"",SUM(F$5:I$5)) -> 10.8 | J13: =IF(COUNT(G$5:J$5)<4,"",SUM(G$5:J$5)) -> 9.6 | K13: =IF(COUNT(H$5:K$5)<4,"",SUM(H$5:K$5)) -> 18 | L13: =IF(COUNT(I$5:L$5)<4,"",SUM(I$5:L$5)) -> 39.8 | ... U13: =IF(COUNT(R$5:U$5)<4,"",SUM(R$5:U$5)) | V13: 십억원
A14: 시가총액 / 연율화 영업이익 | B14: =IFERROR(B$11/B$12,"") | C14: =IFERROR(C$11/C$12,"") | D14: =IFERROR(D$11/D$12,"") | E14: =IFERROR(E$11/E$12,"") | F14: =IFERROR(F$11/F$12,"") -> 17.693338 | G14: =IFERROR(G$11/G$12,"") -> 36.813031 | H14: =IFERROR(H$11/H$12,"") -> -42.698447 | I14: =IFERROR(I$11/I$12,"") -> 169.73058 | ... U14: =IFERROR(U$11/U$12,"") | V14: 배
A15: 시가총액 / TTM 영업이익 | B15: =IFERROR(B$11/B$13,"") | C15: =IFERROR(C$11/C$13,"") | D15: =IFERROR(D$11/D$13,"") | E15: =IFERROR(E$11/E$13,"") | F15: =IFERROR(F$11/F$13,"") | G15: =IFERROR(G$11/G$13,"") | H15: =IFERROR(H$11/H$13,"") | I15: =IFERROR(I$11/I$13,"") -> 157.15794 | ... U15: =IFERROR(U$11/U$13,"") | V15: 배
A17: 주) 회색 칸은 공개 자료로 확보하지 못한 구간입니다. 2020~2022년 분기 영업이익은 DART 분기·반기보고서를 직접 열어야 채울 수 있습니다 (연간값은 13_도표9_연간실적추이 시트에 2018년부터 들어 있습니다).
A18: 주) 3Q23 영업이익 -8.0십억원(적자)은 하나증권 도표 5의 3Q24 영업이익 YoY -273%와 정확히 맞아떨어집니다 (13.8 ÷ (1-2.73) = -7.98). 미래에셋·IM증권 두 리포트의 값도 동일해 교차검증됩니다.
A19: 주) 3Q23 → 4Q23 시가총액 증가는 주가(78,800 → 80,300원, +1.9%)보다 주식수(17,339천주 → 21,137천주, +21.9%) 요인이 큽니다. 2023년 8월 유상증자 때문이므로 시가총액 레벨 변화를 주가 상승으로 읽지 않도록 주의하세요.
A20: 주) 상장주식수가 21,137,058주에서 21,197,058주로 늘어난 정확한 시점은 확인하지 못했습니다. 하나증권 리포트의 2026.02.04 시가총액 3,033.3십억원이 21,197,058주 기준이므로 4Q25부터 적용했습니다. 필요하면 해당 행을 직접 수정하세요.
A22: 출처 (셀 단위 근거)
A23: 항목 | B23: 출처 | I23: URL / 접수번호
A24: 영업이익·매출액 1Q23~4Q23 | B24: 미래에셋증권 2026.01.29 리포트 및 IM증권 2025.10.13 리포트 (두 리포트 수치 동일) | I24: miraeasset / imfnsec PDF
A25: 영업이익·매출액 1Q24~4Q24 | B25: 하나증권 4Q25 실적리뷰 도표 5 (11번 시트 참조) | I25: 본 워크북 내부 참조
A26: 영업이익·매출액 1Q25~4Q25 | B26: 하나증권 4Q25 실적리뷰 도표 4 (10번 시트 참조) | I26: 본 워크북 내부 참조
A27: 영업이익·매출액 1Q26 (확정) | B27: 연결재무제표기준영업(잠정)실적 공정공시 2026.04.27 — 매출 683억 / 영업이익 236억 / 순이익 206억 | I27: DART 접수번호 20260427900108
A28: 영업이익 1Q26F~4Q26F | B28: 하나증권 4Q25 실적리뷰 도표 4 추정치 | I28: 본 워크북 내부 참조
A29: 분기말 종가·상장주식수 | B29: 03_p1_주가추이 시트의 출처와 동일 | I29: stockanalysis / MarketScreener / SK증권
A72: 주) 세 번째 차트의 배수는 2023년 실적 저점(TTM 영업이익 10.8십억원) 때문에 4Q23~3Q24 구간이 100배를 넘습니다. 이익이 0에 가까운 구간의 배수는 해석하기 어렵다는 점을 감안해 보시고, 그 구간은 절대 이익 금액(첫 번째 차트)으로 판단하는 편이 낫습니다.
A73: 주) 원문처럼 두 계열을 한 그림에 겹치지 않고 나눈 것은, 이중축 차트가 두 축의 눈금을 자의적으로 맞추게 되어 '영업이익이 시가총액을 따라간다'는 식의 잘못된 인상을 주기 쉽기 때문입니다. 세 번째 차트가 그 관계를 배수로 직접 보여줍니다.

Sheet 12_도표8_어플리케이션별_매출
A1: 도표 8. ISC 어플리케이션별 매출 비중 추이
A2: 원문 구간은 1Q21~3Q25입니다. 어플리케이션 구분은 하나증권 자체 분류라 공시 항목이 아니고, 표로 인쇄된 1Q24 이후만 확보됩니다. 다른 기준(메모리/비메모리, AI/비AI)의 매출 분해는 D3_매출분해_대체분류 시트에 있습니다.
A4: ① 어플리케이션별 매출 (십억원) — 하나증권 도표 4·5
A5: 구분 | B5: 1Q24 | C5: 2Q24 | D5: 3Q24 | E5: 4Q24 | F5: 1Q25 | G5: 2Q25 | H5: 3Q25 | I5: 4Q25 | J5: 1Q26F | K5: 2Q26F | L5: 3Q26F | M5: 4Q26F
A6: 매출액 | B6: ='09_도표5_분기실적_수정전'!$B$5 -> 35.1 | C6: ='09_도표5_분기실적_수정전'!$C$5 -> 49.8 | D6: ='09_도표5_분기실적_수정전'!$D$5 -> 50.4 | E6: ='09_도표5_분기실적_수정전'!$E$5 -> 39.3 | F6: ='08_도표4_분기실적_수정후'!$B$5 -> 31.7 | G6: ='08_도표4_분기실적_수정후'!$C$5 -> 51.7 | H6: ='08_도표4_분기실적_수정후'!$D$5 -> 64.5 | I6: ='08_도표4_분기실적_수정후'!$E$5 -> 72.3 | J6: ='08_도표4_분기실적_수정후'!$F$5 -> 66.5 | K6: ='08_도표4_분기실적_수정후'!$G$5 -> 71 | L6: ='08_도표4_분기실적_수정후'!$H$5 -> 77.1 | M6: ='08_도표4_분기실적_수정후'!$I$5 -> 88.4
A7: 데이터센터 | B7: ='09_도표5_분기실적_수정전'!$B$8 -> 17.6 | C7: ='09_도표5_분기실적_수정전'!$C$8 -> 19.8 | D7: ='09_도표5_분기실적_수정전'!$D$8 -> 22.5 | E7: ='09_도표5_분기실적_수정전'!$E$8 -> 19 | F7: ='08_도표4_분기실적_수정후'!$B$8 -> 16.9 | G7: ='08_도표4_분기실적_수정후'!$C$8 -> 33.1 | H7: ='08_도표4_분기실적_수정후'!$D$8 -> 44 | I7: ='08_도표4_분기실적_수정후'!$E$8 -> 54.4 | J7: ='08_도표4_분기실적_수정후'!$F$8 -> 47.3 | K7: ='08_도표4_분기실적_수정후'!$G$8 -> 50.6 | L7: ='08_도표4_분기실적_수정후'!$H$8 -> 57.2 | M7: ='08_도표4_분기실적_수정후'!$I$8 -> 62.9
A8: 스마트폰 | B8: ='09_도표5_분기실적_수정전'!$B$9 -> 10.5 | C8: ='09_도표5_분기실적_수정전'!$C$9 -> 12 | D8: ='09_도표5_분기실적_수정전'!$D$9 -> 15 | E8: ='09_도표5_분기실적_수정전'!$E$9 -> 8.6 | F8: ='08_도표4_분기실적_수정후'!$B$9 -> 9.5 | G8: ='08_도표4_분기실적_수정후'!$C$9 -> 14 | H8: ='08_도표4_분기실적_수정후'!$D$9 -> 13.5 | I8: ='08_도표4_분기실적_수정후'!$E$9 -> 12 | J8: ='08_도표4_분기실적_수정후'!$F$9 -> 9.6 | K8: ='08_도표4_분기실적_수정후'!$G$9 -> 10.6 | L8: ='08_도표4_분기실적_수정후'!$H$9 -> 10.6 | M8: ='08_도표4_분기실적_수정후'!$I$9 -> 10
A9: PC/Laptop | B9: ='09_도표5_분기실적_수정전'!$B$10 -> 2.9 | C9: ='09_도표5_분기실적_수정전'!$C$10 -> 8 | D9: ='09_도표5_분기실적_수정전'!$D$10 -> 10 | E9: ='09_도표5_분기실적_수정전'!$E$10 -> 8.3 | F9: ='08_도표4_분기실적_수정후'!$B$10 -> 3.2 | G9: ='08_도표4_분기실적_수정후'!$C$10 -> 3 | H9: ='08_도표4_분기실적_수정후'!$D$10 -> 4.5 | I9: ='08_도표4_분기실적_수정후'!$E$10 -> 3 | J9: ='08_도표4_분기실적_수정후'!$F$10 -> 3.4 | K9: ='08_도표4_분기실적_수정후'!$G$10 -> 3.5 | L9: ='08_도표4_분기실적_수정후'!$H$10 -> 3.6 | M9: ='08_도표4_분기실적_수정후'!$I$10 -> 3.4
A10: 오토모티브 | B10: ='09_도표5_분기실적_수정전'!$B$11 -> 1.8 | C10: ='09_도표5_분기실적_수정전'!$C$11 -> 2 | D10: ='09_도표5_분기실적_수정전'!$D$11 -> 1.5 | E10: ='09_도표5_분기실적_수정전'!$E$11 -> 2.9 | F10: ='08_도표4_분기실적_수정후'!$B$11 -> 1 | G10: ='08_도표4_분기실적_수정후'!$C$11 -> 0.7 | H10: ='08_도표4_분기실적_수정후'!$D$11 -> 1.5 | I10: ='08_도표4_분기실적_수정후'!$E$11 -> 1.9 | J10: ='08_도표4_분기실적_수정후'!$F$11 -> 3.3 | K10: ='08_도표4_분기실적_수정후'!$G$11 -> 2.8 | L10: ='08_도표4_분기실적_수정후'!$H$11 -> 3.4 | M10: ='08_도표4_분기실적_수정후'!$I$11 -> 4.8
A11: 웨어러블 | B11: ='09_도표5_분기실적_수정전'!$B$12 -> 1.8 | C11: ='09_도표5_분기실적_수정전'!$C$12 -> 2.8 | D11: ='09_도표5_분기실적_수정전'!$D$12 -> 1 | E11: ='09_도표5_분기실적_수정전'!$E$12 -> 0 | F11: ='08_도표4_분기실적_수정후'!$B$12 -> 0.7 | G11: ='08_도표4_분기실적_수정후'!$C$12 -> 0.7 | H11: ='08_도표4_분기실적_수정후'!$D$12 -> 0.8 | I11: ='08_도표4_분기실적_수정후'!$E$12 -> 1 | J11: ='08_도표4_분기실적_수정후'!$F$12 -> 0.8 | K11: ='08_도표4_분기실적_수정후'!$G$12 -> 0.8 | L11: ='08_도표4_분기실적_수정후'!$H$12 -> 0.9 | M11: ='08_도표4_분기실적_수정후'!$I$12 -> 0.9
A12: LSI | B12: ='09_도표5_분기실적_수정전'!$B$13 -> 0 | C12: ='09_도표5_분기실적_수정전'!$C$13 -> 4.7 | D12: ='09_도표5_분기실적_수정전'!$D$13 -> 0 | E12: ='09_도표5_분기실적_수정전'!$E$13 -> 0 | F12: ='08_도표4_분기실적_수정후'!$B$13 -> 0 | G12: ='08_도표4_분기실적_수정후'!$C$13 -> 0 | H12: ='08_도표4_분기실적_수정후'!$D$13 -> 0 | I12: ='08_도표4_분기실적_수정후'!$E$13 -> 0 | J12: ='08_도표4_분기실적_수정후'!$F$13 -> 0 | K12: ='08_도표4_분기실적_수정후'!$G$13 -> 0 | L12: ='08_도표4_분기실적_수정후'!$H$13 -> 0 | M12: ='08_도표4_분기실적_수정후'!$I$13 -> 0
A13: 기타 | B13: ='09_도표5_분기실적_수정전'!$B$14 -> 0.5 | C13: ='09_도표5_분기실적_수정전'!$C$14 -> 0.5 | D13: ='09_도표5_분기실적_수정전'!$D$14 -> 0.5 | E13: ='09_도표5_분기실적_수정전'!$E$14 -> 0.5 | F13: ='08_도표4_분기실적_수정후'!$B$14 -> 0.4 | G13: ='08_도표4_분기실적_수정후'!$C$14 -> 0.2 | H13: ='08_도표4_분기실적_수정후'!$D$14 -> 0.2 | I13: ='08_도표4_분기실적_수정후'!$E$14 -> 0 | J13: ='08_도표4_분기실적_수정후'!$F$14 -> 2 | K13: ='08_도표4_분기실적_수정후'!$G$14 -> 2.7 | L13: ='08_도표4_분기실적_수정후'!$H$14 -> 1.5 | M13: ='08_도표4_분기실적_수정후'!$I$14 -> 6.3
A15: ② 어플리케이션별 매출 비중
A16: 구분 | B16: 1Q24 | C16: 2Q24 | D16: 3Q24 | E16: 4Q24 | F16: 1Q25 | G16: 2Q25 | H16: 3Q25 | I16: 4Q25 | J16: 1Q26F | K16: 2Q26F | L16: 3Q26F | M16: 4Q26F
A17: 데이터센터 비중 | B17: =IFERROR(B$7/B$6,0) -> 0.5014245 | C17: =IFERROR(C$7/C$6,0) -> 0.39759036 | D17: =IFERROR(D$7/D$6,0) -> 0.44642857 | E17: =IFERROR(E$7/E$6,0) -> 0.48346056 | F17: =IFERROR(F$7/F$6,0) -> 0.53312303 | G17: =IFERROR(G$7/G$6,0) -> 0.64023211 | H17: =IFERROR(H$7/H$6,0) -> 0.68217054 | I17: =IFERROR(I$7/I$6,0) -> 0.75242047 | ... M17: =IFERROR(M$7/M$6,0) -> 0.71153846
A18: 스마트폰 비중 | B18: =IFERROR(B$8/B$6,0) -> 0.2991453 | C18: =IFERROR(C$8/C$6,0) -> 0.24096386 | D18: =IFERROR(D$8/D$6,0) -> 0.29761905 | E18: =IFERROR(E$8/E$6,0) -> 0.21882952 | F18: =IFERROR(F$8/F$6,0) -> 0.29968454 | G18: =IFERROR(G$8/G$6,0) -> 0.27079304 | H18: =IFERROR(H$8/H$6,0) -> 0.20930233 | I18: =IFERROR(I$8/I$6,0) -> 0.1659751 | ... M18: =IFERROR(M$8/M$6,0) -> 0.11312217
A19: PC/Laptop 비중 | B19: =IFERROR(B$9/B$6,0) -> 0.082621083 | C19: =IFERROR(C$9/C$6,0) -> 0.16064257 | D19: =IFERROR(D$9/D$6,0) -> 0.1984127 | E19: =IFERROR(E$9/E$6,0) -> 0.21119593 | F19: =IFERROR(F$9/F$6,0) -> 0.10094637 | G19: =IFERROR(G$9/G$6,0) -> 0.058027079 | H19: =IFERROR(H$9/H$6,0) -> 0.069767442 | I19: =IFERROR(I$9/I$6,0) -> 0.041493776 | ... M19: =IFERROR(M$9/M$6,0) -> 0.038461538
A20: 오토모티브 비중 | B20: =IFERROR(B$10/B$6,0) -> 0.051282051 | C20: =IFERROR(C$10/C$6,0) -> 0.040160643 | D20: =IFERROR(D$10/D$6,0) -> 0.029761905 | E20: =IFERROR(E$10/E$6,0) -> 0.073791349 | F20: =IFERROR(F$10/F$6,0) -> 0.031545741 | G20: =IFERROR(G$10/G$6,0) -> 0.013539652 | H20: =IFERROR(H$10/H$6,0) -> 0.023255814 | I20: =IFERROR(I$10/I$6,0) -> 0.026279391 | ... M20: =IFERROR(M$10/M$6,0) -> 0.054298643
A21: 웨어러블 비중 | B21: =IFERROR(B$11/B$6,0) -> 0.051282051 | C21: =IFERROR(C$11/C$6,0) -> 0.0562249 | D21: =IFERROR(D$11/D$6,0) -> 0.01984127 | E21: =IFERROR(E$11/E$6,0) -> 0 | F21: =IFERROR(F$11/F$6,0) -> 0.022082019 | G21: =IFERROR(G$11/G$6,0) -> 0.013539652 | H21: =IFERROR(H$11/H$6,0) -> 0.012403101 | I21: =IFERROR(I$11/I$6,0) -> 0.013831259 | ... M21: =IFERROR(M$11/M$6,0) -> 0.010180995
A22: LSI 비중 | B22: =IFERROR(B$12/B$6,0) -> 0 | C22: =IFERROR(C$12/C$6,0) -> 0.09437751 | D22: =IFERROR(D$12/D$6,0) -> 0 | E22: =IFERROR(E$12/E$6,0) -> 0 | F22: =IFERROR(F$12/F$6,0) -> 0 | G22: =IFERROR(G$12/G$6,0) -> 0 | H22: =IFERROR(H$12/H$6,0) -> 0 | I22: =IFERROR(I$12/I$6,0) -> 0 | ... M22: =IFERROR(M$12/M$6,0) -> 0
A23: 기타 비중 | B23: =IFERROR(B$13/B$6,0) -> 0.014245014 | C23: =IFERROR(C$13/C$6,0) -> 0.010040161 | D23: =IFERROR(D$13/D$6,0) -> 0.0099206349 | E23: =IFERROR(E$13/E$6,0) -> 0.012722646 | F23: =IFERROR(F$13/F$6,0) -> 0.012618297 | G23: =IFERROR(G$13/G$6,0) -> 0.003868472 | H23: =IFERROR(H$13/H$6,0) -> 0.0031007752 | I23: =IFERROR(I$13/I$6,0) -> 0 | ... M23: =IFERROR(M$13/M$6,0) -> 0.071266968
A24: 합계 검산 | B24: =B$17+B$18+B$19+B$20+B$21+B$22+B$23 -> 1 | C24: =C$17+C$18+C$19+C$20+C$21+C$22+C$23 -> 1 | D24: =D$17+D$18+D$19+D$20+D$21+D$22+D$23 -> 1.0019841 | E24: =E$17+E$18+E$19+E$20+E$21+E$22+E$23 -> 1 | F24: =F$17+F$18+F$19+F$20+F$21+F$22+F$23 -> 1 | G24: =G$17+G$18+G$19+G$20+G$21+G$22+G$23 -> 1 | H24: =H$17+H$18+H$19+H$20+H$21+H$22+H$23 -> 1 | I24: =I$17+I$18+I$19+I$20+I$21+I$22+I$23 -> 1 | ... M24: =M$17+M$18+M$19+M$20+M$21+M$22+M$23 -> 0.99886878
A26: 출처 (셀 단위 근거)
A27: 항목 | B27: 출처 | I27: URL / 접수번호
A28: 어플리케이션별 매출 1Q24~4Q26F | B28: 하나증권 4Q25 실적리뷰 도표 4·5 | I28: 본 워크북 10·11번 시트
A29: 어플리케이션별 매출 1Q21~4Q23 | B29: 미확보. 하나증권 자체 분류이며 공시 항목이 아니라 과거 하나증권 리포트를 직접 확인해야 함 (hanaw.com은 robots.txt로 자동 수집 차단) | I29: —
A30: 메모리/비메모리 · AI/비AI 분해 | B30: 원문에 없는 대체 분류이므로 D3_매출분해_대체분류 시트로 분리했습니다 | I30: 본 워크북 D3 시트

Sheet 13_도표9_연간실적추이
A1: 도표 9. ISC 연간 실적 추이 및 전망
A2: 원문 구간은 2019~2027F입니다. 2018~2022년은 언론 보도와 리서치 자료로 확보해 원문 구간을 모두 채웠습니다 (2018년은 보너스). 2023년 이후는 15_p5_손익계산서와 연결됩니다.
A4: 구분 | B4: 2018 | C4: 2019 | D4: 2020 | E4: 2021 | F4: 2022 | G4: 2023 | H4: 2024 | I4: 2025F | J4: 2026F | K4: 2027F | L4: 단위
A5: 매출액 | B5: 116.1 | C5: 87.7 | D5: 121.8 | E5: 144.7 | F5: 178.9 | G5: ='15_p5_손익계산서'!$B$5 -> 140.2 | H5: ='15_p5_손익계산서'!$C$5 -> 174.5 | I5: ='15_p5_손익계산서'!$D$5 -> 220.19 | J5: ='15_p5_손익계산서'!$E$5 -> 302.9 | K5: ='15_p5_손익계산서'!$F$5 -> 373.1 | L5: 십억원
A6: 영업이익 | B6: 12.7 | C6: 2 | D6: 18.1 | E6: 37.5 | F6: 55.9 | G6: ='15_p5_손익계산서'!$B$9 -> 10.7 | H6: ='15_p5_손익계산서'!$C$9 -> 44.8 | I6: ='15_p5_손익계산서'!$D$9 -> 60.05 | J6: ='15_p5_손익계산서'!$E$9 -> 93.7 | K6: ='15_p5_손익계산서'!$F$9 -> 125.1 | L6: 십억원
A7: 영업이익률 (OPM) | B7: =B$6/B$5 -> 0.10938846 | C7: =C$6/C$5 -> 0.022805017 | D7: =D$6/D$5 -> 0.14860427 | E7: =E$6/E$5 -> 0.25915688 | F7: =F$6/F$5 -> 0.31246506 | G7: =G$6/G$5 -> 0.076319544 | H7: =H$6/H$5 -> 0.25673352 | I7: =I$6/I$5 -> 0.27271902 | ... K7: =K$6/K$5 -> 0.33529885 | L7: %
A8: 매출액 YoY | C8: =C$5/B$5-1 -> -0.24461671 | D8: =D$5/C$5-1 -> 0.38882554 | E8: =E$5/D$5-1 -> 0.18801314 | F8: =F$5/E$5-1 -> 0.23635107 | G8: =G$5/F$5-1 -> -0.21632197 | H8: =H$5/G$5-1 -> 0.2446505 | I8: =I$5/H$5-1 -> 0.26183381 | J8: =J$5/I$5-1 -> 0.37563014 | K8: =K$5/J$5-1 -> 0.23175966 | L8: %
A9: 영업이익 YoY | C9: =C$6/B$6-1 -> -0.84251969 | D9: =D$6/C$6-1 -> 8.05 | E9: =E$6/D$6-1 -> 1.0718232 | F9: =F$6/E$6-1 -> 0.49066667 | G9: =G$6/F$6-1 -> -0.80858676 | H9: =H$6/G$6-1 -> 3.1869159 | I9: =I$6/H$6-1 -> 0.34040179 | J9: =J$6/I$6-1 -> 0.56036636 | K9: =K$6/J$6-1 -> 0.33511206 | L9: %
A10: 구분 | B10: 확정 (외부 확보) | C10: 확정 (외부 확보) | D10: 확정 (외부 확보) | E10: 확정 (외부 확보) | F10: 확정 (외부 확보) | G10: 확정 (리포트) | H10: 확정 (리포트) | I10: 하나증권 추정 | J10: 하나증권 추정 | K10: 하나증권 추정
A12: 정합성 체크
A13: 2022년 매출액 역산 검증 | B13: ='15_p5_손익계산서'!$B$5/(1+'15_p5_손익계산서'!$B$24) -> 178.89499 | C13: =$F$5 -> 178.9 | D13: ← 왼쪽은 하나증권 2023년 매출액증가율(-21.63%) 역산값, 오른쪽은 표 입력값(IM증권 178.9). 일치하면 정상
A14: 2022년 영업이익 역산 검증 | B14: ='15_p5_손익계산서'!$B$9/(1+'15_p5_손익계산서'!$B$27) -> 55.903866 | C14: =$F$6 -> 55.9 | D14: ← 하나증권 2023년 영업이익증가율(-80.86%) 역산값 vs 표 입력값 55.9 (미래에셋 리포트 표기 56)
A16: 출처 (셀 단위 근거)
A17: 항목 | B17: 출처 | I17: URL / 접수번호
A18: 2018년 매출·영업이익 | B18: 디일렉 2019.03 기사 (2018년 확정: 매출 1,161억 / 영업이익 127억) | I18: thelec.kr
A19: 2019~2021년 매출·영업이익 | B19: 디일렉 2023.02.02 기사 — 2019년 877억/20억, 2020년 1,218억/181억, 2021년 1,447억/375억. 미래에셋 리포트(122/18, 145/38)와 정합 | I19: thelec.kr
A20: 2022년 매출액 | B20: IM증권 2025.10.13 리포트 FY22 178.9십억원 (미래에셋 179, 하나증권 증가율 역산값과 모두 정합) | I20: imfnsec PDF
A21: 2022년 영업이익 | B21: 하나증권 2023년 영업이익증가율 -80.86% 역산 (55.9). 미래에셋 리포트 표기 56과 정합 | I21: 본 워크북 18번 시트
A22: 2023~2027F | B22: 하나증권 4Q25 실적리뷰 추정 재무제표 | I22: 본 워크북 18번 시트

Sheet 14_도표10_소켓_비소켓
A1: 도표 10. ISC 제품별 매출 추이 및 전망 (Socket / Non-socket)
A2: 원문 구간은 1Q19~1Q26입니다. IM증권 리포트에서 분기별 Non Socket 매출을 확보해 1Q23~4Q25 구간을 채웠습니다. 1Q19~4Q22 분기 구분은 미확보이며, 연간값은 FY22부터 있습니다.
A4: ① 분기 제품별 매출 (IM증권 2025.10.13)
A5: 구분 | B5: 1Q23 | C5: 2Q23 | D5: 3Q23 | E5: 4Q23 | F5: 1Q24 | G5: 2Q24 | H5: 3Q24 | I5: 4Q24 | J5: 1Q25 | K5: 2Q25 | L5: 3Q25E | M5: 4Q25E | N5: 단위
A6: 총매출 | B6: 46.4 | C6: 36 | D6: 32.9 | E6: 24.9 | F6: 35.1 | G6: 49.8 | H6: 50.4 | I6: 39.3 | J6: 31.7 | K6: 51.7 | L6: 69.5 | M6: 64 | N6: 십억원
A7: Non Socket (장비·소재 등) | B7: 2.3 | C7: 3.1 | D7: 3.7 | E7: 0.9 | F7: 0.4 | G7: 0.6 | H7: 0.5 | I7: 0.5 | J7: 0.4 | K7: 0.2 | L7: 10 | M7: 10 | N7: 십억원
A8: Socket (= 총매출 − Non Socket) | B8: =B$6-B$7 -> 44.1 | C8: =C$6-C$7 -> 32.9 | D8: =D$6-D$7 -> 29.2 | E8: =E$6-E$7 -> 24 | F8: =F$6-F$7 -> 34.7 | G8: =G$6-G$7 -> 49.2 | H8: =H$6-H$7 -> 49.9 | I8: =I$6-I$7 -> 38.8 | ... M8: =M$6-M$7 -> 54 | N8: 십억원
A9: Socket 비중 | B9: =B$8/B$6 -> 0.95043103 | C9: =C$8/C$6 -> 0.91388889 | D9: =D$8/D$6 -> 0.88753799 | E9: =E$8/E$6 -> 0.96385542 | F9: =F$8/F$6 -> 0.98860399 | G9: =G$8/G$6 -> 0.98795181 | H9: =H$8/H$6 -> 0.99007937 | I9: =I$8/I$6 -> 0.98727735 | ... M9: =M$8/M$6 -> 0.84375 | N9: %
A10: Non Socket 비중 | B10: =B$7/B$6 -> 0.049568966 | C10: =C$7/C$6 -> 0.086111111 | D10: =D$7/D$6 -> 0.11246201 | E10: =E$7/E$6 -> 0.036144578 | F10: =F$7/F$6 -> 0.011396011 | G10: =G$7/G$6 -> 0.012048193 | H10: =H$7/H$6 -> 0.0099206349 | I10: =I$7/I$6 -> 0.012722646 | ... M10: =M$7/M$6 -> 0.15625 | N10: %
A11: 검산: Memory + Non-Memory + Non Socket | B11: =10.1+34+2.3 -> 46.4 | C11: =6+26.9+3.1 -> 36 | D11: =6.6+22.6+3.7 -> 32.9 | E11: =5+19+0.9 -> 24.9 | F11: =5+29.7+0.4 -> 35.1 | G11: =7.5+41.7+0.6 -> 49.8 | H11: =8+41.9+0.5 -> 50.4 | I11: =5.1+33.7+0.5 -> 39.3 | J11: =5.9+25.4+0.4 -> 31.7 | K11: =5.8+45.7+0.2 -> 51.7 | L11: =4.5+55+10 -> 69.5 | M11: =5+49+10 -> 64 | N11: 십억원
A12: 주) 위 검산 행은 총매출 행과 전 분기에서 일치합니다. IM증권의 Memory·Non-Memory 합계가 곧 Socket 매출이라는 뜻이며, 이 구조가 도표 10의 Socket / Non-socket 구분과 같습니다.
A14: ② 연간 제품별 매출 (IM증권 2025.10.13)
A15: 구분 | B15: FY22 | C15: FY23 | D15: FY24 | E15: FY25E | F15: FY26E
A16: 총매출 | B16: 178.9 | C16: 140.2 | D16: 174.5 | E16: 216.8 | F16: 251.6
A17: Non Socket | B17: 0 | C17: 10 | D17: 1.9 | E17: 20.6 | F17: 24.7
A18: Socket (= 총매출 − Non Socket) | B18: =B$16-B$17 -> 178.9 | C18: =C$16-C$17 -> 130.2 | D18: =D$16-D$17 -> 172.6 | E18: =E$16-E$17 -> 196.2 | F18: =F$16-F$17 -> 226.9
A19: Non Socket 비중 | B19: =B$17/B$16 -> 0 | C19: =C$17/C$16 -> 0.071326676 | D19: =D$17/D$16 -> 0.010888252 | E19: =E$17/E$16 -> 0.09501845 | F19: =F$17/F$16 -> 0.098171701
A21: ③ 확보하지 못한 구간과 채우는 방법
A22: 항목 | B22: 내용
A23: 미확보 구간 | B23: 1Q19 ~ 4Q22 분기별 Socket / Non-socket 구분. IM증권 리포트는 1Q23부터만 제공하고 FY22 Non Socket을 0.0으로 표기하므로, 2022년 이전에는 비소켓 매출이 사실상 없었던 것으로 보입니다.
A24: 1차 자료 위치 | B24: DART 사업보고서·분기보고서의 「II. 사업의 내용 > 4. 매출 및 수주상황」에 품목별(제품별) 매출이 실려 있습니다. ISC의 DART 고유번호는 00572905입니다.
A25: 최근 보고서 접수번호 | B25: 사업보고서(2025.12) 20260318000018 · 분기보고서(2026.03) 20260515000092 · 연결영업(잠정)실적 20260427900108
A26: 자동 수집이 안 된 이유 | B26: dart.fss.or.kr의 robots.txt가 보고서 본문 경로(/dsaf001/main.do, /report/viewer.do)를 수집 금지로 두고 있어 본문을 직접 읽지 않았습니다. DART Open API 키를 발급받으면 프로그램으로 받을 수 있고, 보고서 PDF를 첨부해 주시면 바로 표에 채워 넣을 수 있습니다.
A27: 본문에 있는 단서 | B27: 하나증권 본문: 4Q25 AI 반도체용 테스트 소켓 매출 비중 75% (전분기 대비 +8%p). 25년 인수한 장비·소재 부문 4Q25 매출 약 100억원 → IM증권 4Q25E Non Socket 10.0십억원과 부합합니다.
A29: 출처 (셀 단위 근거)
A30: 항목 | B30: 출처 | I30: URL / 접수번호
A31: 분기·연간 Socket / Non Socket | B31: IM증권 2025.10.13 리포트 (총매출 = Memory + Non-Memory + Non Socket 검산 일치) | I31: imfnsec PDF
A32: 3Q25E·4Q25E는 추정치 | B32: 실제 3Q25 매출 64.5 / 4Q25 72.3십억원 (하나증권 도표 4). Non Socket 실제값은 미공표 | I32: 본 워크북 10번 시트

Sheet 15_p5_손익계산서
A1: 추정 재무제표 — 손익계산서
A2: 단위: 십억원 / 음영 = 전망치(F). 2025F~2027F 의 주요 손익 항목은 Forward EPS 시트를 반영합니다(초록 글씨). 2025년은 확정 공시치, 2026·2027년은 기본 입력 상태에서 리포트 원문과 동일합니다.
A4: 구분 | B4: 2023 | C4: 2024 | D4: 2025F | E4: 2026F | F4: 2027F | G4: 비고
A5: 매출액 | B5: 140.2 | C5: 174.5 | D5: ='Forward EPS'!$J$6 -> 220.19 | E5: ='Forward EPS'!$K$6 -> 302.9 | F5: ='Forward EPS'!$L$6 -> 373.1
A6: 매출원가 | B6: 85.1 | C6: 100.1 | D6: ='Forward EPS'!$J$16 -> 122.45 | E6: ='Forward EPS'!$K$16 -> 160.3 | F6: ='Forward EPS'!$L$16 -> 195.6
A7: 매출총이익 | B7: 55.1 | C7: 74.4 | D7: ='Forward EPS'!$J$17 -> 97.74 | E7: ='Forward EPS'!$K$17 -> 142.6 | F7: ='Forward EPS'!$L$17 -> 177.5
A8: 판관비 | B8: 44.4 | C8: 29.6 | D8: ='Forward EPS'!$J$19 -> 37.69 | E8: ='Forward EPS'!$K$19 -> 48.9 | F8: ='Forward EPS'!$L$19 -> 52.4
A9: 영업이익 | B9: 10.7 | C9: 44.8 | D9: ='Forward EPS'!$J$20 -> 60.05 | E9: ='Forward EPS'!$K$20 -> 93.7 | F9: ='Forward EPS'!$L$20 -> 125.1
A10: 금융손익 | B10: 5.2 | C10: 18.8 | D10: 6.8 | E10: 8.1 | F10: 8.8
A11: 종속/관계기업손익 | B11: 0 | C11: 0 | D11: 0 | E11: -1.3 | F11: 3.9
A12: 기타영업외손익 | B12: 1.6 | C12: 6 | D12: -0.3 | E12: 0 | F12: 0
A13: 세전이익 | B13: 17.6 | C13: 69.6 | D13: ='Forward EPS'!$J$22 -> 66.59 | E13: ='Forward EPS'!$K$22 -> 100.4 | F13: ='Forward EPS'!$L$22 -> 137.9
A14: 법인세 | B14: 4 | C14: 14.7 | D14: 10.3 | E14: 18.1 | F14: 24.8
A15: 계속사업이익 | B15: 13.6 | C15: 54.9 | D15: 56.3 | E15: 82.4 | F15: 113.1
A16: 중단사업이익 | B16: 0 | C16: 0 | D16: 0 | E16: 0 | F16: 0
A17: 당기순이익 | B17: 13.6 | C17: 54.9 | D17: 56.3 | E17: 82.4 | F17: 113.1
A18: 비지배주주지분 순이익 | B18: 0.4 | C18: 0.2 | D18: 0.4 | E18: 0.7 | F18: 1
A19: 지배주주순이익 | B19: 13.2 | C19: 54.7 | D19: ='Forward EPS'!$J$23 -> 56.12 | E19: ='Forward EPS'!$K$23 -> 81.6 | F19: ='Forward EPS'!$L$23 -> 112
A20: 지배주주지분포괄이익 | B20: 15.5 | C20: 53.6 | D20: 55 | E20: 81.6 | F20: 112
A21: NOPAT | B21: 8.3 | C21: 35.3 | D21: 50.8 | E21: 76.8 | F21: 102.6
A22: EBITDA | B22: 19.4 | C22: 54.6 | D22: 70 | E22: 111.1 | F22: 143.4
A23: 성장성 (%)
A24: 매출액증가율 | B24: -0.2163 | C24: 0.2447 | D24: 0.2619 | E24: 0.3756 | F24: 0.2318
A25: NOPAT증가율 | B25: -0.7899 | C25: 3.253 | D25: 0.4391 | E25: 0.5118 | F25: 0.3359
A26: EBITDA증가율 | B26: -0.7213 | C26: 1.8144 | D26: 0.2821 | E26: 0.5871 | F26: 0.2907
A27: 영업이익증가율 | B27: -0.8086 | C27: 3.1869 | D27: 0.3415 | E27: 0.5591 | F27: 0.3351
A28: (지배주주)순익증가율 | B28: -0.7 | C28: 3.1439 | D28: 0.0219 | E28: 0.4597 | F28: 0.3725
A29: EPS증가율 | B29: -0.7156 | C29: 2.5819 | D29: 0.0229 | E29: 0.4594 | F29: 0.3727
A30: 수익성 (%)
A31: 매출총이익률 | B31: 0.393 | C31: 0.4264 | D31: 0.445 | E31: 0.4708 | F31: 0.4757
A32: EBITDA이익률 | B32: 0.1384 | C32: 0.3129 | D32: 0.3179 | E32: 0.3668 | F32: 0.3843
A33: 영업이익률 | B33: 0.0763 | C33: 0.2567 | D33: 0.2729 | E33: 0.3093 | F33: 0.3353
A34: 계속사업이익률 | B34: 0.097 | C34: 0.3146 | D34: 0.2557 | E34: 0.272 | F34: 0.3031
A35: 자료: 하나증권
A37: 정합성 체크 (원문 수치를 수식으로 재계산)
A38: 체크 항목 | B38: 2023 | C38: 2024 | D38: 2025F | E38: 2026F | F38: 2027F | G38: 비고
A39: 매출총이익 = 매출액 − 매출원가 | B39: =B$5-B$6 -> 55.1 | C39: =C$5-C$6 -> 74.4 | D39: =D$5-D$6 -> 97.74 | E39: =E$5-E$6 -> 142.6 | F39: =F$5-F$6 -> 177.5 | G39: 원문 매출총이익과 대조
A40: 영업이익 = 매출총이익 − 판관비 | B40: =B$7-B$8 -> 10.7 | C40: =C$7-C$8 -> 44.8 | D40: =D$7-D$8 -> 60.05 | E40: =E$7-E$8 -> 93.7 | F40: =F$7-F$8 -> 125.1 | G40: 원문 영업이익과 대조
A41: 세전이익 = 영업이익 + 영업외손익 합 | B41: =B$9+B$10+B$11+B$12 -> 17.5 | C41: =C$9+C$10+C$11+C$12 -> 69.6 | D41: =D$9+D$10+D$11+D$12 -> 66.55 | E41: =E$9+E$10+E$11+E$12 -> 100.5 | F41: =F$9+F$10+F$11+F$12 -> 137.8 | G41: 원문 세전이익과 대조 (반올림 차이 존재)
A42: 계속사업이익 = 세전이익 − 법인세 | B42: =B$13-B$14 -> 13.6 | C42: =C$13-C$14 -> 54.9 | D42: =D$13-D$14 -> 56.29 | E42: =E$13-E$14 -> 82.3 | F42: =F$13-F$14 -> 113.1 | G42: 원문 계속사업이익과 대조
A43: 당기순이익 = 계속 + 중단사업이익 | B43: =B$15+B$16 -> 13.6 | C43: =C$15+C$16 -> 54.9 | D43: =D$15+D$16 -> 56.3 | E43: =E$15+E$16 -> 82.4 | F43: =F$15+F$16 -> 113.1 | G43: 원문 당기순이익과 대조
A44: 지배주주순이익 = 당기순 − 비지배 | B44: =B$17-B$18 -> 13.2 | C44: =C$17-C$18 -> 54.7 | D44: =D$17-D$18 -> 55.9 | E44: =E$17-E$18 -> 81.7 | F44: =F$17-F$18 -> 112.1 | G44: 원문 지배주주순이익과 대조
A45: 영업이익률 재계산 | B45: =B$9/B$5 -> 0.076319544 | C45: =C$9/C$5 -> 0.25673352 | D45: =D$9/D$5 -> 0.27271902 | E45: =E$9/E$5 -> 0.30934302 | F45: =F$9/F$5 -> 0.33529885 | G45: 원문 영업이익률과 대조
A46: 매출총이익률 재계산 | B46: =B$7/B$5 -> 0.39300999 | C46: =C$7/C$5 -> 0.42636103 | D46: =D$7/D$5 -> 0.44388937 | E46: =E$7/E$5 -> 0.47078244 | F46: =F$7/F$5 -> 0.47574377 | G46: 원문 매출총이익률과 대조
A47: EBITDA이익률 재계산 | B47: =B$22/B$5 -> 0.13837375 | C47: =C$22/C$5 -> 0.31289398 | D47: =D$22/D$5 -> 0.31790726 | E47: =E$22/E$5 -> 0.36678772 | F47: =F$22/F$5 -> 0.38434736 | G47: 원문 EBITDA이익률과 대조
A48: 유효법인세율 | B48: =B$14/B$13 -> 0.22727273 | C48: =C$14/C$13 -> 0.2112069 | D48: =D$14/D$13 -> 0.15467788 | E48: =E$14/E$13 -> 0.18027888 | F48: =F$14/F$13 -> 0.17984046 | G48: 법인세 ÷ 세전이익
A49: 매출액증가율 재계산 | B49: n/a | C49: =C$5/B$5-1 -> 0.2446505 | D49: =D$5/C$5-1 -> 0.26183381 | E49: =E$5/D$5-1 -> 0.37563014 | F49: =F$5/E$5-1 -> 0.23175966 | G49: 2023년은 전기 미제공
A50: 영업이익증가율 재계산 | B50: n/a | C50: =C$9/B$9-1 -> 3.1869159 | D50: =D$9/C$9-1 -> 0.34040179 | E50: =E$9/D$9-1 -> 0.56036636 | F50: =F$9/E$9-1 -> 0.33511206 | G50: 2023년은 전기 미제공
A52: 주) 원문은 소수 첫째자리(또는 둘째자리)까지 반올림 표기되어 있어, 재계산값과 0.1 내외 차이가 날 수 있습니다. 이는 보고서 표기 방식에 따른 것이며 오기입이 아닙니다.

Sheet 16_p5_대차대조표
A1: 추정 재무제표 — 대차대조표
A2: 단위: 십억원 / 음영 = 전망치(F)
A4: 구분 | B4: 2023 | C4: 2024 | D4: 2025F | E4: 2026F | F4: 2027F | G4: 비고
A5: 유동자산 | B5: 361.8 | C5: 405.1 | D5: 444.3 | E5: 438.8 | F5: 541
A6: 금융자산 | B6: 320.5 | C6: 346.9 | D6: 351.7 | E6: 327.4 | F6: 403.9
A7: 현금성자산 | B7: 268 | C7: 39.9 | D7: 54.5 | E7: 59.7 | F7: 74.5
A8: 매출채권 | B8: 21 | C8: 32.9 | D8: 60.6 | E8: 74 | F8: 91.2
A9: 재고자산 | B9: 15.4 | C9: 15.4 | D9: 13.9 | E9: 15.3 | F9: 18.8
A10: 기타유동자산 | B10: 4.9 | C10: 9.9 | D10: 18.1 | E10: 22.1 | F10: 27.1
A11: 비유동자산 | B11: 180 | C11: 177.8 | D11: 171.9 | E11: 254.6 | F11: 262.5
A12: 투자자산 | B12: 9.9 | C12: 8.6 | D12: 0.6 | E12: 0.7 | F12: 0.9
A13: 금융자산 | B13: 9.9 | C13: 8.6 | D13: 0.6 | E13: 0.7 | F13: 0.9 | G13: 원문 표기: 금융자산 (비유동자산 하위 항목)
A14: 유형자산 | B14: 92.8 | C14: 92.2 | D14: 96.1 | E14: 179.9 | F14: 187.8
A15: 무형자산 | B15: 21.4 | C15: 17.7 | D15: 19.8 | E15: 18.7 | F15: 18.5
A16: 기타비유동자산 | B16: 55.9 | C16: 59.3 | D16: 55.4 | E16: 55.3 | F16: 55.3
A17: 자산총계 | B17: 541.8 | C17: 582.9 | D17: 616.2 | E17: 693.4 | F17: 803.6
A18: 부채
A19: 유동부채 | B19: 58.3 | C19: 52.3 | D19: 66.6 | E19: 75 | F19: 85.8
A20: 금융부채 | B20: 40.1 | C20: 20.7 | D20: 21.2 | E20: 21.5 | F20: 21.9 | G20: 원문 표기: 금융부채 (유동부채 하위 항목)
A21: 매입채무 | B21: 4.8 | C21: 7.6 | D21: 13.9 | E21: 17 | F21: 21
A22: 기타유동부채 | B22: 13.4 | C22: 24 | D22: 31.5 | E22: 36.5 | F22: 42.9
A23: 비유동부채 | B23: 10.1 | C23: 7.5 | D23: 13.7 | E23: 16.7 | F23: 20.4
A24: 금융부채 | B24: 3.5 | C24: 0.3 | D24: 0.5 | E24: 0.5 | F24: 0.5 | G24: 원문 표기: 금융부채 (비유동부채 하위 항목)
A25: 기타비유동부채 | B25: 6.6 | C25: 7.2 | D25: 13.2 | E25: 16.2 | F25: 19.9
A26: 부채총계 | B26: 68.4 | C26: 59.7 | D26: 80.3 | E26: 91.7 | F26: 106.2
A27: 자본
A28: 지배주주지분 | B28: 473.4 | C28: 522.7 | D28: 535.2 | E28: 600.2 | F28: 694.8
A29: 자본금 | B29: 10.6 | C29: 10.6 | D29: 10.6 | E29: 10.6 | F29: 10.6
A30: 자본잉여금 | B30: 315.7 | C30: 315.7 | D30: 289.7 | E30: 289.7 | F30: 289.7
A31: 자본조정 | B31: -27 | C31: -27.1 | D31: -27.1 | E31: -27.1 | F31: -27.1
A32: 기타포괄이익누계액 | B32: 0.7 | C32: 1.5 | D32: 1.2 | E32: 1.2 | F32: 1.2
A33: 이익잉여금 | B33: 173.3 | C33: 222 | D33: 260.7 | E33: 325.8 | F33: 420.4
A34: 비지배주주지분 | B34: 0.1 | C34: 0.4 | D34: 0.8 | E34: 1.6 | F34: 2.6
A35: 자본총계 | B35: 473.5 | C35: 523.1 | D35: 536 | E35: 601.8 | F35: 697.4
A36: 순금융부채 | B36: -276.9 | C36: -325.9 | D36: -330 | E36: -305.4 | F36: -381.5 | G36: 순현금 상태 (음수 = 순현금)
A37: 자료: 하나증권
A39: 정합성 체크 (원문 수치를 수식으로 재계산)
A40: 체크 항목 | B40: 2023 | C40: 2024 | D40: 2025F | E40: 2026F | F40: 2027F | G40: 비고
A41: 자산총계 = 유동 + 비유동자산 | B41: =B$5+B$11 -> 541.8 | C41: =C$5+C$11 -> 582.9 | D41: =D$5+D$11 -> 616.2 | E41: =E$5+E$11 -> 693.4 | F41: =F$5+F$11 -> 803.5 | G41: 원문 자산총계와 대조
A42: 부채총계 = 유동 + 비유동부채 | B42: =B$19+B$23 -> 68.4 | C42: =C$19+C$23 -> 59.8 | D42: =D$19+D$23 -> 80.3 | E42: =E$19+E$23 -> 91.7 | F42: =F$19+F$23 -> 106.2 | G42: 원문 부채총계와 대조
A43: 자본총계 = 지배 + 비지배주주지분 | B43: =B$28+B$34 -> 473.5 | C43: =C$28+C$34 -> 523.1 | D43: =D$28+D$34 -> 536 | E43: =E$28+E$34 -> 601.8 | F43: =F$28+F$34 -> 697.4 | G43: 원문 자본총계와 대조
A44: 자산총계 − (부채 + 자본) | B44: =B$17-B$26-B$35 -> -0.1 | C44: =C$17-C$26-C$35 -> 0.1 | D44: =D$17-D$26-D$35 -> -0.1 | E44: =E$17-E$26-E$35 -> -0.1 | F44: =F$17-F$26-F$35 -> 0 | G44: 0에 가까우면 대차 일치
A45: 순금융부채 재계산 | B45: =B$20+B$24-B$6 -> -276.9 | C45: =C$20+C$24-C$6 -> -325.9 | D45: =D$20+D$24-D$6 -> -330 | E45: =E$20+E$24-E$6 -> -305.4 | F45: =F$20+F$24-F$6 -> -381.5 | G45: 유동+비유동 금융부채 − 유동 금융자산 (원문 순금융부채와 일치)
A46: 부채비율 | B46: =B$26/B$35 -> 0.14445618 | C46: =C$26/C$35 -> 0.11412732 | D46: =D$26/D$35 -> 0.14981343 | E46: =E$26/E$35 -> 0.1523762 | F46: =F$26/F$35 -> 0.1522799 | G46: 17_p5_투자지표 부채비율과 대조
A47: 유동비율 | B47: =B$5/B$19 -> 6.2058319 | C47: =C$5/C$19 -> 7.7456979 | D47: =D$5/D$19 -> 6.6711712 | E47: =E$5/E$19 -> 5.8506667 | F47: =F$5/F$19 -> 6.3053613 | G47: 유동자산 ÷ 유동부채
A48: 매출채권 회전율 (회) | B48: ='15_p5_손익계산서'!B$5/B$8 -> 6.6761905 | C48: ='15_p5_손익계산서'!C$5/C$8 -> 5.3039514 | D48: ='15_p5_손익계산서'!D$5/D$8 -> 3.6334983 | E48: ='15_p5_손익계산서'!E$5/E$8 -> 4.0932432 | F48: ='15_p5_손익계산서'!F$5/F$8 -> 4.0910088 | G48: 매출액 ÷ 매출채권 (15_p5_손익계산서 참조)
A49: 재고자산 회전율 (회) | B49: ='15_p5_손익계산서'!B$6/B$9 -> 5.525974 | C49: ='15_p5_손익계산서'!C$6/C$9 -> 6.5 | D49: ='15_p5_손익계산서'!D$6/D$9 -> 8.8093525 | E49: ='15_p5_손익계산서'!E$6/E$9 -> 10.477124 | F49: ='15_p5_손익계산서'!F$6/F$9 -> 10.404255 | G49: 매출원가 ÷ 재고자산 (15_p5_손익계산서 참조)
A51: 주) 원문은 소수 첫째자리(또는 둘째자리)까지 반올림 표기되어 있어, 재계산값과 0.1 내외 차이가 날 수 있습니다. 이는 보고서 표기 방식에 따른 것이며 오기입이 아닙니다.

Sheet 17_p5_투자지표
A1: 추정 재무제표 — 투자지표
A2: 단위: 원, 배, % / 음영 = 전망치(F)
A4: 구분 | B4: 2023 | C4: 2024 | D4: 2025F | E4: 2026F | F4: 2027F | G4: 비고
A5: 주당지표 (원)
A6: EPS | B6: 720 | C6: 2579 | D6: 2638 | E6: 3850 | F6: 5285
A7: BPS | B7: 23173 | C7: 25507 | D7: 26091 | E7: 29159 | F7: 33623
A8: CFPS | B8: 2118 | C8: 2920 | D8: 3313 | E8: 5179 | F8: 6949
A9: EBITDAPS | B9: 1060 | C9: 2578 | D9: 3303 | E9: 5242 | F9: 6764
A10: SPS | B10: 7652 | C10: 8231 | D10: 10387 | E10: 14291 | F10: 17602
A11: DPS | B11: 200 | C11: 810 | D11: 810 | E11: 850 | F11: 900
A12: 주가지표 (배)
A13: PER | B13: 111.53 | C13: 27.96 | D13: 42.12 | E13: 37.17 | F13: 27.08
A14: PBR | B14: 3.47 | C14: 2.83 | D14: 4.26 | E14: 4.91 | F14: 4.26
A15: PCFR | B15: 37.91 | C15: 24.69 | D15: 33.53 | E15: 27.63 | F15: 20.59
A16: EV/EBITDA | B16: 73.34 | C16: 22.01 | D16: 28.94 | E16: 24.56 | F16: 18.51
A17: PSR | B17: 10.49 | C17: 8.76 | D17: 10.7 | E17: 10.01 | F17: 8.13
A18: 재무비율 (%)
A19: ROE | B19: 0.0356 | C19: 0.1098 | D19: 0.1057 | E19: 0.1438 | F19: 0.173
A20: ROA | B20: 0.0293 | C20: 0.0972 | D20: 0.0932 | E20: 0.1246 | F20: 0.1497
A21: ROIC | B21: 0.0526 | C21: 0.275 | D21: 0.3988 | E21: 0.4543 | F21: 0.4744
A22: 부채비율 | B22: 0.1444 | C22: 0.1142 | D22: 0.1498 | E22: 0.1523 | F22: 0.1522
A23: 순부채비율 | B23: -0.5849 | C23: -0.623 | D23: -0.6157 | E23: -0.5075 | F23: -0.547
A24: 이자보상배율 | B24: 5.05 | C24: 28.22 | D24: 57.82 | E24: 90.02 | F24: 118.56 | G24: 단위: 배
A25: 자료: 하나증권
A27: 정합성 체크 (원문 수치를 수식으로 재계산)
A28: 체크 항목 | B28: 2023 | C28: 2024 | D28: 2025F | E28: 2026F | F28: 2027F | G28: 비고
A29: SPS 재계산 = 매출액 / 주식수 | B29: ='15_p5_손익계산서'!B$5*1000000/'01_p1_투자의견_KeyData'!$C$23 -> 6614.1123 | C29: ='15_p5_손익계산서'!C$5*1000000/'01_p1_투자의견_KeyData'!$C$23 -> 8232.2582 | D29: ='15_p5_손익계산서'!D$5*1000000/'01_p1_투자의견_KeyData'!$C$23 -> 10387.742 | E29: ='15_p5_손익계산서'!E$5*1000000/'01_p1_투자의견_KeyData'!$C$23 -> 14289.691 | F29: ='15_p5_손익계산서'!F$5*1000000/'01_p1_투자의견_KeyData'!$C$23 -> 17601.464 | G29: 현재 발행주식수 21,197.1천주 기준. 2023년은 유상증자 이전이라 원문과 차이 발생
A30: EPS 재계산 = 지배주주순이익 / 주식수 | B30: ='15_p5_손익계산서'!B$19*1000000/'01_p1_투자의견_KeyData'!$C$23 -> 622.72669 | C30: ='15_p5_손익계산서'!C$19*1000000/'01_p1_투자의견_KeyData'!$C$23 -> 2580.5417 | D30: ='15_p5_손익계산서'!D$19*1000000/'01_p1_투자의견_KeyData'!$C$23 -> 2647.532 | E30: ='15_p5_손익계산서'!E$19*1000000/'01_p1_투자의견_KeyData'!$C$23 -> 3849.5832 | F30: ='15_p5_손익계산서'!F$19*1000000/'01_p1_투자의견_KeyData'!$C$23 -> 5283.7416 | G30: 원문 EPS와 대조. 2025F 이후는 거의 일치, 2023~24년은 주식수 변동으로 차이
A31: EBITDAPS 재계산 | B31: ='15_p5_손익계산서'!B$22*1000000/'01_p1_투자의견_KeyData'!$C$23 -> 915.21953 | C31: ='15_p5_손익계산서'!C$22*1000000/'01_p1_투자의견_KeyData'!$C$23 -> 2575.8241 | D31: ='15_p5_손익계산서'!D$22*1000000/'01_p1_투자의견_KeyData'!$C$23 -> 3302.3385 | E31: ='15_p5_손익계산서'!E$22*1000000/'01_p1_투자의견_KeyData'!$C$23 -> 5241.283 | F31: ='15_p5_손익계산서'!F$22*1000000/'01_p1_투자의견_KeyData'!$C$23 -> 6765.0764 | G31: 원문 EBITDAPS와 대조
A32: ROE 재계산 = 지배주주순이익 / 지배주주지분 | B32: ='15_p5_손익계산서'!B$19/'16_p5_대차대조표'!B$28 -> 0.027883397 | C32: ='15_p5_손익계산서'!C$19/'16_p5_대차대조표'!C$28 -> 0.10464894 | D32: ='15_p5_손익계산서'!D$19/'16_p5_대차대조표'!D$28 -> 0.104858 | E32: ='15_p5_손익계산서'!E$19/'16_p5_대차대조표'!E$28 -> 0.13595468 | F32: ='15_p5_손익계산서'!F$19/'16_p5_대차대조표'!F$28 -> 0.16119747 | G32: 기말 자본 기준 (원문은 평균 자본 기준일 수 있음)
A33: ROA 재계산 = 당기순이익 / 자산총계 | B33: ='15_p5_손익계산서'!B$17/'16_p5_대차대조표'!B$17 -> 0.025101513 | C33: ='15_p5_손익계산서'!C$17/'16_p5_대차대조표'!C$17 -> 0.094184251 | D33: ='15_p5_손익계산서'!D$17/'16_p5_대차대조표'!D$17 -> 0.091366439 | E33: ='15_p5_손익계산서'!E$17/'16_p5_대차대조표'!E$17 -> 0.11883473 | F33: ='15_p5_손익계산서'!F$17/'16_p5_대차대조표'!F$17 -> 0.14074166 | G33: 기말 자산 기준
A34: 부채비율 재계산 | B34: ='16_p5_대차대조표'!B$26/'16_p5_대차대조표'!B$35 -> 0.14445618 | C34: ='16_p5_대차대조표'!C$26/'16_p5_대차대조표'!C$35 -> 0.11412732 | D34: ='16_p5_대차대조표'!D$26/'16_p5_대차대조표'!D$35 -> 0.14981343 | E34: ='16_p5_대차대조표'!E$26/'16_p5_대차대조표'!E$35 -> 0.1523762 | F34: ='16_p5_대차대조표'!F$26/'16_p5_대차대조표'!F$35 -> 0.1522799 | G34: 원문 부채비율과 대조
A35: PER × EPS = 기준주가 | B35: =B$13*B$6 -> 80301.6 | C35: =C$13*C$6 -> 72108.84 | D35: =D$13*D$6 -> 111112.56 | E35: =E$13*E$6 -> 143104.5 | F35: =F$13*F$6 -> 143117.8 | G35: 각 연도 PER 산정 기준주가 역산
A36: PBR × BPS = 기준주가 | B36: =B$14*B$7 -> 80410.31 | C36: =C$14*C$7 -> 72184.81 | D36: =D$14*D$7 -> 111147.66 | E36: =E$14*E$7 -> 143170.69 | F36: =F$14*F$7 -> 143233.98 | G36: 각 연도 PBR 산정 기준주가 역산
A37: 배당성향 = DPS / EPS | B37: =B$11/B$6 -> 0.27777778 | C37: =C$11/C$6 -> 0.31407522 | D37: =D$11/D$6 -> 0.3070508 | E37: =E$11/E$6 -> 0.22077922 | F37: =F$11/F$6 -> 0.17029328 | G37: 주당배당금 ÷ 주당순이익
A39: 주) 원문은 소수 첫째자리(또는 둘째자리)까지 반올림 표기되어 있어, 재계산값과 0.1 내외 차이가 날 수 있습니다. 이는 보고서 표기 방식에 따른 것이며 오기입이 아닙니다.
A41: 주) 「PER × EPS = 기준주가」 결과가 2025F~2027F에서 143,100원 부근으로 수렴합니다. 즉 전망 연도의 PER·PBR은 현재주가(143,100원, 2026.02.04 종가) 기준으로 산정된 값이며, 2023~2024년은 각 연도의 실제 주가 기준입니다.
A42: 주) ROE·ROA 재계산값이 원문보다 낮게 나오는 것은 원문이 기초·기말 평균 자본(자산)을 쓰는 반면 여기서는 기말 잔액을 썼기 때문입니다. 계산 방식 차이이며 원문 오류가 아닙니다.
A43: 주) 주당지표 재계산은 현재 발행주식수 21,197.1천주를 고정 적용했습니다. 2025F 이후는 원문과 거의 일치하지만, 2023년은 대규모 유상증자(재무활동 자본증가 199.8십억원) 이전이라 당시 가중평균 주식수가 적어 차이가 큽니다.

Sheet 18_p5_현금흐름표
A1: 추정 재무제표 — 현금흐름표
A2: 단위: 십억원 / 음영 = 전망치(F)
A4: 구분 | B4: 2023 | C4: 2024 | D4: 2025F | E4: 2026F | F4: 2027F | G4: 비고
A5: 영업활동 현금흐름 | B5: 22.4 | C5: 50.7 | D5: 64.9 | E5: 102.4 | F5: 132.9
A6: 당기순이익 | B6: 13.6 | C6: 54.9 | D6: 56.3 | E6: 82.4 | F6: 113.1
A7: 조정 | B7: 8.7 | C7: 6.5 | D7: 11.6 | E7: 17.4 | F7: 18.2
A8: 감가상각비 | B8: 8.7 | C8: 9.9 | D8: 9.9 | E8: 17.4 | F8: 18.2
A9: 외환거래손익 | B9: 0.8 | C9: -5.6 | D9: 0.8 | E9: 0 | F9: 0
A10: 지분법손익 | B10: 0 | C10: 0 | D10: 0 | E10: 0 | F10: 0 | G10: 원문 2025F: (0.0)
A11: 기타 | B11: -0.8 | C11: 2.2 | D11: 0.9 | E11: 0 | F11: 0 | G11: 원문 표기: 기타 (조정 하위 항목)
A12: 영업활동자산부채변동 | B12: 0.1 | C12: -10.7 | D12: -3 | E12: 2.6 | F12: 1.6
A13: 투자활동 현금흐름 | B13: -1.6 | C13: -251.9 | D13: -21.5 | E13: -70.6 | F13: -87.8
A14: 투자자산감소(증가) | B14: 3.9 | C14: 1.3 | D14: 8 | E14: -0.1 | F14: -0.2
A15: 자본증가(감소) | B15: -14.5 | C15: -11.4 | D15: -13.5 | E15: -100 | F15: -25 | G15: 원문 표기: 자본증가(감소) — 투자활동 하위 (유형자산 투자)
A16: 기타 | B16: 9 | C16: -241.8 | D16: -16 | E16: 29.5 | F16: -62.6 | G16: 원문 표기: 기타 (투자활동 하위 항목)
A17: 재무활동 현금흐름 | B17: 194.3 | C17: -26.8 | D17: -16.2 | E17: -16.3 | F17: -17
A18: 금융부채증가(감소) | B18: 4.5 | C18: -22.6 | D18: 0.8 | E18: 0.3 | F18: 0.4
A19: 자본증가(감소) | B19: 199.8 | C19: 0 | D19: -26 | E19: 0 | F19: 0 | G19: 원문 표기: 자본증가(감소) — 재무활동 하위
A20: 기타재무활동 | B20: 0 | C20: -0.1 | D20: 25.6 | E20: 0 | F20: 0
A21: 배당지급 | B21: -10 | C21: -4.1 | D21: -16.6 | E21: -16.6 | F21: -17.4
A22: 현금의 증감 | B22: 215 | C22: -228 | D22: 12.8 | E22: 5.2 | F22: 14.9
A23: Unlevered CFO | B23: 38.8 | C23: 61.9 | D23: 70.2 | E23: 109.8 | F23: 147.3
A24: Free Cash Flow | B24: 7.9 | C24: 39.3 | D24: 51.1 | E24: 2.4 | F24: 107.9
A25: 자료: 하나증권
A27: 정합성 체크 (원문 수치를 수식으로 재계산)
A28: 체크 항목 | B28: 2023 | C28: 2024 | D28: 2025F | E28: 2026F | F28: 2027F | G28: 비고
A29: 영업활동 = 순이익 + 조정 + 자산부채변동 | B29: =B$6+B$7+B$12 -> 22.4 | C29: =C$6+C$7+C$12 -> 50.7 | D29: =D$6+D$7+D$12 -> 64.9 | E29: =E$6+E$7+E$12 -> 102.4 | F29: =F$6+F$7+F$12 -> 132.9 | G29: 원문 영업활동 현금흐름과 대조
A30: 현금의 증감 = 영업 + 투자 + 재무 | B30: =B$5+B$13+B$17 -> 215.1 | C30: =C$5+C$13+C$17 -> -228 | D30: =D$5+D$13+D$17 -> 27.2 | E30: =E$5+E$13+E$17 -> 15.5 | F30: =F$5+F$13+F$17 -> 28.1 | G30: 원문 현금의 증감과 대조 (환율효과 등 제외)
A31: FCF 재계산 = 영업활동 + CAPEX | B31: =B$5+B$15 -> 7.9 | C31: =C$5+C$15 -> 39.3 | D31: =D$5+D$15 -> 51.4 | E31: =E$5+E$15 -> 2.4 | F31: =F$5+F$15 -> 107.9 | G31: 원문 Free Cash Flow와 대조
A32: CAPEX / 매출액 | B32: =-B$15/'15_p5_손익계산서'!B$5 -> 0.10342368 | C32: =-C$15/'15_p5_손익계산서'!C$5 -> 0.065329513 | D32: =-D$15/'15_p5_손익계산서'!D$5 -> 0.061310686 | E32: =-E$15/'15_p5_손익계산서'!E$5 -> 0.33014196 | F32: =-F$15/'15_p5_손익계산서'!F$5 -> 0.067006165 | G32: 설비투자 강도 (2026F 증설 반영 확인)
A33: 영업활동 현금흐름 / 매출액 | B33: =B$5/'15_p5_손익계산서'!B$5 -> 0.15977175 | C33: =C$5/'15_p5_손익계산서'!C$5 -> 0.29054441 | D33: =D$5/'15_p5_손익계산서'!D$5 -> 0.29474545 | E33: =E$5/'15_p5_손익계산서'!E$5 -> 0.33806537 | F33: =F$5/'15_p5_손익계산서'!F$5 -> 0.35620477 | G33: 현금창출력
A34: 배당지급 / 지배주주순이익 | B34: =-B$21/'15_p5_손익계산서'!B$19 -> 0.75757576 | C34: =-C$21/'15_p5_손익계산서'!C$19 -> 0.074954296 | D34: =-D$21/'15_p5_손익계산서'!D$19 -> 0.29579473 | E34: =-E$21/'15_p5_손익계산서'!E$19 -> 0.20343137 | F34: =-F$21/'15_p5_손익계산서'!F$19 -> 0.15535714 | G34: 현금 배당성향
A36: 주) 원문은 소수 첫째자리(또는 둘째자리)까지 반올림 표기되어 있어, 재계산값과 0.1 내외 차이가 날 수 있습니다. 이는 보고서 표기 방식에 따른 것이며 오기입이 아닙니다.
A38: 주) 「현금의 증감 = 영업 + 투자 + 재무」 검산은 2023·2024년 실적에서는 원문과 일치하지만, 2025F~2027F에서는 원문 수치보다 10~14십억원 크게 나옵니다. 세 활동의 합계와 원문 「현금의 증감」이 보고서 안에서 맞지 않는 구간이며, 리스부채 상환·환율효과 등 표에 별도로 표시되지 않은 항목이 있는 것으로 보입니다. 전사 오류가 아니라 원문 표 자체의 특성이므로 참고해서 보시면 됩니다.
A39: 주) CAPEX는 투자활동 하위의 「자본증가(감소)」 항목을 설비투자로 간주해 계산했습니다. 2026F CAPEX/매출액이 33%로 급증하는데, 이는 본문의 베트남 신규 생산시설 등 2단계 대규모 증설 계획과 일치합니다.

Sheet 19_p6_투자의견변동_괴리율
A1: 투자의견 변동 내역 및 목표주가 괴리율
A2: 하나증권 리포트 p.6 게재 (ISC)
A4: 날짜 | B4: 투자의견 | C4: 목표주가 (원) | D4: 괴리율 — 평균 | E4: 괴리율 — 최고/최저 | F4: 비고
A5: 26.2.5 | B5: BUY | C5: 180000 | D5: - | E5: - | F5: 금번 리포트 (상향)
A6: 25.11.25 | B6: BUY | C6: 130000 | D6: -0.1441 | E6: 0.1592
A7: 25.5.21 | B7: BUY | C7: 76000 | D7: -0.1296 | E7: 0.1618
A8: 24.10.11 | B8: Not Rated | C8: - | D8: - | E8: - | F8: 커버리지 개시 이전
A10: 목표주가 상향 폭 (계산)
A11: 구분 | B11: 값 | F11: 비고
A12: 직전 목표주가 | B12: =$C$6 -> 130000 | F12: 25.11.25 제시
A13: 금번 목표주가 | B13: =$C$5 -> 180000 | F13: 26.2.5 제시
A14: 상향 폭 | B14: =$B$13/$B$12-1 -> 0.38461538 | F14: 130,000원 → 180,000원
A15: 05_도표1_Valuation 목표주가와 일치 확인 | B15: ='05_도표1_Valuation'!$C$16-$B$13 -> 0 | F15: 0이면 일치
A17: 자료: 하나증권
A18: 주) 괴리율은 제시 목표주가 대비 실제 주가의 평균 및 최고/최저 괴리를 뜻합니다. 금번 리포트(26.2.5)는 제시 직후여서 괴리율이 산출되지 않았습니다. 표지에는 현재주가 기준일이 2026.02.04로, 본 표에는 의견 제시일이 26.2.5로 표기되어 있습니다 (원문 그대로).

Sheet 20_p6_투자등급_비율공시
A1: 투자등급 관련사항 및 투자의견 비율공시
A2: 하나증권 리포트 p.6 게재 / 투자의견 유효기간: 추천일 이후 12개월 기준
A4: ① 투자의견 비율공시
A5: 투자등급 | B5: BUY (매수) | C5: Neutral (중립) | D5: Reduce (매도) | E5: 합계
A6: 금융투자상품의 비율 | B6: 0.9631 | C6: 0.0369 | D6: 0 | E6: 1
A7: 합계 검산 | B7: =SUM($B$6:$D$6) -> 1 | E7: =SUM($B$6:$D$6)-$E$6 -> 0
A8: 기준일: 2026년 02월 01일
A10: ② 기업의 분류 (투자의견 기준)
A11: 투자의견 | B11: 기준
A12: BUY (매수) | B12: 목표주가가 현주가 대비 15% 이상 상승 여력
A13: Neutral (중립) | B13: 목표주가가 현주가 대비 -15% ~ 15% 등락
A14: Reduce (비중축소) | B14: 목표주가가 현주가 대비 15% 이상 하락 가능
A16: ③ 산업의 분류 (투자의견 기준)
A17: 투자의견 | B17: 기준
A18: Overweight (비중확대) | B18: 업종지수가 현재지수 대비 15% 이상 상승 여력
A19: Neutral (중립) | B19: 업종지수가 현재지수 대비 -15% ~ 15% 등락
A20: Underweight (비중축소) | B20: 업종지수가 현재지수 대비 -15% ~ 15% 등락
A22: ④ 현재 투자의견 적용 검증
A23: 상승여력 (05_도표1_Valuation) | B23: ='05_도표1_Valuation'!$C$17 -> 0.25786164 | C23: → 15% 이상 → BUY 기준 충족
A25: 자료: 하나증권
A26: 주) 원문 산업 분류의 Underweight 기준은 '-15%~15% 등락'으로 인쇄되어 있습니다 (Neutral과 동일 표기). 원문 그대로 옮겼습니다.

Sheet D1_컨센서스_괴리율
A1: 하나증권 추정치 vs 시장 컨센서스 (파생)
A2: 리포트에 없는 파생 표입니다. 02_p1_Consensus 의 컨센서스와 추정 재무제표를 비교해 괴리율을 계산합니다.
A4: 구분 | B4: 항목 | C4: 2025F | D4: 2026F | E4: 비고
A5: 하나증권 | B5: 하나증권 매출액 | C5: ='15_p5_손익계산서'!$D$5 -> 220.19 | D5: ='15_p5_손익계산서'!$E$5 -> 302.9 | E5: 15_p5_손익계산서 참조
A6: 하나증권 | B6: 하나증권 영업이익 | C6: ='15_p5_손익계산서'!$D$9 -> 60.05 | D6: ='15_p5_손익계산서'!$E$9 -> 93.7 | E6: 15_p5_손익계산서 참조
A7: 하나증권 | B7: 하나증권 EPS | C7: ='17_p5_투자지표'!$D$6 -> 2638 | D7: ='17_p5_투자지표'!$E$6 -> 3850 | E7: 17_p5_투자지표 참조
A8: 컨센서스 | B8: 컨센서스 매출액 | C8: ='02_p1_Consensus'!$C$6 -> 215.9 | D8: ='02_p1_Consensus'!$D$6 -> 282.7 | E8: 02_p1_Consensus 참조
A9: 컨센서스 | B9: 컨센서스 영업이익 | C9: ='02_p1_Consensus'!$C$7 -> 56.9 | D9: ='02_p1_Consensus'!$D$7 -> 79.6 | E9: 02_p1_Consensus 참조
A10: 컨센서스 | B10: 컨센서스 EPS | C10: ='02_p1_Consensus'!$C$9 -> 2555 | D10: ='02_p1_Consensus'!$D$9 -> 3563 | E10: 02_p1_Consensus 참조
A11: 괴리율 | B11: 매출액 괴리율 | C11: =$C$5/$C$8-1 -> 0.01987031 | D11: =$D$5/$D$8-1 -> 0.071453838 | E11: 하나증권 추정 ÷ 컨센서스 − 1
A12: 괴리율 | B12: 영업이익 괴리율 | C12: =$C$6/$C$9-1 -> 0.055360281 | D12: =$D$6/$D$9-1 -> 0.17713568 | E12: 하나증권 추정 ÷ 컨센서스 − 1
A13: 괴리율 | B13: EPS 괴리율 | C13: =$C$7/$C$10-1 -> 0.032485323 | D13: =$D$7/$D$10-1 -> 0.080550098 | E13: 하나증권 추정 ÷ 컨센서스 − 1
A15: 자료: 하나증권
A16: 주) 컨센서스 순이익의 지배주주 기준 여부가 원문에 명시되어 있지 않아 매출액·영업이익·EPS만 비교했습니다.

Sheet D2_추정치_변경폭
A1: 추정치 변경 폭 — 도표 4 (수정 후) vs 도표 5 (수정 전)
A2: 겹치는 기간만 비교했습니다. 초록 글씨는 10·11번 시트를 참조한 계산값입니다.
A4: 구분 | B4: 4Q25 | C4: 2025 | D4: 2026F | G4: 비고
A5: 매출액 (수정 후) | B5: ='08_도표4_분기실적_수정후'!$E$5 -> 72.3 | C5: ='08_도표4_분기실적_수정후'!$K$5 -> 220.1 | D5: ='08_도표4_분기실적_수정후'!$L$5 -> 302.9 | G5: 도표 4
A6: 매출액 (수정 전) | B6: ='09_도표5_분기실적_수정전'!$I$5 -> 68.2 | C6: ='09_도표5_분기실적_수정전'!$K$5 -> 216.1 | D6: ='09_도표5_분기실적_수정전'!$L$5 -> 301.6 | G6: 도표 5
A7: 변경 폭 (금액) | B7: =B$5-B$6 -> 4.1 | C7: =C$5-C$6 -> 4 | D7: =D$5-D$6 -> 1.3 | G7: 수정 후 − 수정 전
A8: 변경 폭 (%) | B8: =B$5/B$6-1 -> 0.060117302 | C8: =C$5/C$6-1 -> 0.018509949 | D8: =D$5/D$6-1 -> 0.0043103448 | G8: 본문: 4Q25 실적이 하나증권 추정치를 6% 상회
A10: 영업이익 (수정 후) | B10: ='08_도표4_분기실적_수정후'!$E$15 -> 21.9 | C10: ='08_도표4_분기실적_수정후'!$K$15 -> 60 | D10: ='08_도표4_분기실적_수정후'!$L$15 -> 93.7 | G10: 도표 4
A11: 영업이익 (수정 전) | B11: ='09_도표5_분기실적_수정전'!$I$15 -> 19.4 | C11: ='09_도표5_분기실적_수정전'!$K$15 -> 57.5 | D11: ='09_도표5_분기실적_수정전'!$L$15 -> 86.5 | G11: 도표 5
A12: 변경 폭 (금액) | B12: =B$10-B$11 -> 2.5 | C12: =C$10-C$11 -> 2.5 | D12: =D$10-D$11 -> 7.2 | G12: 수정 후 − 수정 전
A13: 변경 폭 (%) | B13: =B$10/B$11-1 -> 0.12886598 | C13: =C$10/C$11-1 -> 0.043478261 | D13: =D$10/D$11-1 -> 0.083236994 | G13: 본문: 4Q25 영업이익이 하나증권 추정치를 13% 상회
A15: 데이터센터 매출 추정 변경
A16: 구분 | B16: 4Q25 | C16: 2025 | D16: 2026F | G16: 비고
A17: 데이터센터 (수정 후) | B17: ='08_도표4_분기실적_수정후'!$E$8 -> 54.4 | C17: ='08_도표4_분기실적_수정후'!$K$8 -> 148.4 | D17: ='08_도표4_분기실적_수정후'!$L$8 -> 218.1
A18: 데이터센터 (수정 전) | B18: ='09_도표5_분기실적_수정전'!$I$8 -> 48.4 | C18: ='09_도표5_분기실적_수정전'!$K$8 -> 142.4 | D18: ='09_도표5_분기실적_수정전'!$L$8 -> 226.1
A19: 변경 폭 (%) | B19: =B$17/B$18-1 -> 0.12396694 | C19: =C$17/C$18-1 -> 0.042134831 | D19: =D$17/D$18-1 -> -0.035382574 | G19: 2026F는 소폭 하향, 2025는 상향
A21: 자료: 하나증권 도표 4·5 기준, 변경 폭은 자체 계산
A22: 주) 1Q25~3Q25는 두 표 모두 확정 실적이라 동일합니다. 4Q25는 '수정 전' 표에서 전망치(4Q25F)였고 '수정 후' 표에서 확정 실적이므로, 변경 폭이 곧 실적의 추정치 대비 서프라이즈 폭입니다.

Sheet D3_매출분해_대체분류
A1: 매출 분해 — 대체 분류 (파생)
A2: 리포트 도표 8은 어플리케이션 기준입니다. 여기에는 리서치 자료로 확보한 다른 기준의 분기 매출 분해를 모았습니다. 원문에 없는 자료이므로 별도 시트로 분리했습니다.
A4: ③ 메모리 / 비메모리 매출 (IM증권 2025.10.13) — 대체 분류
A5: 구분 | B5: 1Q23 | C5: 2Q23 | D5: 3Q23 | E5: 4Q23 | F5: 1Q24 | G5: 2Q24 | H5: 3Q24 | I5: 4Q24 | J5: 1Q25 | K5: 2Q25 | L5: 3Q25E | M5: 4Q25E
A6: 총매출 | B6: 46.4 | C6: 36 | D6: 32.9 | E6: 24.9 | F6: 35.1 | G6: 49.8 | H6: 50.4 | I6: 39.3 | J6: 31.7 | K6: 51.7 | L6: 69.5 | M6: 64
A7: Memory | B7: 10.1 | C7: 6 | D7: 6.6 | E7: 5 | F7: 5 | G7: 7.5 | H7: 8 | I7: 5.1 | J7: 5.9 | K7: 5.8 | L7: 4.5 | M7: 5
A8: Non-Memory | B8: 34 | C8: 26.9 | D8: 22.6 | E8: 19 | F8: 29.7 | G8: 41.7 | H8: 41.9 | I8: 33.7 | J8: 25.4 | K8: 45.7 | L8: 55 | M8: 49
A9: Memory 비중 | B9: =B$7/B$6 -> 0.21767241 | C9: =C$7/C$6 -> 0.16666667 | D9: =D$7/D$6 -> 0.2006079 | E9: =E$7/E$6 -> 0.20080321 | F9: =F$7/F$6 -> 0.14245014 | G9: =G$7/G$6 -> 0.15060241 | H9: =H$7/H$6 -> 0.15873016 | I9: =I$7/I$6 -> 0.12977099 | ... M9: =M$7/M$6 -> 0.078125
A10: 주) 3Q25E·4Q25E는 IM증권 추정치입니다. 실제 3Q25 매출은 64.5, 4Q25는 72.3십억원이었습니다 (하나증권 도표 4).
A12: ④ AI / 비AI 매출 (미래에셋증권 2026.01.29) — 일부 분기만 공개
A13: 구분 | B13: 1Q24 | C13: 3Q24 | D13: 4Q24 | E13: 2Q25 | F13: 3Q25
A14: AI 매출 | B14: 8.9 | C14: 17.6 | D14: 27.5 | E14: 34.5 | F14: 43
A15: 비AI 매출 | B15: 26.2 | C15: 32.8 | D15: 11.8 | E15: 17.2 | F15: 21.5
A16: AI 비중 | B16: =B$14/(B$14+B$15) -> 0.25356125 | C16: =C$14/(C$14+C$15) -> 0.34920635 | D16: =D$14/(D$14+D$15) -> 0.69974555 | E16: =E$14/(E$14+E$15) -> 0.66731141 | F16: =F$14/(F$14+F$15) -> 0.66666667
A17: 주) 리포트 본문의 'AI 반도체용 테스트 소켓 매출 비중 4Q25 75% (전분기 대비 +8%p)'와는 정의가 다릅니다. 미래에셋 기준은 AI 관련 전체 매출이고, 하나증권 본문은 테스트 소켓 내 AI 비중입니다.
A42: 출처 (셀 단위 근거)
A43: 항목 | B43: 출처 | I43: URL / 접수번호
A44: 메모리/비메모리 1Q23~4Q25E | B44: IM증권 2025.10.13 리포트. Memory + Non-Memory + Non Socket = 총매출로 검산 일치 | I44: imfnsec PDF
A45: AI/비AI 일부 분기 | B45: 미래에셋증권 2026.01.29 리포트. AI + 비AI = 총매출로 검산 일치 | I45: miraeasset PDF

Sheet Z_출처_공시_리서치
A1: 출처 정리 — 공시 자료 및 리서치
A2: 리포트에 인쇄되지 않아 외부에서 끌어온 수치의 출처입니다. 수집 시점 2026-07-25.
A4: ① 외부에서 확보해 워크북에 채운 데이터
A5: # | B5: 데이터 항목 | C5: 구간 | D5: 출처 | E5: URL / 접수번호 | F5: 들어간 시트
A6: 1 | B6: 연간 매출액·영업이익 | C6: 2018년 | D6: 디일렉(THE ELEC) 2019.03 기사 | E6: thelec.kr/news/articleView.html?idxno=19668 | F6: 16번
A7: 2 | B7: 연간 매출액·영업이익 | C7: 2019~2021년 | D7: 디일렉(THE ELEC) 2023.02.02 기사 — 2019년 877억/20억, 2020년 1,218억/181억, 2021년 1,447억/375억 | E7: thelec.kr/news/articleView.html?idxno=19668 | F7: 16번
A8: 3 | B8: 연간 매출액 | C8: 2022년 | D8: IM증권 2025.10.13 리포트 FY22 178.9십억원 | E8: m.imfnsec.com/upload/R_E08/2025/10/[13065339]_095340.pdf | F8: 16번
A9: 4 | B9: 연간 영업이익 | C9: 2022년 | D9: 하나증권 4Q25 실적리뷰 2023년 영업이익증가율 -80.86% 역산 (55.9). 미래에셋 2026.01.29 리포트 표기 56과 정합 | E9: 본 리포트 추정재무제표 | F9: 16번
A10: 5 | B10: 연간 매출·영업이익 교차검증 | C10: 2020~2024년 | D10: 미래에셋증권 2026.01.29 리포트 (122/145/179/140/174, 18/38/56/11/45) | E10: securities.miraeasset.com/bbs/download/2142114.pdf | F10: 16번
A11: 6 | B11: 분기 매출액·영업이익 | C11: 1Q23~4Q23 | D11: 미래에셋증권 2026.01.29 및 IM증권 2025.10.13 리포트 (두 리포트 수치 동일). 3Q23 영업이익 -8.0은 하나증권 도표5의 YoY -273%와 정확히 일치 | E11: miraeasset / imfnsec PDF | F11: 14번
A12: 7 | B12: 분기 매출·영업이익·순이익 | C12: 1Q26 확정 | D12: 연결재무제표기준영업(잠정)실적(공정공시) 2026.04.27 — 매출 683억 / 영업이익 236억 / 순이익 206억 | E12: DART 접수번호 20260427900108 | F12: 14번
A13: 8 | B13: 분기말 종가 | C13: 1Q22~2Q26 | D13: stockanalysis.com 분기 시가총액 ÷ 주식수 역산. MarketScreener 연말 무수정 종가(35,350 / 31,350 / 80,300 / 72,100)와 정확히 일치하고 전 분기가 호가단위에 떨어짐 | E13: stockanalysis.com/quote/kosdaq/095340 | F13: 06·14번
A14: 9 | B14: 상장주식수 이력 | C14: 2022~2026년 | D14: 2023년 8월 유상증자 신주 3,797,587주(발행가 52,665원) — 증자 전 17,339,471주 / 후 21,137,058주 / 2026년 21,197,058주 | E14: SK증권 2023.07.10 리포트, wisereport 기업현황 | F14: 06·14번
A15: 10 | B15: 분기 Memory / Non-Memory 매출 | C15: 1Q23~4Q25E | D15: IM증권 2025.10.13 리포트. Memory + Non-Memory + Non Socket = 총매출 검산 일치 | E15: m.imfnsec.com/upload/R_E08/2025/10/[13065339]_095340.pdf | F15: 15번
A16: 11 | B16: 분기·연간 Non Socket 매출 | C16: 1Q23~4Q25E, FY22~FY26E | D16: IM증권 2025.10.13 리포트. 도표 10의 Socket / Non-socket 구분에 해당 | E16: m.imfnsec.com/upload/R_E08/2025/10/[13065339]_095340.pdf | F16: 17번
A17: 12 | B17: 분기 AI / 비AI 매출 | C17: 1Q24·3Q24·4Q24·2Q25·3Q25 | D17: 미래에셋증권 2026.01.29 리포트. AI + 비AI = 총매출 검산 일치 | E17: securities.miraeasset.com/bbs/download/2142114.pdf | F17: 15번
A18: 13 | B18: 1Q26 실적 교차검증 | C18: 1Q26 | D18: GoInsider 종목 페이지 (DART 잠정실적 공시 인용). QoQ -5.6%가 68.3/72.3-1과 일치 | E18: goinsider.kr/stock/00572905 | F18: 14번
A20: ② 확보하지 못한 데이터와 이유
A21: # | B21: 데이터 항목 | C21: 구간 | D21: 왜 못 채웠는지 | E21: 채우는 방법
A22: 1 | B22: 분기 매출액·영업이익 | C22: 1Q19~4Q22 | D22: 무료로 열람 가능한 리서치·집계 사이트가 1Q23부터만 분기 시계열을 제공합니다. stockanalysis는 2020년 이전을 유료 구간으로 막아 두었습니다. | E22: DART 분기·반기보고서를 열어 누적 수치를 차분하거나, DART Open API 키로 fnlttSinglAcnt를 호출
A23: 2 | B23: 어플리케이션별 매출 | C23: 1Q21~4Q23 | D23: 데이터센터·스마트폰 같은 구분은 하나증권 자체 분류로 공시 항목이 아닙니다. 과거 하나증권 리포트에 표로 실려 있을 수 있으나 hanaw.com이 robots.txt로 자동 수집을 막고 있습니다. | E23: 하나증권 과거 ISC 리포트(2025.05.21, 2025.11.26 등)를 직접 내려받아 도표를 확인
A24: 3 | B24: Socket / Non-socket 매출 | C24: 1Q19~4Q22 | D24: IM증권 리포트가 1Q23부터만 제공합니다. FY22 Non Socket은 0.0으로 표기되어 있어 그 이전에는 비소켓 매출이 사실상 없었던 것으로 보입니다. | E24: DART 사업보고서 「II. 사업의 내용 > 4. 매출 및 수주상황」의 품목별 매출
A25: 4 | B25: 월별 주가 및 KOSDAQ 상대지수 | C25: 25.1~26.1 | D25: 월별 시세를 제공하는 사이트(네이버금융, 야후파이낸스, stooq 등)가 모두 자동 수집을 차단하고 있습니다. | E25: KRX 정보데이터시스템에서 일별 시세를 내려받아 월말 종가만 추출
A26: 5 | B26: 2020~2021년 상장주식수 | C26: 2020~2021년 | D26: 증자·자기주식 이력을 확인할 수 있는 무료 출처를 찾지 못했습니다. | E26: DART 사업보고서 「주식의 총수」 항목
A28: ③ ISC의 DART 공시 정보 (직접 열어볼 때 참고)
A29: # | B29: 구분 | C29: 값 | D29: 설명
A30: 1 | B30: DART 고유번호 | C30: 00572905 | D30: 공시통합검색·Open API에서 ISC를 지정할 때 쓰는 번호
A31: 2 | B31: 종목코드 | C31: 095340 | D31: KOSDAQ 상장
A32: 3 | B32: 사업보고서 (2025.12) | C32: 20260318000018 | D32: 품목별 매출·주식의 총수 등 연간 확정 정보
A33: 4 | B33: 분기보고서 (2026.03) | C33: 20260515000092 | D33: 1Q26 재무제표
A34: 5 | B34: 연결영업(잠정)실적 (2026.04.27) | C34: 20260427900108 | D34: 1Q26 매출 683억 / 영업이익 236억 / 순이익 206억
A35: 6 | B35: 보고서 열람 URL 형식 | C35: dart.fss.or.kr/dsaf001/main.do?rcpNo=(접수번호) | D35: 브라우저로는 열리지만 이 작업에서는 robots.txt 때문에 자동 수집하지 않았습니다
A37: ④ Forward EPS 분기 수치의 출처 — DART 정기보고서 (반영 완료)
A38: # | B38: 보고서 | C38: 접수번호 | D38: 가져온 항목 | E38: 채워진 칸
A39: 1 | B39: 분기보고서 (2025.03) | C39: 20250515000342 | D39: 연결 손익계산서: 매출원가·판관비·세전이익·지배주주순이익 | E39: Forward EPS 1Q25 열
A40: 2 | B40: 반기보고서 (2025.06) | C40: 20250814000396 | D40: 연결 손익계산서 (상반기 누적) — 1Q25를 빼면 2Q25 | E40: Forward EPS 2Q25 열
A41: 3 | B41: 분기보고서 (2025.09) | C41: 20251114000063 | D41: 연결 손익계산서 (3분기 누적) — 상반기를 빼면 3Q25 | E41: Forward EPS 3Q25 열
A42: 4 | B42: 사업보고서 (2025.12) | C42: 20260318000018 | D42: 연결 손익계산서 (연간) — 3분기 누적을 빼면 4Q25. 품목별 매출도 여기 있음 | E42: Forward EPS 4Q25 열 · 도표 10
A43: 5 | B43: 분기보고서 (2026.03) | C43: 20260515000092 | D43: 연결 손익계산서: 1Q26 매출원가·판관비·세전이익 | E43: Forward EPS 1Q26P 열
A45: 주) 위 5개 보고서의 IFRS 원문 XBRL 을 직접 파싱해 연결 기준 손익 항목을 가져왔습니다. 2Q25·3Q25 는 각 보고서의 3개월 컨텍스트를, 4Q25 는 사업보고서 연간에서 3분기 누적을 뺀 값을 썼습니다. 분기 합계가 2025년 연간 확정치와 소수점까지 일치합니다.
A46: 주) 아직 남아 있는 회색 칸 — ① 11_도표7 의 2020~2022년 분기 영업이익 (해당 연도 정기보고서 필요), ② Forward EPS 의 1Q26P 어플리케이션별 분해 (공표되지 않음), ③ 14_도표10 의 1Q19~4Q22 Socket/Non-socket (품목별 매출은 XBRL 이 아니라 사업보고서 본문 「매출 및 수주상황」에 있어 원문 HTML/PDF 가 필요합니다).
A48: ⑤ 원문 차트 목록과 재현 범위
A49: 도표 | B49: 제목 | C49: 축 / 계열 | D49: 기간 | E49: 재현 결과
A50: 도표 2 | B50: ISC 12MF P/E Band | C50: 수정주가, 57.0x / 45.1x / 33.3x / 21.4x / 5.0x | D50: 21.1 ~ 26.1 | E50: 밴드 배수만 06번 시트에 기록 (주가 시계열 미인쇄)
A51: 도표 3 | B51: ISC 12MF P/B Band | C51: 수정주가, 5.1x / 4.2x / 3.2x / 2.3x / 1.3x | D51: 21.1 ~ 26.1 | E51: 밴드 배수만 07번 시트에 기록
A52: 도표 7 | B52: 분기 영업이익 vs 시가총액 추이 | C52: 영업이익(우), 시가총액(좌), 십억원 | D52: 20.1 ~ 26.1 | E52: 11번 시트에서 재현 (영업이익 1Q23~ / 시가총액 1Q22~)
A53: 도표 8 | B53: 어플리케이션 별 매출 비중 추이 | C53: 데이터센터/스마트폰/PC·노트북/Auto/Wearable/LSI/기타 | D53: 1Q21 ~ 3Q25 | E53: 12번 시트에서 1Q24 이후 재현
A54: 도표 9 | B54: 연간 실적 추이 및 전망 | C54: 매출액(좌), OPM(우) | D54: 2019 ~ 2027F | E54: 13번 시트에서 2018 이후 전 구간 재현
A55: 도표 10 | B55: 제품별 매출 추이 및 전망 | C55: Socket / Non-socket | D55: 1Q19 ~ 1Q26 | E55: 14번 시트에서 1Q23~4Q25 재현
A56: p.1 Stock Price | B56: ISC 주가 vs 상대지수 | C56: ISC(좌), 상대지수(우) | D56: 25.1 ~ 26.1 | E56: 03번 시트에서 분기말 종가·시가총액으로 대체
A58: 주) 원문 차트에는 데이터 라벨이 없어 눈금 기준 추정 수치는 넣지 않았습니다. 표에 인쇄된 수치와 공시·리서치로 교차검증된 값만 사용했습니다.
A60: 주) 외부에서 가져온 수치는 모두 파란 글씨(전사값)로 넣었고, 가능한 경우 두 개 이상의 출처가 일치하는 것을 확인했습니다. 특히 3Q23 영업이익(-8.0십억원)과 2022년 매출액(178.9십억원)은 하나증권 리포트의 증가율로 역산한 값과 정확히 맞아떨어집니다.
A61: 주) 분기말 종가는 대부분 「분기 시가총액 ÷ 주식수」 역산값입니다. 네 개 연말 종가가 다른 출처와 정확히 일치하고 전 분기 값이 호가단위(50원)에 떨어지지만, 1차 출처의 직접 인용은 아니라는 점을 감안해 주세요.
A62: 주) 시가총액은 한국식(상장주식수 × 종가)으로 계산했습니다. stockanalysis 등 해외 사이트는 자기주식을 제외한 주식수를 쓰기 때문에 같은 종가에서도 약 3.5% 작게 나옵니다. 하나증권 리포트와 맞추려면 한국식이 맞습니다.
A63: 주) 이 워크북은 하나증권 리서치 자료와 공개 자료를 정리한 학습·분석용이며 투자 권유가 아닙니다.
